Workbook

Sheet Main
A1: Shenzou International
A2: numbers in mio RMB | I2: Price HKD | J2: 35.46
I3: Price RMB | J3: =+J2*J10 -> 31.2048
I4: Shares | J4: 1503.2224 | K4: Q226
B5: IR | I5: MC | J5: =+J3*J4 -> 46907.754
B6: 2313.HK | I6: Cash | J6: =202.802+15279.98+11297.186 -> 26779.968 | K6: Q226
I7: Debt | J7: 197 | K7: Q226
I8: EV | J8: =+J5-J6+J7 -> 20324.786
B9: Notes
B10: Produce Apparel and knit wear | I10: HKD/RMB | J10: 0.88
B11: produce finished products based on designs by costumers
B12: and specialized components e.g. for Nike | I12: Workforce | J12: 101720
B14: 4 Big Costumers: | D14: Revenue | E14: % of Rev | F14: Guess
B15: Costumer A | D15: 4333.071 | E15: =+D15/Model!$I$7 -> 0.28952023 | F15: Uniqlo
B16: Costumer B | D16: 3435.558 | E16: =+D16/Model!$I$7 -> 0.22955164 | F16: Nike
B17: Costumer C | D17: 2992.45 | E17: =+D17/Model!$I$7 -> 0.19994476 | F17: Adidas
B18: Costumer D | D18: 1532.209 | E18: =+D18/Model!$I$7 -> 0.1023767 | F18: Puma
B19: Total | D19: =+SUM(D15:D18) -> 12293.288 | E19: =+D19/Model!$I$7 -> 0.82139333

Sheet Model
A1: Main
C2: H122 | D2: H222 | E2: H123 | F2: H223 | G2: H124 | H2: H224 | I2: H125 | J2: H225 | K2: H126 | L2: H226
B3: Sportswear | E3: 8560.723 | G3: 9212.546 | I3: 10128.586 | K3: 9041.833
B4: Casual wear | E4: 2299.766 | G4: 2760.739 | I4: 3792.133 | K4: 3962.863
B5: Lingerie wear | E5: 612.784 | G5: 903.182 | I5: 940.211 | K5: 997.752
B6: Other knitwear | E6: 88.689 | G6: 99.504 | I6: 105.454 | K6: 176.729
B7: Revenue | C7: =+SUM(C3:C6) -> 0 | D7: =+SUM(D3:D6) -> 0 | E7: =+SUM(E3:E6) -> 11561.962 | F7: =+SUM(F3:F6) -> 0 | G7: =+SUM(G3:G6) -> 12975.971 | H7: =+SUM(H3:H6) -> 0 | I7: 14966.384 | K7: 14179.177
B8: COGS | E8: 8967.058 | G8: 9214.502 | I8: 10908.366 | K8: 10981.713
B9: Gross Profit | C9: =+C7-C8 -> 0 | D9: =+D7-D8 -> 0 | E9: =+E7-E8 -> 2594.904 | F9: =+F7-F8 -> 0 | G9: =+G7-G8 -> 3761.469 | H9: =+H7-H8 -> 0 | I9: =+I7-I8 -> 4058.018 | J9: =+J7-J8 -> 0 | K9: =+K7-K8 -> 3197.464
B10: Other Income | E10: 507.389 | G10: 635.463 | I10: 799.397 | K10: 681.355
B11: Selling & Distrinution | E11: 81.135 | G11: 84.837 | I11: 108.757 | K11: 123.086
B12: Administrative Expenses | E12: 913.688 | G12: 943.697 | I12: 1081.8 | K12: 1064.184
B13: Operating Income | C13: =+C9+C10-SUM(C11:C12) -> 0 | D13: =+D9+D10-SUM(D11:D12) -> 0 | E13: =+E9+E10-SUM(E11:E12) -> 2107.47 | F13: =+F9+F10-SUM(F11:F12) -> 0 | G13: =+G9+G10-SUM(G11:G12) -> 3368.398 | H13: =+H9+H10-SUM(H11:H12) -> 0 | I13: =+I9+I10-SUM(I11:I12) -> 3666.858 | J13: =+J9+J10-SUM(J11:J12) -> 0 | K13: =+K9+K10-SUM(K11:K12) -> 2691.549
B14: Finance cost | E14: 146.258 | G14: 191.389 | I14: 175.886 | K14: 156.019
B15: Other gains net | E15: 376.659 | G15: 69.64 | I15: 139.196 | K15: -497.095
B16: earning of subsidaries | E16: 10.553 | G16: 2.56 | I16: 1.952 | K16: 1.439
B17: Pretax Income | C17: =+C13-C14+C15+C16 -> 0 | D17: =+D13-D14+D15+D16 -> 0 | E17: =+E13-E14+E15+E16 -> 2348.424 | F17: =+F13-F14+F15+F16 -> 0 | G17: =+G13-G14+G15+G16 -> 3249.209 | H17: =+H13-H14+H15+H16 -> 0 | I17: =+I13-I14+I15+I16 -> 3632.12 | J17: =+J13-J14+J15+J16 -> 0 | K17: =+K13-K14+K15+K16 -> 2039.874
B18: Tax Expense | E18: 221.595 | G18: 318.181 | I18: 455.284 | K18: 135.311
B19: Net Income | C19: =+C17-C18 -> 0 | D19: =+D17-D18 -> 0 | E19: =+E17-E18 -> 2126.829 | F19: =+F17-F18 -> 0 | G19: =+G17-G18 -> 2931.028 | H19: =+H17-H18 -> 0 | I19: =+I17-I18 -> 3176.836 | J19: =+J17-J18 -> 0 | K19: =+K17-K18 -> 1904.563
B21: EPS | C21: =+C19/C22 -> #DIV/0! | D21: =+D19/D22 -> #DIV/0! | E21: =+E19/E22 -> 1.4148465 | F21: =+F19/F22 -> #DIV/0! | G21: =+G19/G22 -> 1.9498299 | H21: =+H19/H22 -> #DIV/0! | I21: =+I19/I22 -> 2.1133506 | J21: =+J19/J22 -> #DIV/0! | K21: =+K19/K22 -> 1.2669868
B22: Shares | E22: 1503.2224 | G22: 1503.2224 | I22: 1503.2224 | K22: 1503.2224
B25: Revenue Growth | E25: =+E7/C7-1 -> #DIV/0! | F25: =+F7/D7-1 -> #DIV/0! | G25: =+G7/E7-1 -> 0.12229836 | H25: =+H7/F7-1 -> #DIV/0! | I25: =+I7/G7-1 -> 0.15339222 | J25: =+J7/H7-1 -> #DIV/0! | K25: =+K7/I7-1 -> -0.052598343
B26: Gross Margin | E26: =+E9/E7 -> 0.22443457 | F26: =+F9/F7 -> #DIV/0! | G26: =+G9/G7 -> 0.28987958 | H26: =+H9/H7 -> #DIV/0! | I26: =+I9/I7 -> 0.27114218 | J26: =+J9/J7 -> #DIV/0! | K26: =+K9/K7 -> 0.2255042
B27: Operating Margin | E27: =+E13/E7 -> 0.18227616 | F27: =+F13/F7 -> #DIV/0! | G27: =+G13/G7 -> 0.25958736 | H27: =+H13/H7 -> #DIV/0! | I27: =+I13/I7 -> 0.24500628 | J27: =+J13/J7 -> #DIV/0! | K27: =+K13/K7 -> 0.18982406
B28: Tax Rate | E28: =+E18/E17 -> 0.094359025 | F28: =+F18/F17 -> #DIV/0! | G28: =+G18/G17 -> 0.09792568 | H28: =+H18/H17 -> #DIV/0! | I28: =+I18/I17 -> 0.12534938 | J28: =+J18/J17 -> #DIV/0! | K28: =+K18/K17 -> 0.066333019
