Workbook

Sheet Main
A1: Inditex
A2: numbers in mio USD
I3: Price | J3: 54.85
B4: ITX.MC | C4: Start FY | D4: 45323 | I4: Shares | J4: 3115.9215 | K4: Q226
B5: Investors | C5: End FY | D5: 45322 | I5: MC | J5: =J4*J3 -> 170908.3
I6: Cash | J6: =6038+4361 -> 10399 | K6: Q226
B7: Segments/Brands | C7: % of Rev. | D7: Products | E7: Customers | F7: Competitiors | I7: Debt | J7: 1 | K7: Q226
B8: Zara | C8: =Model!Y22/Model!$Y$29 -> 0.724678 | D8: Fast Fashion | I8: EV | J8: =J5-J6+J7 -> 160510.3
B9: Paul&Bear | C9: =Model!Y23/Model!$Y$29 -> 0.065624391 | D9: Fast Fashion
B10: Massimo Duti | C10: =Model!Y24/Model!$Y$29 -> 0.05115865 | D10: Fast Fashion | I10: CEO: Oscar Garcia Maceiras
B11: Bershka | C11: =Model!Y25/Model!$Y$29 -> 0.0729129 | D11: Fast Fashion
B12: Stardivarius | C12: =Model!Y26/Model!$Y$29 -> 0.064928923 | D12: Fast Fashion
B13: Oysho | C13: =Model!Y27/Model!$Y$29 -> 0.020697137 | D13: Fast Fashion
B17: Notes
B18: New Brand: Lefties - high budget Zara pieces
B19: John Galliano will desing collections for Zara:
B20: https://www.businessoffashion.com/articles/retail/zara-taps-john-galliano-to-design-seasonal-collections/

Sheet Model
A1: Main
C2: Q123 | D2: Q223 | E2: Q323 | F2: Q423 | G2: Q124 | H2: Q224 | I2: Q324 | J2: Q424 | K2: Q125 | L2: Q225 | M2: Q325 | N2: Q425 | O2: Q126 | P2: Q226 | Q2: Q326 | R2: Q426 | T2: 18 | U2: =T2+1 -> 19 | V2: =U2+1 -> 20 | W2: =V2+1 -> 21 | X2: =W2+1 -> 22 | Y2: =X2+1 -> 23 | Z2: =Y2+1 -> 24 | AA2: =Z2+1 -> 25 | AB2: =AA2+1 -> 26 | ... AE2: =AD2+1 -> 29
B3: Zara Stores | I3: =1588+203+407 -> 2198 | L3: =1534+379+210 -> 2123 | M3: =1528+380+213 -> 2121 | O3: =1495+376+217 -> 2088 | P3: =1487+374+223 -> 2084 | Z3: =1550+391+209 -> 2150 | AA3: =1500+374+215 -> 2089
B4: Pull&Bear Stores | I4: 812 | L4: 801 | M4: 800 | O4: 792 | P4: 789 | Z4: 800 | AA4: 791
B5: Massimo Dutti Stores | I5: 542 | L5: 518 | M5: 519 | O5: 509 | P5: 509 | Z5: 528 | AA5: 511
B6: Bershka Stores | I6: 855 | L6: 856 | M6: 859 | O6: 851 | P6: 849 | Z6: 854 | AA6: 852
B7: Stradivarius Stores | I7: 845 | L7: 839 | M7: 839 | O7: 837 | P7: 835 | Z7: 835 | AA7: 834
B8: Oysho Stores | I8: 407 | L8: 391 | M8: 389 | O8: 379 | P8: 378 | Z8: 396 | AA8: 383
B9: Uterqüe Stores | I9: 203 | L9: 0 | M9: 0 | N9: 0 | O9: 0 | P9: 0 | Z9: 0 | AA9: 0
B10: Number of Stores | C10: 5801 | D10: 5745 | G10: 5698 | H10: 5667 | I10: 5659 | J10: 5563 | K10: 5562 | L10: =+SUM(L3:L9) -> 5528 | M10: =+SUM(M3:M9) -> 5527 | N10: =+SUM(N3:N9) -> 0 | O10: =+SUM(O3:O9) -> 5456 | P10: =+SUM(P3:P9) -> 5444 | T10: 7490 | U10: 7469 | V10: 6829 | W10: 6477 | X10: 5815 | Y10: 5692 | Z10: 5563 | AA10: 5460 | AB10: =AA10*0.97 -> 5296.2 | AC10: =AB10*0.97 -> 5137.314 | AD10: =AC10*0.97 -> 4983.1946 | AE10: =AD10*0.97 -> 4833.6987
B11: Selling Space in Square Meter | T11: 4962.081 | U11: 5086.732 | V11: 4826.556 | W11: 4742.157 | X11: 4473.358 | Y11: 4557.17 | Z11: 4650.575 | AA11: 4650.575
B12: Sales in Stores | T12: =T29-T15 -> 22945 | U12: =U29-U15 -> 24387 | V12: =V29-V15 -> 13802 | W12: =W29-W15 -> 20216 | X12: =X29-X15 -> 24769 | Y12: =Y29-Y15 -> 26847 | Z12: =Z29-Z15 -> 28432 | AA12: =AA29-AA15 -> 29149.92 | AB12: =AB13*AB10 -> 29689.194 | AC12: =AC13*AC10 -> 30238.444 | AD12: =AD13*AD10 -> 30797.855 | AE12: =AE13*AE10 -> 31367.615
B13: Revenue per Store | T13: =T12/T10 -> 3.0634179 | U13: =U12/U10 -> 3.2650957 | V13: =V12/V10 -> 2.0210865 | W13: =W12/W10 -> 3.1211981 | X13: =X12/X10 -> 4.2595013 | Y13: =Y12/Y10 -> 4.7166198 | Z13: =Z12/Z10 -> 5.1109114 | AA13: =AA12/AA10 -> 5.3388132 | AB13: =AA13*1.05 -> 5.6057538 | AC13: =AB13*1.05 -> 5.8860415 | AD13: =AC13*1.05 -> 6.1803436 | AE13: =AD13*1.05 -> 6.4893608
B14: Revenue per Square Meter | T14: =T12/T11 -> 4.624068 | U14: =U12/U11 -> 4.7942372 | V14: =V12/V11 -> 2.859596 | W14: =W12/W11 -> 4.263039 | X14: =X12/X11 -> 5.5370037 | Y14: =Y12/Y11 -> 5.8911561 | Z14: =Z12/Z11 -> 6.1136526 | AA14: =AA12/AA11 -> 6.2680249
B15: Online Sale | T15: 3200 | U15: 3900 | V15: 6600 | W15: 7500 | X15: 7800 | Y15: 9100 | Z15: 10200 | AA15: =AA17*AA20 -> 10714.08 | AB15: =AB17*AB20 -> 11254.07 | AC15: =AC17*AC20 -> 11821.275 | AD15: =AD17*AD20 -> 12417.067 | AE15: =AE17*AE20 -> 13042.887
B16: App Users | T16: n.a | U16: n.a | V16: 132 | W16: 146 | X16: 149 | Y16: 152 | Z16: 218
B17: Views on Website | T17: n.a | U17: n.a | V17: 5300 | W17: 6200 | X17: =Y17/1.1 -> 5909.0909 | Y17: 6500 | Z17: 8100 | AA17: =Z17*1.01 -> 8181 | AB17: =AA17*1.01 -> 8262.81 | AC17: =AB17*1.01 -> 8345.4381 | AD17: =AC17*1.01 -> 8428.8925 | AE17: =AD17*1.01 -> 8513.1814
B18: Social Media Follower | T18: n.a | U18: n.a | V18: 200 | W18: 228 | X18: 240 | Y18: 251 | Z18: 257
B19: Revenue per App User | T19: n.a | U19: n.a | V19: =V15/V16 -> 50 | W19: =W15/W16 -> 51.369863 | X19: =X15/X16 -> 52.348993 | Y19: =Y15/Y16 -> 59.868421 | Z19: =Z15/Z16 -> 46.788991 | AA19: =AA15/AA16 -> #DIV/0!
B20: Revenue per Website Visit | T20: n.a | U20: n.a | V20: =V15/V17 -> 1.245283 | W20: =W15/W17 -> 1.2096774 | X20: =X15/X17 -> 1.32 | Y20: =Y15/Y17 -> 1.4 | Z20: =Z15/Z17 -> 1.2592593 | AA20: =Z20*1.04 -> 1.3096296 | AB20: =AA20*1.04 -> 1.3620148 | AC20: =AB20*1.04 -> 1.4164954 | AD20: =AC20*1.04 -> 1.4731552 | AE20: =AD20*1.04 -> 1.5320814
B22: Zara | T22: 18021 | U22: 19564 | V22: 14129 | W22: 19586 | X22: 23761 | Y22: 26050 | Z22: 27778 | AA22: 28051
B23: Paul&Bear | T23: 1862 | U23: 1970 | V23: 1425 | W23: 1876 | X23: 2152 | Y23: 2359 | Z23: 2469 | AA23: 2546
B24: Massimo Duti | T24: 1802 | U24: 1900 | V24: 1271 | W24: 1653 | X24: 1593 | Y24: 1839 | Z24: 1960 | AA24: 2019
B25: Bershka | T25: 2240 | U25: 2384 | V25: 1772 | W25: 2177 | X25: 2384 | Y25: 2621 | Z25: 2930 | AA25: 3286
B26: Stardivarius | T26: 1534 | U26: 1750 | V26: 1283 | W26: 1824 | X26: 2056 | Y26: 2334 | Z26: 2664 | AA26: 3002
B27: Oysho | T27: 585 | U27: 604 | V27: 522 | W27: 600 | X27: 623 | Y27: 744 | Z27: 831 | AA27: 960
B28: Uterqüe | T28: 101 | U28: 115 | V28: 0 | W28: 0 | X28: 0 | Y28: 0 | Z28: 0 | AA28: 0
B29: Revenues | C29: 7611 | D29: 9239 | E29: 8758 | F29: 10338 | G29: 8150 | H29: =18065-G29 -> 9915 | I29: =27422-SUM(G29:H29) -> 9357 | J29: 11210 | K29: 8274 | L29: =18357-K29 -> 10083 | M29: =28171-SUM(K29:L29) -> 9814 | N29: =+AA29-SUM(K29:M29) -> 11693 | O29: 8750 | P29: =19755-O29 -> 11005 | T29: =SUM(T22:T28) -> 26145 | U29: =SUM(U22:U28) -> 28287 | V29: =SUM(V22:V28) -> 20402 | W29: =SUM(W22:W28) -> 27716 | X29: =SUM(X22:X28) -> 32569 | Y29: =SUM(Y22:Y28) -> 35947 | Z29: 38632 | AA29: 39864 | AB29: =AB12+AB15 -> 40943.263 | AC29: =AC12+AC15 -> 42059.718 | AD29: =AD12+AD15 -> 43214.922 | AE29: =AE12+AE15 -> 44410.502
B30: COGS | C30: 3008 | D30: 4042 | E30: 3356 | F30: 4780 | G30: 3210 | H30: =7524-G30 -> 4314 | I30: =11132-SUM(G30:H30) -> 3608 | J30: 5157 | K30: 3262 | L30: =7654-K30 -> 4392 | M30: =11361-SUM(K30:L30) -> 3707 | N30: =+AA30-SUM(K30:M30) -> 5281 | O30: 3391 | P30: =8159-O30 -> 4768 | T30: 11329 | U30: 12479 | V30: 9013 | W30: 11902 | X30: 14011 | Y30: 15186 | Z30: 16288 | AA30: 16642
B31: Gross Profit | C31: =C29-C30 -> 4603 | D31: =D29-D30 -> 5197 | E31: =E29-E30 -> 5402 | F31: =F29-F30 -> 5558 | G31: =G29-G30 -> 4940 | H31: =H29-H30 -> 5601 | I31: =I29-I30 -> 5749 | J31: =J29-J30 -> 6053 | ... P31: =P29-P30 -> 6237 | T31: =T29-T30 -> 14816 | U31: =U29-U30 -> 15808 | V31: =V29-V30 -> 11389 | W31: =W29-W30 -> 15814 | X31: =X29-X30 -> 18558 | Y31: =Y29-Y30 -> 20761 | Z31: =Z29-Z30 -> 22344 | AA31: =AA29-AA30 -> 23222
B32: OpEx | C32: 2398 | D32: 2718 | E32: 2617 | F32: 3120 | G32: 2553 | H32: =5467-G32 -> 2914 | I32: =8276-SUM(G32:H32) -> 2809 | J32: 3278 | K32: 2612 | L32: =5584-K32 -> 2972 | M32: =8479-SUM(K32:L32) -> 2895 | N32: =+AA32-SUM(K32:M32) -> 3399 | O32: 2779 | P32: =6048-O32 -> 3269 | T32: 9329 | U32: 8176 | V32: 6807 | W32: 8596 | X32: 9867 | Y32: 10853 | Z32: 11555 | AA32: 11878
B33: Other Operating Income | C33: -10 | D33: -12 | E33: -19 | F33: -18 | G33: -17 | H33: =-34-G33 -> -17 | I33: =-48-H33-G33 -> -14 | J33: -13 | K33: -6 | L33: =-5-K33 -> 1 | M33: =-29-SUM(K33:L33) -> -24 | N33: =+AA33-SUM(K33:M33) -> -48 | O33: -12 | P33: =-35-O33 -> -23 | T33: -30 | U33: -33 | V33: -31 | W33: -35 | X33: -43 | Y33: -59 | Z33: -60 | AA33: -77
B34: Operating Income (EBITDA) | C34: =C31-C32+C33 -> 2195 | D34: =D31-D32+D33 -> 2467 | E34: =E31-E32+E33 -> 2766 | F34: =F31-F32+F33 -> 2420 | G34: =G31-G32+G33 -> 2370 | H34: =H31-H32+H33 -> 2670 | I34: =I31-I32+I33 -> 2926 | J34: =J31-J32+J33 -> 2762 | ... P34: =P31-P32+P33 -> 2945 | T34: =T31-T32+T33 -> 5457 | U34: =U31-U32+U33 -> 7599 | V34: =V31-V32+V33 -> 4551 | W34: =W31-W32+W33 -> 7183 | X34: =X31-X32+X33 -> 8648 | Y34: =Y31-Y32+Y33 -> 9849 | Z34: =Z31-Z32+Z33 -> 10729 | AA34: =AA31-AA32+AA33 -> 11267
B35: Other Results | C35: 0 | D35: 0 | E35: 0 | F35: 0 | G35: 0 | H35: 0 | I35: 0 | J35: 0 | K35: 0 | L35: 0 | M35: 0 | N35: =+AA35-SUM(K35:M35) -> 0 | O35: 0 | P35: 0 | T35: 0 | U35: 0 | V35: 0 | W35: 0 | X35: -231 | Y35: 0 | Z35: 0 | AA35: 0
B36: D&A | C36: 712 | D36: 786 | E36: 739 | F36: 804 | G36: 734 | H36: =1499-G36 -> 765 | I36: 794 | J36: 880 | K36: 752 | L36: =1542-K36 -> 790 | M36: =2359-SUM(K36:L36) -> 817 | N36: =+AA36-SUM(K36:M36) -> 911 | O36: 812 | P36: =1670-O36 -> 858 | T36: 1100 | U36: 2826 | V36: 3045 | W36: 2901 | X36: 2899 | Y36: 3041 | Z36: 3174 | AA36: 3270
B37: EBIT | C37: =C34+C35-C36 -> 1483 | D37: =D34+D35-D36 -> 1681 | E37: =E34+E35-E36 -> 2027 | F37: =F34+F35-F36 -> 1616 | G37: =G34+G35-G36 -> 1636 | H37: =H34+H35-H36 -> 1905 | I37: =I34+I35-I36 -> 2132 | J37: =J34+J35-J36 -> 1882 | ... P37: =P34+P35-P36 -> 2087 | T37: =T34+T35-T36 -> 4357 | U37: =U34+U35-U36 -> 4773 | V37: =V34+V35-V36 -> 1506 | W37: =W34+W35-W36 -> 4282 | X37: =X34+X35-X36 -> 5518 | Y37: =Y34+Y35-Y36 -> 6808 | Z37: =Z34+Z35-Z36 -> 7555 | AA37: =AA34+AA35-AA36 -> 7997
B38: Financial Income | C38: 10 | D38: 44 | E38: -56 | F38: -9 | G38: 21 | H38: =12-G38 -> -9 | I38: =14-H38-G38 -> 2 | J38: -90 | K38: 5 | L38: =-12-K38 -> -17 | M38: =-49-SUM(K38:L38) -> -37 | N38: =+AA38-SUM(K38:M38) -> -31 | O38: -16 | P38: =-51-O38 -> -35 | T38: 17 | U38: -152 | V38: -139 | W38: -142 | X38: -214 | Y38: -11 | Z38: -77 | AA38: -80
B39: Income from consilidated companies | C39: 12 | D39: 22 | E39: 14 | F39: 24 | G39: 14 | H39: =45-G39 -> 31 | I39: =67-SUM(G39:H39) -> 22 | J39: 32 | K39: 25 | L39: =42-K39 -> 17 | M39: =69-SUM(K39:L39) -> 27 | N39: =+AA39-SUM(K39:M39) -> 33 | O39: 23 | P39: =52-O39 -> 29 | T39: 54 | U39: 61 | V39: 33 | W39: 58 | X39: 53 | Y39: 72 | Z39: 99 | AA39: 102
B40: EBT | C40: =C37+C38+C39 -> 1505 | D40: =D37+D38+D39 -> 1747 | E40: =E37+E38+E39 -> 1985 | F40: =F37+F38+F39 -> 1631 | G40: =G37+G38+G39 -> 1671 | H40: =H37+H38+H39 -> 1927 | I40: =I37+I38+I39 -> 2156 | J40: =J37+J38+J39 -> 1824 | ... P40: =P37+P38+P39 -> 2081 | T40: =T37+T38+T39 -> 4428 | U40: =U37+U38+U39 -> 4682 | V40: =V37+V38+V39 -> 1400 | W40: =W37+W38+W39 -> 4198 | X40: =X37+X38+X39 -> 5357 | Y40: =Y37+Y38+Y39 -> 6869 | Z40: =Z37+Z38+Z39 -> 7577 | AA40: =AA37+AA38+AA39 -> 8019
B41: Income Tax | C41: 333 | D41: 399 | E41: 392 | F41: 351 | G41: 373 | H41: 448 | I41: 474 | J41: 406 | K41: 366 | L41: =810-K41 -> 444 | M41: =1341-SUM(K41:L41) -> 531 | N41: =+AA41-SUM(K41:M41) -> 459 | O41: 388 | P41: =865-O41 -> 477 | T41: 980 | U41: 1034 | V41: 297 | W41: 949 | X41: 1211 | Y41: 1475 | Z41: 1700 | AA41: 1800
B42: Net Income | C42: =C40-C41 -> 1172 | D42: =D40-D41 -> 1348 | E42: =E40-E41 -> 1593 | F42: =F40-F41 -> 1280 | G42: =G40-G41 -> 1298 | H42: =H40-H41 -> 1479 | I42: =I40-I41 -> 1682 | J42: =J40-J41 -> 1418 | ... P42: =P40-P41 -> 1604 | T42: =T40-T41 -> 3448 | U42: =U40-U41 -> 3648 | V42: =V40-V41 -> 1103 | W42: =W40-W41 -> 3249 | X42: =X40-X41 -> 4146 | Y42: =Y40-Y41 -> 5394 | Z42: =Z40-Z41 -> 5877 | AA42: =AA40-AA41 -> 6219
B43: Minorities | C43: 4 | D43: 3 | E43: 5 | F43: 2 | G43: 5 | H43: 5 | I43: 1 | J43: 0 | K43: 0 | L43: 0 | M43: 0 | N43: =+AA43-SUM(K43:M43) -> 0 | O43: 0 | P43: 0 | T43: 4 | U43: 8 | V43: -2 | W43: 7 | X43: 17 | Y43: 14 | Z43: 11 | AA43: 0
B44: Net Income to Firm | C44: =C42-C43 -> 1168 | D44: =D42-D43 -> 1345 | E44: =E42-E43 -> 1588 | F44: =F42-F43 -> 1278 | G44: =G42-G43 -> 1293 | H44: =H42-H43 -> 1474 | I44: =I42-I43 -> 1681 | J44: =J42-J43 -> 1418 | ... P44: =P42-P43 -> 1604 | T44: =T42-T43 -> 3444 | U44: =U42-U43 -> 3640 | V44: =V42-V43 -> 1105 | W44: =W42-W43 -> 3242 | X44: =X42-X43 -> 4129 | Y44: =Y42-Y43 -> 5380 | Z44: =Z42-Z43 -> 5866 | AA44: =AA42-AA43 -> 6219
B46: EPS | C46: =C44/C47 -> 0.37522047 | D46: =D44/D47 -> 0.43208179 | E46: =E44/E47 -> 0.51014564 | F46: =F44/F47 -> 0.41055802 | G46: =G44/G47 -> 0.41528107 | H46: =H44/H47 -> 0.47332238 | I46: =I44/I47 -> 0.53975871 | J46: =J44/J47 -> 0.45095284 | ... P46: =P44/P47 -> 0.51477548 | T46: =T44/T47 -> 1.1060789 | U46: =U44/U47 -> 1.1687704 | V46: =V44/V47 -> 0.35475144 | W46: =W44/W47 -> 1.0412481 | X46: =X44/X47 -> 1.3266054 | Y46: =Y44/Y47 -> 1.7283272 | Z46: =Z44/Z47 -> 1.8655073 | AA46: =AA44/AA47 -> 1.9957694
B47: Shares | C47: 3112.8366 | D47: 3112.8366 | E47: 3112.8366 | F47: 3112.8366 | G47: 3113.5539 | H47: 3114.1566 | I47: 3114.3545 | J47: =+Z47 -> 3144.453 | K47: 3115.2378 | L47: 3115.8116 | M47: 3115.9987 | N47: 3116.0915 | O47: 3116.1155 | P47: 3115.9215 | T47: 3113.7019 | U47: 3114.3842 | V47: 3114.857 | W47: 3113.571 | X47: 3112.4554 | Y47: 3112.8366 | Z47: 3144.453 | AA47: 3116.0915
B49: Zara | U49: =U22/T22-1 -> 0.08562233 | V49: =V22/U22-1 -> -0.27780617 | W49: =W22/V22-1 -> 0.38622691 | X49: =X22/W22-1 -> 0.21316246 | Y49: =Y22/X22-1 -> 0.096334329 | Z49: =Z22/Y22-1 -> 0.066333973 | AA49: =AA22/Z22-1 -> 0.0098279214
B50: Paul&Bear | U50: =U23/T23-1 -> 0.058002148 | V50: =V23/U23-1 -> -0.27664975 | W50: =W23/V23-1 -> 0.31649123 | X50: =X23/W23-1 -> 0.14712154 | Y50: =Y23/X23-1 -> 0.096189591 | Z50: =Z23/Y23-1 -> 0.046629928 | AA50: =AA23/Z23-1 -> 0.031186715
B51: Massimo Duti | U51: =U24/T24-1 -> 0.054384018 | V51: =V24/U24-1 -> -0.33105263 | W51: =W24/V24-1 -> 0.30055075 | X51: =X24/W24-1 -> -0.036297641 | Y51: =Y24/X24-1 -> 0.15442561 | Z51: =Z24/Y24-1 -> 0.065796629 | AA51: =AA24/Z24-1 -> 0.030102041
B52: Bershka | U52: =U25/T25-1 -> 0.064285714 | V52: =V25/U25-1 -> -0.25671141 | W52: =W25/V25-1 -> 0.2285553 | X52: =X25/W25-1 -> 0.095084979 | Y52: =Y25/X25-1 -> 0.099412752 | Z52: =Z25/Y25-1 -> 0.11789393 | AA52: =AA25/Z25-1 -> 0.12150171
B53: Stardivarius | U53: =U26/T26-1 -> 0.14080834 | V53: =V26/U26-1 -> -0.26685714 | W53: =W26/V26-1 -> 0.42166797 | X53: =X26/W26-1 -> 0.12719298 | Y53: =Y26/X26-1 -> 0.13521401 | Z53: =Z26/Y26-1 -> 0.14138817 | AA53: =AA26/Z26-1 -> 0.12687688
B54: Oysho | U54: =U27/T27-1 -> 0.032478632 | V54: =V27/U27-1 -> -0.13576159 | W54: =W27/V27-1 -> 0.14942529 | X54: =X27/W27-1 -> 0.038333333 | Y54: =Y27/X27-1 -> 0.19422151 | Z54: =Z27/Y27-1 -> 0.11693548 | AA54: =AA27/Z27-1 -> 0.15523466
B55: Revenue Growth | G55: =G29/C29-1 -> 0.070818552 | H55: =H29/D29-1 -> 0.073168092 | I55: =I29/E29-1 -> 0.068394611 | J55: =J29/F29-1 -> 0.084349004 | K55: =K29/G29-1 -> 0.015214724 | L55: =L29/H29-1 -> 0.016944024 | M55: =M29/I29-1 -> 0.04884044 | N55: =N29/J29-1 -> 0.04308653 | ... P55: =P29/L29-1 -> 0.091441039 | U55: =U29/T29-1 -> 0.081927711 | V55: =V29/U29-1 -> -0.27874996 | W55: =W29/V29-1 -> 0.35849427 | X55: =X29/W29-1 -> 0.17509742 | Y55: =Y29/X29-1 -> 0.10371826 | Z55: =Z29/Y29-1 -> 0.074693298 | AA55: =AA29/Z29-1 -> 0.031890661
B56: Gross Margin | C56: =C31/C29 -> 0.60478255 | D56: =D31/D29 -> 0.56250676 | E56: =E31/E29 -> 0.61680749 | F56: =F31/F29 -> 0.53762817 | G56: =G31/G29 -> 0.60613497 | H56: =H31/H29 -> 0.56490166 | I56: =I31/I29 -> 0.61440633 | J56: =J31/J29 -> 0.53996432 | ... P56: =P31/P29 -> 0.56674239 | T56: =T31/T29 -> 0.56668579 | U56: =U31/U29 -> 0.55884328 | V56: =V31/V29 -> 0.55822959 | W56: =W31/W29 -> 0.57057295 | X56: =X31/X29 -> 0.56980564 | Y56: =Y31/Y29 -> 0.57754472 | Z56: =Z31/Z29 -> 0.57838062 | AA56: =AA31/AA29 -> 0.5825306
B57: EBITDA Margin | C57: =C34/C29 -> 0.28839837 | D57: =D34/D29 -> 0.26702024 | E57: =E34/E29 -> 0.31582553 | F57: =F34/F29 -> 0.23408783 | G57: =G34/G29 -> 0.29079755 | H57: =H34/H29 -> 0.26928896 | I57: =I34/I29 -> 0.31270706 | J57: =J34/J29 -> 0.24638715 | ... P57: =P34/P29 -> 0.26760563 | T57: =T34/T29 -> 0.2087206 | U57: =U34/U29 -> 0.2686393 | V57: =V34/V29 -> 0.22306637 | W57: =W34/W29 -> 0.25916438 | X57: =X34/X29 -> 0.26552857 | Y57: =Y34/Y29 -> 0.2739867 | Z57: =Z34/Z29 -> 0.27772313 | AA57: =AA34/AA29 -> 0.28263596
B58: EBIT Margin | C58: =C37/C29 -> 0.19484956 | D58: =D37/D29 -> 0.1819461 | E58: =E37/E29 -> 0.23144554 | F58: =F37/F29 -> 0.1563165 | G58: =G37/G29 -> 0.2007362 | H58: =H37/H29 -> 0.19213313 | I58: =I37/I29 -> 0.22785081 | J58: =J37/J29 -> 0.16788582 | ... P58: =P37/P29 -> 0.18964107 | T58: =T37/T29 -> 0.16664754 | U58: =U37/U29 -> 0.16873475 | V58: =V37/V29 -> 0.073816293 | W58: =W37/W29 -> 0.1544956 | X58: =X37/X29 -> 0.16942491 | Y58: =Y37/Y29 -> 0.18938994 | Z58: =Z37/Z29 -> 0.19556326 | AA58: =AA37/AA29 -> 0.20060706
B59: Net Margin | C59: =C42/C29 -> 0.15398765 | D59: =D42/D29 -> 0.14590324 | E59: =E42/E29 -> 0.18189084 | F59: =F42/F29 -> 0.12381505 | G59: =G42/G29 -> 0.1592638 | H59: =H42/H29 -> 0.14916793 | I59: =I42/I29 -> 0.17975847 | J59: =J42/J29 -> 0.1264942 | ... P59: =P42/P29 -> 0.14575193 | T59: =T42/T29 -> 0.1318799 | U59: =U42/U29 -> 0.12896383 | V59: =V42/V29 -> 0.054063327 | W59: =W42/W29 -> 0.11722471 | X59: =X42/X29 -> 0.12729897 | Y59: =Y42/Y29 -> 0.15005425 | Z59: =Z42/Z29 -> 0.15212777 | AA59: =AA42/AA29 -> 0.15600542
B60: Distribution Margin | G60: =(G34-C34)/(G29-C29) -> 0.32467532 | U60: =(U34-T34)/(U29-T29) -> 1 | V60: =(V34-U34)/(V29-U29) -> 0.38655675 | W60: =(W34-V34)/(W29-V29) -> 0.35985781 | X60: =(X34-W34)/(X29-W29) -> 0.30187513 | Y60: =(Y34-X34)/(Y29-X29) -> 0.35553582 | Z60: =(Z34-Y34)/(Z29-Y29) -> 0.32774674 | AA60: =(AA34-Z34)/(AA29-Z29) -> 0.43668831
B61: Tax Rate | C61: =C41/C40 -> 0.22126246 | D61: =D41/D40 -> 0.22839153 | E61: =E41/E40 -> 0.19748111 | F61: =F41/F40 -> 0.2152054 | G61: =G41/G40 -> 0.22321963 | H61: =H41/H40 -> 0.23248573 | I61: =I41/I40 -> 0.21985158 | J61: =J41/J40 -> 0.22258772 | ... P61: =P41/P40 -> 0.22921672 | T61: =T41/T40 -> 0.22131888 | U61: =U41/U40 -> 0.22084579 | V61: =V41/V40 -> 0.21214286 | W61: =W41/W40 -> 0.22606003 | X61: =X41/X40 -> 0.22605936 | Y61: =Y41/Y40 -> 0.21473286 | Z61: =Z41/Z40 -> 0.2243632 | AA61: =AA41/AA40 -> 0.22446689
B63: Right of Use | G63: 4774 | I63: 5065 | T63: 0 | U63: 6043 | V63: 5477 | W63: 5224 | X63: 4910 | Y63: 5097 | Z63: 5269 | AA63: 5542
B64: Intnagibles | G64: 1483 | I64: 1597 | T64: 1016 | U64: 618 | V64: 645 | W64: 790 | X64: 1003 | Y64: 1420 | Z64: 1607 | AA64: 1840
B65: PP&E | G65: 8715 | I65: 9477 | T65: 8359 | U65: 8376 | V65: 7422 | W65: 7503 | X65: 7615 | Y65: 8361 | Z65: 10014 | AA65: 11142
B66: Financial Investments | G66: 413 | I66: 453 | T66: 267 | U66: 249 | V66: 261 | W66: 307 | X66: 335 | Y66: 398 | Z66: 450 | AA66: 471
B67: Other | G67: 1506 | I67: 1400 | T67: 1422 | U67: 1692 | V67: 1656 | W67: 1519 | X67: 1481 | Y67: 1443 | Z67: 1017 | AA67: 952
B68: Total Non Current Assets | C68: =SUM(C63:C67) -> 0 | D68: =SUM(D63:D67) -> 0 | E68: =SUM(E63:E67) -> 0 | F68: =SUM(F63:F67) -> 0 | G68: =SUM(G63:G67) -> 16891 | H68: =SUM(H63:H67) -> 0 | I68: =SUM(I63:I67) -> 17992 | J68: =SUM(J63:J67) -> 0 | T68: =SUM(T63:T67) -> 11064 | U68: =SUM(U63:U67) -> 16978 | V68: =SUM(V63:V67) -> 15461 | W68: =SUM(W63:W67) -> 15343 | X68: =SUM(X63:X67) -> 15344 | Y68: =SUM(Y63:Y67) -> 16719 | Z68: =SUM(Z63:Z67) -> 18357 | AA68: =SUM(AA63:AA67) -> 19947
B69: Inventories | G69: 3566 | I69: 4290 | T69: 2716 | U69: 2269 | V69: 2321 | W69: 3042 | X69: 3191 | Y69: 2966 | Z69: 3321 | AA69: 3249
B70: Receivables | G70: 1131 | I70: 1159 | T70: 820 | U70: 780 | V70: 715 | W70: 842 | X70: 851 | Y70: 1038 | Z70: 1088 | AA70: 1166
B71: Short Term Investments | G71: 3978 | I71: 3569 | T71: 1929 | U71: 3319 | V71: 176 | W71: 2374 | X71: 4522 | Y71: 4415 | Z71: 5120 | AA71: 5684
B72: Cash and Cash Equivalents | G72: 7668 | I72: 8268 | T72: 4866 | U72: 4780 | V72: 7398 | W72: 7021 | X72: 5561 | Y72: 7007 | Z72: 6382 | AA72: 5276
B73: Other | G73: 736 | I73: 813 | T73: 289 | U73: 265 | V73: 347 | W73: 323 | X73: 515 | Y73: 590 | Z73: 445 | AA73: 316
B74: Total Current Assets | C74: =SUM(C69:C73) -> 0 | D74: =SUM(D69:D73) -> 0 | E74: =SUM(E69:E73) -> 0 | F74: =SUM(F69:F73) -> 0 | G74: =SUM(G69:G73) -> 17079 | H74: =SUM(H69:H73) -> 0 | I74: =SUM(I69:I73) -> 18099 | J74: =SUM(J69:J73) -> 0 | T74: =SUM(T69:T73) -> 10620 | U74: =SUM(U69:U73) -> 11413 | V74: =SUM(V69:V73) -> 10957 | W74: =SUM(W69:W73) -> 13602 | X74: =SUM(X69:X73) -> 14640 | Y74: =SUM(Y69:Y73) -> 16016 | Z74: =SUM(Z69:Z73) -> 16356 | AA74: =SUM(AA69:AA73) -> 15691
B75: Total Assets | C75: =C68+C74 -> 0 | D75: =D68+D74 -> 0 | E75: =E68+E74 -> 0 | F75: =F68+F74 -> 0 | G75: =G68+G74 -> 33970 | H75: =H68+H74 -> 0 | I75: =I68+I74 -> 36091 | J75: =J68+J74 -> 0 | T75: =T68+T74 -> 21684 | U75: =U68+U74 -> 28391 | V75: =V68+V74 -> 26418 | W75: =W68+W74 -> 28945 | X75: =X68+X74 -> 29984 | Y75: =Y68+Y74 -> 32735 | Z75: =Z68+Z74 -> 34713 | AA75: =AA68+AA74 -> 35638
B77: Equity | G77: 17519 | I77: 18140 | T77: 14653 | U77: 14913 | V77: 14520 | W77: 15733 | X77: 17008 | Y77: 18642 | Z77: 19676 | AA77: 20395
B78: Minorites | G78: 35 | I78: 0 | T78: 30 | U78: 36 | V78: 30 | W78: 26 | X78: 25 | Y78: 30 | Z78: 0 | AA78: 0
B79: Total Equity | C79: =C77+C78 -> 0 | D79: =D77+D78 -> 0 | E79: =E77+E78 -> 0 | F79: =F77+F78 -> 0 | G79: =G77+G78 -> 17554 | H79: =H77+H78 -> 0 | I79: =I77+I78 -> 18140 | J79: =J77+J78 -> 0 | T79: =T77+T78 -> 14683 | U79: =U77+U78 -> 14949 | V79: =V77+V78 -> 14550 | W79: =W77+W78 -> 15759 | X79: =X77+X78 -> 17033 | Y79: =Y77+Y78 -> 18672 | Z79: =Z77+Z78 -> 19676 | AA79: =AA77+AA78 -> 20395
B80: Deffered Taxes | G80: 444 | I80: 391 | T80: 312 | U80: 370 | V80: 396 | W80: 359 | X80: 384 | Y80: 394 | Z80: 72 | AA80: 101
B81: Financial Debt | G81: 0 | I81: 0 | T81: 5 | U81: 6 | V81: 3 | W81: 1 | X81: 0 | Y81: 0 | Z81: 0 | AA81: 0
B82: Lease Liabilities | G82: 3790 | I82: 4010 | T82: 0 | U82: 5163 | V82: 4599 | W82: 4262 | X82: 3924 | Y82: 4123 | Z82: 4180 | AA82: 4394
B83: Other | G83: 570 | I83: 598 | T83: 1301 | U83: 597 | V83: 532 | W83: 536 | X83: 505 | Y83: 610 | Z83: 599 | AA83: 576
B84: Total Non Current Liabilities | C84: =SUM(C80:C83) -> 0 | D84: =SUM(D80:D83) -> 0 | E84: =SUM(E80:E83) -> 0 | F84: =SUM(F80:F83) -> 0 | G84: =SUM(G80:G83) -> 4804 | H84: =SUM(H80:H83) -> 0 | I84: =SUM(I80:I83) -> 4999 | J84: =SUM(J80:J83) -> 0 | T84: =SUM(T80:T83) -> 1618 | U84: =SUM(U80:U83) -> 6136 | V84: =SUM(V80:V83) -> 5530 | W84: =SUM(W80:W83) -> 5158 | X84: =SUM(X80:X83) -> 4813 | Y84: =SUM(Y80:Y83) -> 5127 | Z84: =SUM(Z80:Z83) -> 4851 | AA84: =SUM(AA80:AA83) -> 5071
B85: Financial Debt | G85: 22 | I85: 13 | T85: 84 | U85: 32 | V85: 11 | W85: 35 | X85: 13 | Y85: 16 | Z85: 7 | AA85: 2
B86: Lease Liabilities | G86: 1443 | I86: 1499 | T86: 0 | U86: 1649 | V86: 1552 | W86: 1562 | X86: 1517 | Y86: 1428 | Z86: 1542 | AA86: 1539
B87: Payables | G87: 10126 | I87: 11392 | T87: 5251 | U87: 5585 | V87: 4747 | W87: 6411 | X87: 6561 | Y87: 7467 | Z87: 8590 | AA87: 8587
B88: Other | G88: 21 | I88: 48 | T88: 47 | U88: 40 | V88: 27 | W88: 22 | X88: 46 | Y88: 26 | Z88: 48 | AA88: 43
B89: Total Current Liabilities | C89: =SUM(C85:C88) -> 0 | D89: =SUM(D85:D88) -> 0 | E89: =SUM(E85:E88) -> 0 | F89: =SUM(F85:F88) -> 0 | G89: =SUM(G85:G88) -> 11612 | H89: =SUM(H85:H88) -> 0 | I89: =SUM(I85:I88) -> 12952 | J89: =SUM(J85:J88) -> 0 | T89: =SUM(T85:T88) -> 5382 | U89: =SUM(U85:U88) -> 7306 | V89: =SUM(V85:V88) -> 6337 | W89: =SUM(W85:W88) -> 8030 | X89: =SUM(X85:X88) -> 8137 | Y89: =SUM(Y85:Y88) -> 8937 | Z89: =SUM(Z85:Z88) -> 10187 | AA89: =SUM(AA85:AA88) -> 10171
B90: Equity & Liabilities | C90: =C79+C84+C89 -> 0 | D90: =D79+D84+D89 -> 0 | E90: =E79+E84+E89 -> 0 | F90: =F79+F84+F89 -> 0 | G90: =G79+G84+G89 -> 33970 | H90: =H79+H84+H89 -> 0 | I90: =I79+I84+I89 -> 36091 | J90: =J79+J84+J89 -> 0 | T90: =T79+T84+T89 -> 21683 | U90: =U79+U84+U89 -> 28391 | V90: =V79+V84+V89 -> 26417 | W90: =W79+W84+W89 -> 28947 | X90: =X79+X84+X89 -> 29983 | Y90: =Y79+Y84+Y89 -> 32736 | Z90: =Z79+Z84+Z89 -> 34714 | AA90: =AA79+AA84+AA89 -> 35637
B93: EBT | T93: =T40 -> 4428 | U93: =U40 -> 4682 | V93: =V40 -> 1400 | W93: =W40 -> 4198 | X93: =X40 -> 5357 | Y93: =Y40 -> 6869 | Z93: =Z40 -> 7577 | AA93: 8020
B94: D&A | T94: 1100 | U94: 2826 | V94: 3045 | W94: 2901 | X94: 2899 | Y94: 3041 | Z94: 3174 | AA94: 3270
B95: Finance Lease Liabilities | T95: 0 | U95: 142 | V95: 120 | W95: 92 | X95: 116 | Y95: 196 | Z95: 223 | AA95: 215
B96: Other | T96: =-48-33 -> -81 | U96: =272-19 -> 253 | V96: -250 | W96: 74 | X96: 146 | Y96: 76 | Z96: 51 | AA96: 114
B97: Income Tax | T97: -1070 | U97: -1207 | V97: -452 | W97: -734 | X97: -1176 | Y97: -1460 | Z97: -1539 | AA97: -1585
B98: Change in WC:
B99: Change in Inventories | T99: -70 | U99: 201 | V99: 93 | W99: -759 | X99: -193 | Y99: 130 | Z99: -427 | AA99: 9
B100: Change in Receivables | T100: -142 | U100: -10 | V100: 34 | W100: -154 | X100: -58 | Y100: -341 | Z100: -164 | AA100: -149
B101: Change in Current Liabilties | T101: -137 | U101: 14 | V101: -974 | W101: 1136 | X101: -418 | Y101: 154 | Z101: 392 | AA101: -663
B102: Total | T102: =SUM(T99:T101) -> -349 | U102: =SUM(U99:U101) -> 205 | V102: =SUM(V99:V101) -> -847 | W102: =SUM(W99:W101) -> 223 | X102: =SUM(X99:X101) -> -669 | Y102: =SUM(Y99:Y101) -> -57 | Z102: =SUM(Z99:Z101) -> -199 | AA102: =SUM(AA99:AA101) -> -803
B103: CFFO | T103: =T93+SUM(T94:T97)+T102 -> 4028 | U103: =U93+SUM(U94:U97)+U102 -> 6901 | V103: =V93+SUM(V94:V97)+V102 -> 3016 | W103: =W93+SUM(W94:W97)+W102 -> 6754 | X103: =X93+SUM(X94:X97)+X102 -> 6673 | Y103: =Y93+SUM(Y94:Y97)+Y102 -> 8665 | Z103: =Z93+SUM(Z94:Z97)+Z102 -> 9287 | AA103: =AA93+SUM(AA94:AA97)+AA102 -> 9231
B104: Investments in Intangibles | T104: -230 | U104: -238 | V104: -241 | W104: -460 | X104: -388 | Y104: -473 | Z104: -465 | AA104: -519
B105: Investments in Tangibles | T105: =-1391+159 -> -1232 | U105: =-914+40 -> -874 | V105: =-467+36-5 -> -436 | W105: -666 | X105: -1027 | Y105: -1399 | Z105: -2207 | AA105: -2193
B106: Other long term financial investments | T106: 24 | U106: 70 | V106: 12 | W106: 25 | X106: 24 | Y106: 61 | Z106: =51-14 -> 37 | AA106: =-16+55 -> 39
B107: Other Asset Investments | T107: 20 | U107: 56 | V107: 36 | W107: 46 | X107: 36 | Y107: -6 | Z107: 51 | AA107: 3
...

Sheet Ratios
A1: Main
D2: 18 | E2: =D2+1 -> 19 | F2: =E2+1 -> 20 | G2: =F2+1 -> 21 | H2: =G2+1 -> 22 | I2: =H2+1 -> 23 | J2: =I2+1 -> 24 | K2: FY25 | M2: Average
A3: x | B3: Profitabilty
B4: ROE | D4: =Model!T44/Model!T77 -> 0.23503719 | E4: =Model!U44/Model!U77 -> 0.24408234 | F4: =Model!V44/Model!V77 -> 0.076101928 | G4: =Model!W44/Model!W77 -> 0.20606369 | H4: =Model!X44/Model!X77 -> 0.24276811 | I4: =Model!Y44/Model!Y77 -> 0.28859564 | J4: =Model!Z44/Model!Z77 -> 0.2981297 | K4: =Model!AA44/Model!AA77 -> 0.30492768 | M4: =AVERAGE(G4:I4,D4:E4) -> 0.2433094
B5: ROA | D5: =Model!T37/Model!T75 -> 0.20093156 | E5: =Model!U37/Model!U75 -> 0.16811666 | F5: =Model!V37/Model!V75 -> 0.057006586 | G5: =Model!W37/Model!W75 -> 0.14793574 | H5: =Model!X37/Model!X75 -> 0.18403148 | I5: =Model!Y37/Model!Y75 -> 0.20797312 | J5: =Model!Z37/Model!Z75 -> 0.21764181 | K5: =Model!AA37/Model!AA75 -> 0.22439531 | M5: =AVERAGE(G5:I5,D5:E5) -> 0.18179771
B6: ROIC | D6: =(Model!T37*(1-Model!T61))/(Model!T79+Model!T82+Model!T83+Model!T85+Model!T86-Model!T72-Model!T71) -> 0.36587012 | E6: =(Model!U37*(1-Model!U61))/(Model!U79+Model!U82+Model!U83+Model!U85+Model!U86-Model!U72-Model!U71) -> 0.26022693 | F6: =(Model!V37*(1-Model!V61))/(Model!V79+Model!V82+Model!V83+Model!V85+Model!V86-Model!V72-Model!V71) -> 0.086796844 | G6: =(Model!W37*(1-Model!W61))/(Model!W79+Model!W82+Model!W83+Model!W85+Model!W86-Model!W72-Model!W71) -> 0.25973908 | H6: =(Model!X37*(1-Model!X61))/(Model!X79+Model!X82+Model!X83+Model!X85+Model!X86-Model!X72-Model!X71) -> 0.3308238 | I6: =(Model!Y37*(1-Model!Y61))/(Model!Y79+Model!Y82+Model!Y83+Model!Y85+Model!Y86-Model!Y72-Model!Y71) -> 0.39816033 | J6: =(Model!Z37*(1-Model!Z61))/(Model!Z79+Model!Z82+Model!Z83+Model!Z85+Model!Z86-Model!Z72-Model!Z71) -> 0.40407778 | K6: =(Model!AA37*(1-Model!AA61))/(Model!AA79+Model!AA82+Model!AA83+Model!AA85+Model!AA86-Model!AA72-Model!AA71) -> 0.38893379 | M6: =AVERAGE(G6:I6,D6:E6) -> 0.32296405
B7: ROCE | D7: =Model!T37/(Model!T68+Model!T69+Model!T70+Model!T73-Model!T87) -> 0.45206474 | E7: =Model!U37/(Model!U68+Model!U69+Model!U70+Model!U73-Model!U87) -> 0.32453934 | F7: =Model!V37/(Model!V68+Model!V69+Model!V70+Model!V73-Model!V87) -> 0.10683124 | G7: =Model!W37/(Model!W68+Model!W69+Model!W70+Model!W73-Model!W87) -> 0.32589999 | H7: =Model!X37/(Model!X68+Model!X69+Model!X70+Model!X73-Model!X87) -> 0.41364318 | I7: =Model!Y37/(Model!Y68+Model!Y69+Model!Y70+Model!Y73-Model!Y87) -> 0.49169435 | J7: =Model!Z37/(Model!Z68+Model!Z69+Model!Z70+Model!Z73-Model!Z87) -> 0.51672252 | K7: =Model!AA37/(Model!AA68+Model!AA69+Model!AA70+Model!AA73-Model!AA87) -> 0.49698589 | M7: =AVERAGE(G7:I7,D7:E7) -> 0.40156832
B9: Retention Rate | D9: =1-(-Model!T114/Model!T44) -> 0.32200929 | E9: =1-(-Model!U114/Model!U44) -> 0.24697802 | F9: =1-(-Model!V114/Model!V44) -> 0.013574661 | G9: =1-(-Model!W114/Model!W44) -> 0.32387415 | H9: =1-(-Model!X114/Model!X44) -> 0.29426011 | I9: =1-(-Model!Y114/Model!Y44) -> 0.30408922 | J9: =1-(-Model!Z114/Model!Z44) -> 0.18223662 | K9: =1-(-Model!AA114/Model!AA44) -> 0.15822479 | M9: =AVERAGE(G9:I9,D9:E9) -> 0.29824216
B10: Expected Growth | D10: =D9*D4 -> 0.07568416 | E10: =E9*E4 -> 0.060282975 | F10: =F9*F4 -> 0.0010330579 | G10: =G9*G4 -> 0.066738702 | H10: =H9*H4 -> 0.071436971 | I10: =I9*I4 -> 0.087758824 | J10: =J9*J4 -> 0.054330148 | K10: =K9*K4 -> 0.048247119 | M10: =AVERAGE(G10:I10,D10:E10) -> 0.072380326
B11: Reinvestment Rate | D11: =(-Model!T102-Model!T109)/(Model!T37*(1-Model!T61)) -> 0.65552246 | E11: =(-Model!U102-Model!U109)/(Model!U37*(1-Model!U61)) -> 0.5837743 | F11: =(-Model!V102-Model!V109)/(Model!V37*(1-Model!V61)) -> -1.4049574 | G11: =(-Model!W102-Model!W109)/(Model!W37*(1-Model!W61)) -> 0.91429993 | H11: =(-Model!X102-Model!X109)/(Model!X37*(1-Model!X61)) -> 0.97691089 | I11: =(-Model!Y102-Model!Y109)/(Model!Y37*(1-Model!Y61)) -> 0.33052139 | J11: =(-Model!Z102-Model!Z109)/(Model!Z37*(1-Model!Z61)) -> 0.59522834 | K11: =(-Model!AA102-Model!AA109)/(Model!AA37*(1-Model!AA61)) -> 0.64786198 | M11: =AVERAGE(G11:I11,D11:E11) -> 0.6922058
B12: Expected Growth | D12: =D11*D6 -> 0.23983608 | E12: =E11*E6 -> 0.15191379 | F12: =F11*F6 -> -0.12194587 | G12: =G11*G6 -> 0.23747943 | H12: =H11*H6 -> 0.32318537 | I12: =I11*I6 -> 0.13160051 | J12: =J11*J6 -> 0.24051855 | K12: =K11*K6 -> 0.25197542 | M12: =AVERAGE(G12:I12,D12:E12) -> 0.21680304
A14: x | B14: Financial Stabiltiy
B15: Gearing | M15: =AVERAGE(G15:I15,D15:E15) -> #DIV/0!
B16: Net Debt/EBITDA | M16: =AVERAGE(G16:I16,D16:E16) -> #DIV/0!
A19: x | B19: WC Managment
B20: Debitors | D20: =Model!T70/Model!T29*360 -> 11.290878 | E20: =Model!U70/Model!U29*360 -> 9.9268215 | F20: =Model!V70/Model!V29*360 -> 12.61641 | G20: =Model!W70/Model!W29*360 -> 10.936643 | H20: =Model!X70/Model!X29*360 -> 9.4064908 | I20: =Model!Y70/Model!Y29*360 -> 10.395304 | J20: =Model!Z70/Model!Z29*360 -> 10.138745 | K20: =Model!AA70/Model!AA29*360 -> 10.529801 | M20: =AVERAGE(D20:I20) -> 10.762091
B21: Creditors | D21: =Model!T87/Model!T29*360 -> 72.302926 | E21: =Model!U87/Model!U29*360 -> 71.078587 | F21: =Model!V87/Model!V29*360 -> 83.762376 | G21: =Model!W87/Model!W29*360 -> 83.271756 | H21: =Model!X87/Model!X29*360 -> 72.521723 | I21: =Model!Y87/Model!Y29*360 -> 74.780093 | J21: =Model!Z87/Model!Z29*360 -> 80.047629 | K21: =Model!AA87/Model!AA29*360 -> 77.546659 | M21: =AVERAGE(D21:I21) -> 76.286244
B22: Inventory-Intensity | D22: =Model!T69/Model!T75 -> 0.12525364 | E22: =Model!U69/Model!U75 -> 0.079919693 | F22: =Model!V69/Model!V75 -> 0.087856764 | G22: =Model!W69/Model!W75 -> 0.10509587 | H22: =Model!X69/Model!X75 -> 0.10642343 | I22: =Model!Y69/Model!Y75 -> 0.090606385 | J22: =Model!Z69/Model!Z75 -> 0.09567021 | K22: =Model!AA69/Model!AA75 -> 0.091166732 | M22: =AVERAGE(D22:I22) -> 0.09919263
B23: Inventory Turnover | D23: =Model!T30/Model!T69 -> 4.1712077 | E23: =Model!U30/Model!U69 -> 5.4997796 | F23: =Model!V30/Model!V69 -> 3.88324 | G23: =Model!W30/Model!W69 -> 3.9125575 | H23: =Model!X30/Model!X69 -> 4.3907866 | I23: =Model!Y30/Model!Y69 -> 5.120027 | J23: =Model!Z30/Model!Z69 -> 4.9045468 | K23: =Model!AA30/Model!AA69 -> 5.1221914 | M23: =AVERAGE(D23:I23) -> 4.4962664
B24: Storage Duration | D24: =360/D23 -> 86.305941 | E24: =360/E23 -> 65.457168 | F24: =360/F23 -> 92.706091 | G24: =360/G23 -> 92.011427 | H24: =360/H23 -> 81.989865 | I24: =360/I23 -> 70.31213 | J24: =360/J23 -> 73.401277 | K24: =360/K23 -> 70.282418 | M24: =AVERAGE(D24:I24) -> 81.46377
B25: Cash Conversion Cycle | D25: =D24+D20-D21 -> 25.293892 | E25: =E24+E20-E21 -> 4.3054022 | F25: =F24+F20-F21 -> 21.560125 | G25: =G24+G20-G21 -> 19.676313 | H25: =H24+H20-H21 -> 18.874633 | I25: =I24+I20-I21 -> 5.9273409 | J25: =J24+J20-J21 -> 3.4923932 | K25: =K24+K20-K21 -> 3.2655607 | M25: =AVERAGE(D25:I25) -> 15.939618
A28: x | B28: Multiples
B29: Price | D29: 28.05 | E29: 33.1 | F29: 30.01 | G29: 30.04 | H29: 31.05 | I29: 42.73 | J29: 59 | K29: 52.8
B30: Shares | D30: =Model!T47 -> 3113.7019 | E30: =Model!U47 -> 3114.3842 | F30: =Model!V47 -> 3114.857 | G30: =Model!W47 -> 3113.571 | H30: =Model!X47 -> 3112.4554 | I30: =Model!Y47 -> 3112.8366 | J30: =Model!Z47 -> 3144.453 | K30: =Model!AA47 -> 3116.0915
B31: MC | D31: =D29*D30 -> 87339.337 | E31: =E29*E30 -> 103086.12 | F31: =F29*F30 -> 93476.857 | G31: =G29*G30 -> 93531.672 | H31: =H29*H30 -> 96641.74 | I31: =I29*I30 -> 133011.51 | J31: =J29*J30 -> 185522.73 | K31: =K29*K30 -> 164529.63
B32: Net Debt | D32: =Model!T81+Model!T82+Model!T85+Model!T86-Model!T72-Model!T71-Model!T66 -> -6973 | E32: =Model!U81+Model!U82+Model!U85+Model!U86-Model!U72-Model!U71-Model!U66 -> -1498 | F32: =Model!V81+Model!V82+Model!V85+Model!V86-Model!V72-Model!V71-Model!V66 -> -1670 | G32: =Model!W81+Model!W82+Model!W85+Model!W86-Model!W72-Model!W71-Model!W66 -> -3842 | H32: =Model!X81+Model!X82+Model!X85+Model!X86-Model!X72-Model!X71-Model!X66 -> -4964 | I32: =Model!Y81+Model!Y82+Model!Y85+Model!Y86-Model!Y72-Model!Y71-Model!Y66 -> -6253 | J32: =Model!Z81+Model!Z82+Model!Z85+Model!Z86-Model!Z72-Model!Z71-Model!Z66 -> -6223 | K32: =Model!AA81+Model!AA82+Model!AA85+Model!AA86-Model!AA72-Model!AA71-Model!AA66 -> -5496
B33: EV | D33: =D31+D32 -> 80366.337 | E33: =E31+E32 -> 101588.12 | F33: =F31+F32 -> 91806.857 | G33: =G31+G32 -> 89689.672 | H33: =H31+H32 -> 91677.74 | I33: =I31+I32 -> 126758.51 | J33: =J31+J32 -> 179299.73 | K33: =K31+K32 -> 159033.63
B34: Equity-Multiples
B35: P/E | D35: =D31/Model!T44 -> 25.359854 | E35: =E31/Model!U44 -> 28.320362 | F35: =F31/Model!V44 -> 84.594441 | G35: =G31/Model!W44 -> 28.849991 | H35: =H31/Model!X44 -> 23.405604 | I35: =I31/Model!Y44 -> 24.723328 | J35: =J31/Model!Z44 -> 31.626786 | K35: =K31/Model!AA44 -> 26.455962 | M35: =AVERAGE(G35:I35,D35:E35) -> 26.131828
B36: PEG | E36: =E35/((Model!U44/Model!T44-1)*100) -> 4.9762921 | F36: =F35/((Model!V44/Model!U44-1)*100) -> -1.2146894 | G36: =G35/((Model!W44/Model!V44-1)*100) -> 0.14917754 | H36: =H35/((Model!X44/Model!W44-1)*100) -> 0.8554788 | I36: =I35/((Model!Y44/Model!X44-1)*100) -> 0.81600817 | J36: =J35/((Model!Z44/Model!Y44-1)*100) -> 3.5010722 | K36: =K35/((Model!AA44/Model!Z44-1)*100) -> 4.3963364 | M36: =AVERAGE(G36:I36,D36:E36) -> 1.6992392
B37: P/B | D37: =D31/Model!T79 -> 5.9483305 | E37: =E31/Model!U79 -> 6.8958537 | F37: =F31/Model!V79 -> 6.4245263 | G37: =G31/Model!W79 -> 5.9351274 | H37: =H31/Model!X79 -> 5.6737944 | I37: =I31/Model!Y79 -> 7.1235811 | J37: n.a. | K37: n.a. | M37: =AVERAGE(G37:I37,D37:E37) -> 6.3153374
B38: Entity -Multiples
B39: EV/Sales | D39: =D33/Model!T29 -> 3.0738702 | E39: =E33/Model!U29 -> 3.5913358 | F39: =F33/Model!V29 -> 4.499895 | G39: =G33/Model!W29 -> 3.2360251 | H39: =H33/Model!X29 -> 2.8148773 | I39: =I33/Model!Y29 -> 3.526261 | J39: =J33/Model!Z29 -> 4.641223 | K39: =K33/Model!AA29 -> 3.9894047 | M39: =AVERAGE(G39:I39,D39:E39) -> 3.2484739
B40: EV/EBITDA | D40: =D33/Model!T34 -> 14.727201 | E40: =E33/Model!U34 -> 13.368617 | F40: =F33/Model!V34 -> 20.172898 | G40: =G33/Model!W34 -> 12.486381 | H40: =H33/Model!X34 -> 10.601034 | I40: =I33/Model!Y34 -> 12.87019 | J40: =J33/Model!Z34 -> 16.71169 | K40: =K33/Model!AA34 -> 14.114993 | M40: =AVERAGE(G40:I40,D40:E40) -> 12.810685
B41: EV/EBIT | D41: =D33/Model!T37 -> 18.445338 | E41: =E33/Model!U37 -> 21.283913 | F41: =F33/Model!V37 -> 60.960729 | G41: =G33/Model!W37 -> 20.945743 | H41: =H33/Model!X37 -> 16.614306 | I41: =I33/Model!Y37 -> 18.619052 | J41: =J33/Model!Z37 -> 23.732591 | K41: =K33/Model!AA37 -> 19.886661 | M41: =AVERAGE(G41:I41,D41:E41) -> 19.18167

Sheet DCF
A1: Main | B1: DCF
B3: Ticker | E3: Indexy | G3: Share Price | J3: =Main!J3 -> 54.85
B4: Date | E4: 45519 | G4: Fair Share Price | J4: =V60 -> 68.98918
B5: End of FY | E5: 45657 | G5: Implied Upside | J5: =J4/J3-1 -> 0.25777904
A7: x | B7: Assumptions
B9: Switches | G9: Conservative Case | L9: Base Case | Q9: Optimistic Case
B10: Assuptions | G10: Assuptions | I10: Year | J10: Metic | L10: Assuptions | N10: Year | O10: Metic | Q10: Assuptions | S10: Year | T10: Metic
B11: Revenue | E11: 2 | G11: Revenue | L11: Revenue | Q11: Revenue
B12: EBIT | E12: 2
B13: WACC | E13: 2 | G13: EBIT | L13: EBIT | Q13: EBIT
B14: TGR | E14: 2
B16: Valuation
B17: WACC | E17: =CHOOSE(E13,J17,O17,T17) -> 0.08 | G17: WACC | L17: WACC | O17: 0.08 | Q17: WACC
B18: TGR | E18: =CHOOSE(E14,J18,O18,T18) -> 0.02 | G18: TGR | L18: TGR | O18: 0.02 | Q18: TGR
A22: x | B22: Model | G22: 18 | H22: =G22+1 -> 19 | I22: =H22+1 -> 20 | J22: =I22+1 -> 21 | K22: =J22+1 -> 22 | L22: =K22+1 -> 23 | M22: =L22+1 -> 24 | N22: =M22+1 -> 25 | O22: =N22+1 -> 26 | ... V22: =U22+1 -> 33
B23: Revenue | G23: =Model!T29 -> 26145 | H23: =Model!U29 -> 28287 | I23: =Model!V29 -> 20402 | J23: =Model!W29 -> 27716 | K23: =Model!X29 -> 32569 | L23: =Model!Y29 -> 35947 | M23: =L23*(1+M24) -> 38463.29 | N23: =M23*(1+N24) -> 41128.796 | O23: =N23*(1+O24) -> 43950.519 | P23: =O23*(1+P24) -> 46935.679 | Q23: =P23*(1+Q24) -> 50091.715 | R23: =Q23*(1+R24) -> 53426.286 | S23: =R23*(1+S24) -> 56947.271 | T23: =S23*(1+T24) -> 60662.771 | ... V23: =U23*(1+V24) -> 68710.826
B24: Growth (%) | H24: =H23/G23-1 -> 0.081927711 | I24: =I23/H23-1 -> -0.27874996 | J24: =J23/I23-1 -> 0.35849427 | K24: =K23/J23-1 -> 0.17509742 | L24: =L23/K23-1 -> 0.10371826 | M24: {=OFFSET(M24,$E$11,,)} -> 0.07 | N24: {=OFFSET(N24,$E$11,,)} -> 0.0693 | O24: {=OFFSET(O24,$E$11,,)} -> 0.068607 | P24: {=OFFSET(P24,$E$11,,)} -> 0.06792093 | Q24: {=OFFSET(Q24,$E$11,,)} -> 0.067241721 | R24: {=OFFSET(R24,$E$11,,)} -> 0.066569303 | S24: {=OFFSET(S24,$E$11,,)} -> 0.06590361 | T24: {=OFFSET(T24,$E$11,,)} -> 0.065244574 | ... V24: {=OFFSET(V24,$E$11,,)} -> 0.063946207
B25: Conservative Case | M25: 0.07 | N25: =M25*(1-5%) -> 0.0665 | O25: =N25*(1-5%) -> 0.063175 | P25: =O25*(1-5%) -> 0.06001625 | Q25: =P25*(1-5%) -> 0.057015437 | R25: =Q25*(1-5%) -> 0.054164666 | S25: =R25*(1-5%) -> 0.051456432 | T25: =S25*(1-5%) -> 0.048883611 | U25: =T25*(1-5%) -> 0.04643943 | V25: =U25*(1-5%) -> 0.044117459
B26: Base Case | M26: 0.07 | N26: =M26*(1-1%) -> 0.0693 | O26: =N26*(1-1%) -> 0.068607 | P26: =O26*(1-1%) -> 0.06792093 | Q26: =P26*(1-1%) -> 0.067241721 | R26: =Q26*(1-1%) -> 0.066569303 | S26: =R26*(1-1%) -> 0.06590361 | T26: =S26*(1-1%) -> 0.065244574 | U26: =T26*(1-1%) -> 0.064592129 | V26: =U26*(1-1%) -> 0.063946207
B27: Optimisitic Case | M27: 0.07 | N27: =M27*(1+1%) -> 0.0707 | O27: =N27*(1+1%) -> 0.071407 | P27: =O27*(1+1%) -> 0.07212107 | Q27: =P27*(1+1%) -> 0.072842281 | R27: =Q27*(1+1%) -> 0.073570704 | S27: 0.071 | T27: 0.069 | U27: 0.066 | V27: 0.064
B29: EBIT | G29: =Model!T34-Model!T94 -> 4357 | H29: =Model!U34-Model!U94 -> 4773 | I29: =Model!V34-Model!V94 -> 1506 | J29: =Model!W34-Model!W94 -> 4282 | K29: =Model!X34-Model!X94 -> 5749 | L29: =Model!Y34-Model!Y94 -> 6808 | M29: =M30*M23 -> 7692.658 | N29: =N30*N23 -> 8431.4032 | O29: =O30*O23 -> 9229.6091 | P29: =P30*P23 -> 10091.171 | Q29: =Q30*Q23 -> 11020.177 | R29: =R30*R23 -> 12288.046 | S29: =S30*S23 -> 13382.609 | T29: =T30*T23 -> 14559.065 | ... V29: =V30*V23 -> 17177.707
B30: % of Sales | G30: =G29/G23 -> 0.16664754 | H30: =H29/H23 -> 0.16873475 | I30: =I29/I23 -> 0.073816293 | J30: =J29/J23 -> 0.1544956 | K30: =K29/K23 -> 0.17651755 | L30: =L29/L23 -> 0.18938994 | M30: {=OFFSET(M30,$E$12,,)} -> 0.2 | N30: {=OFFSET(N30,$E$12,,)} -> 0.205 | O30: {=OFFSET(O30,$E$12,,)} -> 0.21 | P30: {=OFFSET(P30,$E$12,,)} -> 0.215 | Q30: {=OFFSET(Q30,$E$12,,)} -> 0.22 | R30: {=OFFSET(R30,$E$12,,)} -> 0.23 | S30: {=OFFSET(S30,$E$12,,)} -> 0.235 | T30: {=OFFSET(T30,$E$12,,)} -> 0.24 | ... V30: {=OFFSET(V30,$E$12,,)} -> 0.25
B31: Conservative Case | M31: 0.19 | N31: 0.19 | O31: 0.19 | P31: 0.19 | Q31: 0.19 | R31: 0.19 | S31: 0.19 | T31: 0.19 | U31: 0.19 | V31: 0.19
B32: Base Case | M32: 0.2 | N32: 0.205 | O32: 0.21 | P32: 0.215 | Q32: 0.22 | R32: 0.23 | S32: 0.235 | T32: 0.24 | U32: 0.245 | V32: 0.25
B33: Optimisitic Case | M33: 0.2 | N33: =M33*(1+5%) -> 0.21 | O33: =N33*(1+5%) -> 0.2205 | P33: =O33*(1+5%) -> 0.231525 | Q33: =P33*(1+5%) -> 0.24310125 | R33: =Q33*(1+5%) -> 0.25525631 | S33: =R33*(1+5%) -> 0.26801913 | T33: =S33*(1+5%) -> 0.28142008 | U33: =T33*(1+5%) -> 0.29549109 | V33: =U33*(1+5%) -> 0.31026564
B35: Taxes | G35: =Model!T41 -> 980 | H35: =Model!U41 -> 1034 | I35: =Model!V41 -> 297 | J35: =Model!W41 -> 949 | K35: =Model!X41 -> 1211 | L35: =Model!Y41 -> 1475 | M35: =M36*M29 -> 1692.3848 | N35: =N36*N29 -> 1854.9087 | O35: =O36*O29 -> 2030.514 | P35: =P36*P29 -> 2220.0576 | Q35: =Q36*Q29 -> 2424.439 | R35: =R36*R29 -> 2703.3701 | S35: =S36*S29 -> 2944.1739 | T35: =T36*T29 -> 3202.9943 | ... V35: =V36*V29 -> 3779.0954
B36: Tax Rate (%) | G36: =G35/G29 -> 0.22492541 | H36: =H35/H29 -> 0.21663524 | I36: =I35/I29 -> 0.19721116 | J36: =J35/J29 -> 0.22162541 | K36: =K35/K29 -> 0.21064533 | L36: =L35/L29 -> 0.21665687 | M36: 0.22 | N36: 0.22 | O36: 0.22 | P36: 0.22 | Q36: 0.22 | R36: 0.22 | S36: 0.22 | T36: 0.22 | U36: 0.22 | V36: 0.22
B38: Nopat | G38: =G29-G35 -> 3377 | H38: =H29-H35 -> 3739 | I38: =I29-I35 -> 1209 | J38: =J29-J35 -> 3333 | K38: =K29-K35 -> 4538 | L38: =L29-L35 -> 5333 | M38: =M29-M35 -> 6000.2732 | N38: =N29-N35 -> 6576.4945 | ... V38: =V29-V35 -> 13398.611
B40: D&A | G40: =Model!T94 -> 1100 | H40: =Model!U94 -> 2826 | I40: =Model!V94 -> 3045 | J40: =Model!W94 -> 2901 | K40: =Model!X94 -> 2899 | L40: =Model!Y94 -> 3041 | M40: =M41*M23 -> 3269.3797 | N40: =N41*N23 -> 3216.2718 | O40: =O41*O23 -> 3161.9762 | P40: =P41*P23 -> 3106.6013 | Q40: =Q41*Q23 -> 3050.2549 | R40: =R41*R23 -> 2993.0436 | S40: =S41*S23 -> 2935.0723 | T40: =T41*T23 -> 2876.4443 | ... V40: =V41*V23 -> 2757.6208
B41: % of Sales | G41: =G40/G23 -> 0.042073054 | H41: =H40/H23 -> 0.09990455 | I41: =I40/I23 -> 0.14925007 | J41: =J40/J23 -> 0.10466878 | K41: =K40/K23 -> 0.089011023 | L41: =L40/L23 -> 0.084596767 | M41: 0.085 | N41: =M41*(1-8%) -> 0.0782 | O41: =N41*(1-8%) -> 0.071944 | P41: =O41*(1-8%) -> 0.06618848 | Q41: =P41*(1-8%) -> 0.060893402 | R41: =Q41*(1-8%) -> 0.056021929 | S41: =R41*(1-8%) -> 0.051540175 | T41: =S41*(1-8%) -> 0.047416961 | U41: =T41*(1-8%) -> 0.043623604 | V41: =U41*(1-8%) -> 0.040133716
B43: CapEx | G43: =Model!T105+Model!T104 -> -1462 | H43: =Model!U105+Model!U104 -> -1112 | I43: =Model!V105+Model!V104 -> -677 | J43: =Model!W105+Model!W104 -> -1126 | K43: =Model!X105+Model!X104 -> -1415 | L43: =Model!Y105+Model!Y104 -> -1872 | M43: =M44*M23 -> -2000.0911 | N43: =N44*N23 -> -2031.7625 | O43: =O44*O23 -> -2062.5979 | P43: =P44*P23 -> -2092.5569 | Q43: =Q44*Q23 -> -2121.6008 | R43: =R44*R23 -> -2149.6926 | S43: =S44*S23 -> -2176.7968 | T43: =T44*T23 -> -2202.8799 | ... V43: =V44*V23 -> -2251.8578
B44: % of Sales | G44: =G43/G23 -> -0.055918914 | H44: =H43/H23 -> -0.039311344 | I44: =I43/I23 -> -0.033183021 | J44: =J43/J23 -> -0.040626353 | K44: =K43/K23 -> -0.043446222 | L44: =L43/L23 -> -0.052076668 | M44: -0.052 | N44: =M44*(1-5%) -> -0.0494 | O44: =N44*(1-5%) -> -0.04693 | P44: =O44*(1-5%) -> -0.0445835 | Q44: =P44*(1-5%) -> -0.042354325 | R44: =Q44*(1-5%) -> -0.040236609 | S44: =R44*(1-5%) -> -0.038224778 | T44: =S44*(1-5%) -> -0.036313539 | U44: =T44*(1-5%) -> -0.034497862 | V44: =U44*(1-5%) -> -0.032772969
B46: Change in WC | G46: =Model!T102 -> -349 | H46: =Model!U102 -> 205 | I46: =Model!V102 -> -847 | J46: =Model!W102 -> 223 | K46: =Model!X102 -> -669 | L46: =Model!Y102 -> -57 | M46: =M47*M23 -> -384.6329 | N46: =N47*N23 -> -394.83644 | O46: =O47*O23 -> -405.04799 | P46: =P47*P23 -> -415.25685 | Q46: =Q47*Q23 -> -425.45226 | R46: =R47*R23 -> -435.62335 | S46: =S47*S23 -> -445.7592 | T46: =T47*T23 -> -455.84887 | ... V46: =V47*V23 -> -475.84583
B47: % of Sales | G47: =G46/G23 -> -0.013348633 | H47: =H46/H23 -> 0.0072471453 | I47: =I46/I23 -> -0.041515538 | J47: =J46/J23 -> 0.0080458941 | K47: =K46/K23 -> -0.020541005 | L47: =L46/L23 -> -0.0015856678 | M47: -0.01 | N47: =M47*(1-4%) -> -0.0096 | O47: =N47*(1-4%) -> -0.009216 | P47: =O47*(1-4%) -> -0.00884736 | Q47: =P47*(1-4%) -> -0.0084934656 | R47: =Q47*(1-4%) -> -0.008153727 | S47: =R47*(1-4%) -> -0.0078275779 | T47: =S47*(1-4%) -> -0.0075144748 | U47: =T47*(1-4%) -> -0.0072138958 | V47: =U47*(1-4%) -> -0.00692534
B49: Unlevered Free Cashflow | G49: =G38+G40+G43+G46 -> 2666 | H49: =H38+H40+H43+H46 -> 5658 | I49: =I38+I40+I43+I46 -> 2730 | J49: =J38+J40+J43+J46 -> 5331 | K49: =K38+K40+K43+K46 -> 5353 | L49: =L38+L40+L43+L46 -> 6445 | M49: =M38+M40+M43+M46 -> 6884.9289 | N49: =N38+N40+N43+N46 -> 7366.1674 | ... V49: =V38+V40+V43+V46 -> 13428.528
B50: Present Value of unlevered FC | M50: =(M49*M51)/(1+$D$13)^M51 -> 2600.9731 | N50: =N49/(1+$D$13)^N51 -> 7366.1674 | O50: =O49/(1+$D$13)^O51 -> 7893.4254 | P50: =P49/(1+$D$13)^P51 -> 8469.901 | Q50: =Q49/(1+$D$13)^Q51 -> 9098.9402 | R50: =R49/(1+$D$13)^R51 -> 9992.4034 | S50: =S49/(1+$D$13)^S51 -> 10750.951 | T50: =T49/(1+$D$13)^T51 -> 11573.786 | U50: =U49/(1+$D$13)^U51 -> 12464.919 | V50: =V49/(1+$D$13)^V51 -> 13428.528
B51: Discount Period | M51: =YEARFRAC(E4,E5) -> 0.37777778 | N51: =M51+1 -> 1.3777778 | O51: =N51+1 -> 2.3777778 | P51: =O51+1 -> 3.3777778 | Q51: =P51+1 -> 4.3777778 | R51: =Q51+1 -> 5.3777778 | S51: =R51+1 -> 6.3777778 | T51: =S51+1 -> 7.3777778 | U51: =T51+1 -> 8.3777778 | V51: =U51+1 -> 9.3777778
B52: Sum of Present Value | V52: =SUM(M50:V50) -> 93639.995
B53: Terminal Value | V53: =(V49*(1+E18))/(E17-E18) -> 228284.98
B54: Present Value of TV | V54: =V53/(1+E17)^V51 -> 110926.88
B55: Enterprise Value | V55: =V52+V54 -> 204566.87
B56: (+) Cash | V56: =Main!J6 -> 10399
B57: (-) Debt | V57: =Main!J7 -> 1
B58: Equity Value | V58: =V55+V56-V57 -> 214964.87
B59: Number of Shares | V59: =Main!J4 -> 3115.9215
B60: Share Price | V60: =V58/V59 -> 68.98918
A64: x | B64: Sensitivity Analysis
C66: TGR
B67: WACC
