Workbook

Sheet Main
A1: Meta Platforms Inc
A2: numbers in mio USD | H2: Price | I2: 535
H3: Shares | I3: =2205.128509+342.377716 -> 2547.5062 | J3: Q226
B4: SEC | H4: MC | I4: =I2*I3 -> 1362915.8
B5: META | H5: Cash | I5: =15462+74798 -> 90260 | J5: Q226
H6: Debt | I6: 83664 | J6: Q226
A7: x | B7: Mangement | H7: EV | I7: =I4-I5+I6 -> 1356319.8
B8: CEO | C8: Mark Zuckerberg
B9: COO | C9: Javier Olivan | H9: Founded: | I9: 2004 by Mark Zuckerberg
B10: CPO | C10: Chris Cox | H10: Employees: | I10: 74067
B11: CLO | C11: Jennifer Newstead
B12: CFO | C12: Susan Li
B13: CTO | C13: Andrew Boswoth
A15: x | B15: Notes
B16: Apps: Facebook, Instagram, Messanger, Whats App, Theads
B17: Revenue:
B18: Ads | C18: Substantially all of the Revenue -> Ads displayed on Facebook, Instagram, Messanger, Whats App and third party mobile apllications
B19: Other | C19: Whats App Buisness Platform, net fees from devolopers using Metas payment infrastructures and other
B20: Reality Labs | C20: Delivery of consumer hadware products such as Meta Quests, wearables, and related software content, Meta Horizon
C21: Meta Orion Glasses in colloborations with Luxottica (Ray Ban)

Sheet Model
A1: Main
C2: Q123 | D2: Q223 | E2: Q323 | F2: Q423 | G2: Q124 | H2: Q224 | I2: Q324 | J2: Q424 | K2: Q125 | L2: Q225 | M2: Q325 | N2: Q425 | O2: Q126 | P2: Q226 | Q2: Q326 | R2: Q426 | T2: FY18 | U2: FY19 | V2: FY20 | W2: FY21 | X2: FY22 | Y2: FY23 | Z2: FY24 | AA2: FY25
B3: DAPs in billions | C3: 3.02 | D3: 3.07 | E3: 3.14 | F3: 3.19 | G3: 3.24 | H3: 3.27 | I3: 3.29 | J3: 3.35 | K3: 3.43 | L3: 3.48 | M3: 3.54 | N3: 3.58 | O3: 3.56 | P3: 3.6 | T3: 2.03 | U3: 2.26 | V3: 2.6 | W3: 2.82 | X3: 2.96 | Y3: 3.19 | Z3: 3.35 | AA3: 3.58
B4: ARPP | C4: =C10/(C3*1000) -> 9.3728477 | D4: =D10/(D3*1000) -> 10.333225 | E4: =E10/(E3*1000) -> 1.0815287 | F4: =F10/(F3*1000) -> 21.812226 | G4: =G10/(G3*1000) -> 11.115741 | H4: =H10/(H3*1000) -> 11.840367 | I4: =I10/(I3*1000) -> 12.255015 | J4: =J10/(J3*1000) -> 14.120299 | ... P4: =P10/(P3*1000) -> 16.769444 | T4: =T10/(T3*1000) -> 27.506404 | U4: =U10/(U3*1000) -> 31.281858 | V4: =V10/(V3*1000) -> 32.625385 | W4: =W10/(W3*1000) -> 41.012411 | X4: =X10/(X3*1000) -> 38.665541 | Y4: =Y10/(Y3*1000) -> 41.694671 | Z4: =Z10/(Z3*1000) -> 48.464179 | AA4: =AA10/(AA3*1000) -> 55.519274
B5: Ad Impressions | C5: 0.26 | D5: 0.34 | E5: 0.31 | F5: 0.21 | G5: 0.2 | H5: 0.1 | I5: 0.07 | J5: 0.06 | K5: 0.05 | L5: 0.11 | M5: 0.14 | N5: 0.18 | O5: 0.19 | P5: 0.14 | T5: n.a. | U5: n.a. | V5: n.a. | W5: n.a. | X5: 0.26 | Y5: 0.21 | Z5: 0.06 | AA5: 0.18
B6: Change in APPA | C6: -0.17 | D6: -0.16 | E6: -0.06 | F6: 0.02 | G6: 0.06 | H6: 0.1 | I6: 0.11 | J6: 0.14 | K6: 0.1 | L6: 0.09 | M6: 0.1 | N6: 0.06 | O6: 0.12 | P6: 0.12 | T6: n.a. | U6: n.a. | V6: n.a. | W6: n.a. | X6: -0.17 | Y6: 0.02 | Z6: 0.14 | AA6: 0.06
B8: Advertising | C8: 28101 | D8: 31498 | E8: 33643 | F8: =+Y8-SUM(C8:E8) -> 38706 | G8: 35635 | H8: 38329 | I8: 39885 | J8: =+Z8-SUM(G8:I8) -> 46784 | K8: 41392 | L8: 46563 | M8: 50082 | N8: =+AA8-SUM(K8:M8) -> 58138 | O8: 55024 | P8: 59363 | T8: 55013 | U8: 69655 | V8: 84169 | W8: 114934 | X8: 113642 | Y8: 131948 | Z8: 160633 | AA8: 196175
B9: Other | C9: 205 | D9: 225 | E9: 293 | F9: =+Y9-SUM(C9:E9) -> 335 | G9: 380 | H9: 389 | I9: 434 | J9: =+Z9-SUM(G9:I9) -> 519 | K9: 510 | L9: 583 | M9: 690 | N9: =+AA9-SUM(K9:M9) -> 801 | O9: 885 | P9: 1007 | T9: 825 | U9: 1042 | V9: 657 | W9: 721 | X9: 808 | Y9: 1058 | Z9: 1722 | AA9: 2584
B10: Apps | C10: 28306 | D10: 31723 | E10: 3396 | F10: =+Y10-SUM(C10:E10) -> 69581 | G10: 36015 | H10: 38718 | I10: 40319 | J10: =+Z10-SUM(G10:I10) -> 47303 | K10: 41902 | L10: 47146 | M10: 50772 | N10: =+AA10-SUM(K10:M10) -> 58939 | O10: 55909 | P10: 60370 | T10: 55838 | U10: 70697 | V10: 84826 | W10: 115655 | X10: 114450 | Y10: 133006 | Z10: 162355 | AA10: 198759
B11: Reality Labs | C11: 3339 | D11: 276 | E11: 210 | F11: =+Y11-SUM(C11:E11) -> -1929 | G11: 440 | H11: 353 | I11: 270 | J11: =+Z11-SUM(G11:I11) -> 1083 | K11: 412 | L11: 370 | M11: 470 | N11: =+AA11-SUM(K11:M11) -> 955 | O11: 402 | P11: 431 | T11: 0 | U11: 0 | V11: 1139 | W11: 2274 | X11: 2159 | Y11: 1896 | Z11: 2146 | AA11: 2207
B12: Revenue | C12: 28645 | D12: 31999 | E12: 34146 | F12: =+Y12-SUM(C12:E12) -> 40112 | G12: 36455 | H12: 39071 | I12: 40589 | J12: =+Z12-SUM(G12:I12) -> 48386 | K12: 42314 | L12: 47516 | M12: 51242 | N12: =+AA12-SUM(K12:M12) -> 59894 | O12: 56311 | P12: 60801 | T12: 55838 | U12: 70697 | V12: 85965 | W12: 117929 | X12: 116609 | Y12: 134902 | Z12: 164501 | AA12: 200966 | AB12: 213520 | AC12: =+AB12*(1+AC28) -> 225524.4 | AD12: =+AC12*(1+AD28) -> 236935.78 | AE12: =+AD12*(1+AE28) -> 247725.69 | AF12: =+AE12*(1+AF28) -> 257878.84 | AG12: =+AF12*(1+AG28) -> 267391.18 | AH12: =+AG12*(1+AH28) -> 276268.09 | AI12: =+AH12*(1+AI28) -> 284522.54
B13: COGS | C13: 6108 | D13: 5945 | E13: 6210 | F13: =+Y13-SUM(C13:E13) -> 7696 | G13: 6640 | H13: 7308 | I13: 7375 | J13: =+Z13-SUM(G13:I13) -> 8838 | K13: 7572 | L13: 8491 | M13: 9206 | N13: =+AA13-SUM(K13:M13) -> 10906 | O13: 10218 | P13: 11330 | T13: 9355 | U13: 12770 | V13: 16692 | W13: 22649 | X13: 25249 | Y13: 25959 | Z13: 30161 | AA13: 36175
B14: Gross Profit | C14: =C12-C13 -> 22537 | D14: =D12-D13 -> 26054 | E14: =E12-E13 -> 27936 | F14: =F12-F13 -> 32416 | G14: =G12-G13 -> 29815 | H14: =H12-H13 -> 31763 | I14: =I12-I13 -> 33214 | J14: =J12-J13 -> 39548 | ... P14: =P12-P13 -> 49471 | T14: =T12-T13 -> 46483 | U14: =U12-U13 -> 57927 | V14: =V12-V13 -> 69273 | W14: =W12-W13 -> 95280 | X14: =X12-X13 -> 91360 | Y14: =Y12-Y13 -> 108943 | Z14: =Z12-Z13 -> 134340 | AA14: =AA12-AA13 -> 164791
B15: R&D | C15: 9381 | D15: 9344 | E15: 9241 | F15: =+Y15-SUM(C15:E15) -> 10517 | G15: 9978 | H15: 10537 | I15: 11177 | J15: =+Z15-SUM(G15:I15) -> 12181 | K15: 12150 | L15: 12942 | M15: 15144 | N15: =+AA15-SUM(K15:M15) -> 17136 | O15: 17699 | P15: 21656 | T15: 10273 | U15: 13600 | V15: 18447 | W15: 24655 | X15: 35338 | Y15: 38483 | Z15: 43873 | AA15: 57372
B16: Marketing and Sales | C16: 3044 | D16: 3154 | E16: 2877 | F16: =+Y16-SUM(C16:E16) -> 3226 | G16: 2564 | H16: 2721 | I16: 2822 | J16: =+Z16-SUM(G16:I16) -> 3240 | K16: 2757 | L16: 2979 | M16: 2845 | N16: =+AA16-SUM(K16:M16) -> 3410 | O16: 2908 | P16: 3431 | T16: 7846 | U16: 9876 | V16: 11591 | W16: 14043 | X16: 15262 | Y16: 12301 | Z16: 11347 | AA16: 11991
B17: General and Administrative | C17: 2885 | D17: 4164 | E17: 2070 | F17: =+Y17-SUM(C17:E17) -> 2289 | G17: 3455 | H17: 3658 | I17: 1865 | J17: =+Z17-SUM(G17:I17) -> 762 | K17: 2280 | L17: 2663 | M17: 3512 | N17: =+AA17-SUM(K17:M17) -> 3697 | O17: 2614 | P17: 5609 | T17: 3451 | U17: 10465 | V17: 6564 | W17: 9829 | X17: 11816 | Y17: 11408 | Z17: 9740 | AA17: 12152
B18: Operating Profit | C18: =C14-SUM(C15:C17) -> 7227 | D18: =D14-SUM(D15:D17) -> 9392 | E18: =E14-SUM(E15:E17) -> 13748 | F18: =F14-SUM(F15:F17) -> 16384 | G18: =G14-SUM(G15:G17) -> 13818 | H18: =H14-SUM(H15:H17) -> 14847 | I18: =I14-SUM(I15:I17) -> 17350 | J18: =J14-SUM(J15:J17) -> 23365 | ... P18: =P14-SUM(P15:P17) -> 18775 | T18: =T14-SUM(T15:T17) -> 24913 | U18: =U14-SUM(U15:U17) -> 23986 | V18: =V14-SUM(V15:V17) -> 32671 | W18: =W14-SUM(W15:W17) -> 46753 | X18: =X14-SUM(X15:X17) -> 28944 | Y18: =Y14-SUM(Y15:Y17) -> 46751 | Z18: =Z14-SUM(Z15:Z17) -> 69380 | AA18: =AA14-SUM(AA15:AA17) -> 83276
B19: Interest Income | C19: 80 | D19: -99 | E19: 272 | F19: =+Y19-SUM(C19:E19) -> 424 | G19: 365 | H19: 259 | I19: 472 | J19: =+Z19-SUM(G19:I19) -> 187 | K19: 827 | L19: 93 | M19: 1128 | N19: =+AA19-SUM(K19:M19) -> 608 | O19: -1120 | P19: -19 | T19: 448 | U19: 826 | V19: 509 | W19: 531 | X19: -125 | Y19: 677 | Z19: 1283 | AA19: 2656
B20: Pretax Income | C20: =C18+C19 -> 7307 | D20: =D18+D19 -> 9293 | E20: =E18+E19 -> 14020 | F20: =F18+F19 -> 16808 | G20: =G18+G19 -> 14183 | H20: =H18+H19 -> 15106 | I20: =I18+I19 -> 17822 | J20: =J18+J19 -> 23552 | ... P20: =P18+P19 -> 18756 | T20: =T18+T19 -> 25361 | U20: =U18+U19 -> 24812 | V20: =V18+V19 -> 33180 | W20: =W18+W19 -> 47284 | X20: =X18+X19 -> 28819 | Y20: =Y18+Y19 -> 47428 | Z20: =Z18+Z19 -> 70663 | AA20: =AA18+AA19 -> 85932
B21: Income Tax | C21: 1598 | D21: 1505 | E21: 2437 | F21: =+Y21-SUM(C21:E21) -> 2790 | G21: 1814 | H21: 1641 | I21: 2134 | J21: =+Z21-SUM(G21:I21) -> 2714 | K21: 1738 | L21: 2197 | M21: 18954 | N21: =+AA21-SUM(K21:M21) -> 2585 | O21: -5021 | P21: 2908 | T21: =3249+1 -> 3250 | U21: 6327 | V21: 4034 | W21: 7914 | X21: 5619 | Y21: 8330 | Z21: 8303 | AA21: 25474
B22: Net Income | C22: =C20-C21 -> 5709 | D22: =D20-D21 -> 7788 | E22: =E20-E21 -> 11583 | F22: =F20-F21 -> 14018 | G22: =G20-G21 -> 12369 | H22: =H20-H21 -> 13465 | I22: =I20-I21 -> 15688 | J22: =J20-J21 -> 20838 | ... P22: =P20-P21 -> 15848 | T22: =T20-T21 -> 22111 | U22: =U20-U21 -> 18485 | V22: =V20-V21 -> 29146 | W22: =W20-W21 -> 39370 | X22: =X20-X21 -> 23200 | Y22: =Y20-Y21 -> 39098 | Z22: =Z20-Z21 -> 62360 | AA22: =AA20-AA21 -> 60458
B24: EPS | C24: =C22/C25 -> 2.2068032 | D24: =D22/D25 -> 3.0327103 | E24: =E22/E25 -> 4.4965062 | F24: =F22/F25 -> 5.4459984 | G24: =G22/G25 -> 4.8601179 | H24: =H22/H25 -> 5.3137332 | I24: =I22/I25 -> 6.2032424 | J24: =J22/J25 -> 8.2244682 | ... P24: =P22/P25 -> 6.2320094 | T24: =T22/T25 -> 7.6508651 | U24: =U22/U25 -> 6.4768746 | V24: =V22/V25 -> 10.22308 | W24: =W22/W25 -> 13.98579 | X24: =X22/X25 -> 8.6341645 | Y24: =Y22/Y25 -> 15.189588 | Z24: =Z22/Z25 -> 24.609313 | AA24: =AA22/AA25 -> 23.981753
B25: Shares | C25: 2587 | D25: 2568 | E25: 2576 | F25: =+Y25 -> 2574 | G25: 2545 | H25: 2534 | I25: 2529 | J25: 2533.6593 | K25: 2527 | L25: 2518 | M25: 2517 | N25: 2521 | O25: 2534 | P25: 2543 | T25: 2890 | U25: 2854 | V25: 2851 | W25: 2815 | X25: 2687 | Y25: 2574 | Z25: 2534 | AA25: 2521
B27: DAP Growth | G27: =G3/C3-1 -> 0.072847682 | H27: =H3/D3-1 -> 0.06514658 | I27: =I3/E3-1 -> 0.047770701 | J27: =J3/F3-1 -> 0.05015674 | K27: =K3/G3-1 -> 0.058641975 | L27: =L3/H3-1 -> 0.064220183 | M27: =M3/I3-1 -> 0.075987842 | N27: =N3/J3-1 -> 0.068656716 | ... P27: =P3/L3-1 -> 0.034482759 | U27: =+U3/T3-1 -> 0.11330049 | V27: =+V3/U3-1 -> 0.15044248 | W27: =+W3/V3-1 -> 0.084615385 | X27: =+X3/W3-1 -> 0.04964539 | Y27: =+Y3/X3-1 -> 0.077702703 | Z27: =+Z3/Y3-1 -> 0.05015674 | AA27: =+AA3/Z3-1 -> 0.068656716
B28: Revenue YoY | G28: =G12/C12-1 -> 0.27264793 | H28: =H12/D12-1 -> 0.22100691 | I28: =I12/E12-1 -> 0.18868974 | J28: =J12/F12-1 -> 0.20627244 | K28: =K12/G12-1 -> 0.16071869 | L28: =L12/H12-1 -> 0.21614497 | M28: =M12/I12-1 -> 0.26246027 | N28: =N12/J12-1 -> 0.23783739 | ... P28: =P12/L12-1 -> 0.27959003 | U28: =+U12/T12-1 -> 0.2661091 | V28: =+V12/U12-1 -> 0.2159639 | W28: =+W12/V12-1 -> 0.37182574 | X28: =+X12/W12-1 -> -0.011193176 | Y28: =+Y12/X12-1 -> 0.15687468 | Z28: =+Z12/Y12-1 -> 0.21941113 | AA28: =+AA12/Z12-1 -> 0.22167038 | AB28: =+AB12/AA12-1 -> 0.062468278 | AC28: =+AB28*(1-10%) -> 0.05622145 | AD28: =+AC28*(1-10%) -> 0.050599305 | AE28: =+AD28*(1-10%) -> 0.045539375 | AF28: =+AE28*(1-10%) -> 0.040985437 | AG28: =+AF28*(1-10%) -> 0.036886894 | AH28: =+AG28*(1-10%) -> 0.033198204 | AI28: =+AH28*(1-10%) -> 0.029878384 | AJ28: =+AI28*(1-10%) -> 0.026890545 | ... AL28: =+AK28*(1-10%) -> 0.021781342
B29: Gross Margin | C29: =C14/C12 -> 0.78676907 | D29: =D14/D12 -> 0.81421294 | E29: =E14/E12 -> 0.8181339 | F29: =F14/F12 -> 0.80813722 | G29: =G14/G12 -> 0.81785763 | H29: =H14/H12 -> 0.8129559 | I29: =I14/I12 -> 0.81830052 | J29: =J14/J12 -> 0.81734386 | ... P29: =P14/P12 -> 0.81365438 | T29: =+T14/T12 -> 0.83246176 | U29: =+U14/U12 -> 0.81936999 | V29: =+V14/V12 -> 0.80582795 | W29: =+W14/W12 -> 0.80794376 | X29: =+X14/X12 -> 0.78347297 | Y29: =+Y14/Y12 -> 0.80757142 | Z29: =+Z14/Z12 -> 0.81665157 | AA29: =+AA14/AA12 -> 0.81999443
B30: Operating Margin | C30: =C18/C12 -> 0.25229534 | D30: =D18/D12 -> 0.29350917 | E30: =E18/E12 -> 0.40262403 | F30: =F18/F12 -> 0.40845632 | G30: =G18/G12 -> 0.37904266 | H30: =H18/H12 -> 0.38000051 | I30: =I18/I12 -> 0.42745571 | J30: =J18/J12 -> 0.48288761 | ... P30: =P18/P12 -> 0.30879426 | T30: =+T18/T12 -> 0.44616569 | U30: =+U18/U12 -> 0.33927889 | V30: =+V18/V12 -> 0.38005002 | W30: =+W18/W12 -> 0.39645041 | X30: =+X18/X12 -> 0.24821412 | Y30: =+Y18/Y12 -> 0.34655528 | Z30: =+Z18/Z12 -> 0.42176035 | AA30: =+AA18/AA12 -> 0.41437855
B31: Tax Rate | C31: =C21/C20 -> 0.2186944 | D31: =D21/D20 -> 0.16194985 | E31: =E21/E20 -> 0.17382311 | F31: =F21/F20 -> 0.16599238 | G31: =G21/G20 -> 0.1278996 | H31: =H21/H20 -> 0.10863233 | I31: =I21/I20 -> 0.11973965 | J31: =J21/J20 -> 0.11523438 | ... P31: =P21/P20 -> 0.15504372 | T31: =+T21/T20 -> 0.12814952 | U31: =+U21/U20 -> 0.25499758 | V31: =+V21/V20 -> 0.12157926 | W31: =+W21/W20 -> 0.16737163 | X31: =+X21/X20 -> 0.19497554 | Y31: =+Y21/Y20 -> 0.17563465 | Z31: =+Z21/Z20 -> 0.11750138 | AA31: =+AA21/AA20 -> 0.2964437
B33: Cash and Cash Equivalents | T33: 10019 | U33: 19079 | V33: 17576 | W33: 16601 | X33: 14681 | Y33: 41862 | Z33: 43889 | AA33: 35873
B34: Marketable Securities | T34: 31095 | U34: 35776 | V34: 44378 | W34: 31397 | X34: 26057 | Y34: 23541 | Z34: 33926 | AA34: 45719
B35: Accounts receivables | T35: 7587 | U35: 9518 | V35: 11335 | W35: 14039 | X35: 13466 | Y35: 16169 | Z35: 16994 | AA35: 19769
B36: Prepaid expenses and other | T36: 1779 | U36: 1852 | V36: 2381 | W36: 4629 | X36: 5345 | Y36: 3793 | Z36: 5236 | AA36: 7361
B37: Current Assets | T37: =+SUM(T33:T36) -> 50480 | U37: =+SUM(U33:U36) -> 66225 | V37: =+SUM(V33:V36) -> 75670 | W37: =+SUM(W33:W36) -> 66666 | X37: =+SUM(X33:X36) -> 59549 | Y37: =+SUM(Y33:Y36) -> 85365 | Z37: =+SUM(Z33:Z36) -> 100045 | AA37: =+SUM(AA33:AA36) -> 108722
B38: Non-marketable securities | T38: 0 | U38: 0 | V38: 6234 | W38: 6775 | X38: 6201 | Y38: 6141 | Z38: 6070 | AA38: 27524
B39: PP&E | T39: 24683 | U39: 35323 | V39: 45633 | W39: 57809 | X39: 79518 | Y39: 96587 | Z39: 121346 | AA39: 176400
B40: Operating Leases | T40: 0 | U40: 9460 | V40: 9348 | W40: 12155 | X40: 12673 | Y40: 13294 | Z40: 14922 | AA40: 20404
B41: Goodwill | T41: =1294+18301 -> 19595 | U41: =894+18715 -> 19609 | V41: =623+19050 -> 19673 | W41: =634+19197 -> 19831 | X41: =897+20306 -> 21203 | Y41: 20654 | Z41: 20654 | AA41: 24534
B42: Other | T42: 2576 | U42: 2759 | V42: 2758 | W42: 2751 | X42: 6583 | Y42: 7582 | Z42: 13017 | AA42: 8437
B43: Non-current Assets | T43: =+SUM(T38:T42) -> 46854 | U43: =+SUM(U38:U42) -> 67151 | V43: =+SUM(V38:V42) -> 83646 | W43: =+SUM(W38:W42) -> 99321 | X43: =+SUM(X38:X42) -> 126178 | Y43: =+SUM(Y38:Y42) -> 144258 | Z43: =+SUM(Z38:Z42) -> 176009 | AA43: =+SUM(AA38:AA42) -> 257299
B44: Total Assets | T44: =+T37+T43 -> 97334 | U44: =+U37+U43 -> 133376 | V44: =+V37+V43 -> 159316 | W44: =+W37+W43 -> 165987 | X44: =+X37+X43 -> 185727 | Y44: =+Y37+Y43 -> 229623 | Z44: =+Z37+Z43 -> 276054 | AA44: =+AA37+AA43 -> 366021
B45: Accounts payables | T45: =820+541 -> 1361 | U45: =1363+886 -> 2249 | V45: =1331+1093 -> 2424 | W45: =4083+1052 -> 5135 | X45: =4990+1117 -> 6107 | Y45: 4849 | Z45: 7687 | AA45: 8894
B46: Operating Lease Liabilties | T46: 0 | U46: 800 | V46: 1023 | W46: 1127 | X46: 1367 | Y46: 1623 | Z46: 1942 | AA46: 2213
B47: Accrued expenses | T47: =5509+147 -> 5656 | U47: =11735+269 -> 12004 | V47: =11152+382 -> 11534 | W47: 14873 | X47: 19552 | Y47: 25488 | Z47: 23967 | AA47: 30729
B48: Current Liabilities | T48: =+SUM(T45:T47) -> 7017 | U48: =+SUM(U45:U47) -> 15053 | V48: =+SUM(V45:V47) -> 14981 | W48: =+SUM(W45:W47) -> 21135 | X48: =+SUM(X45:X47) -> 27026 | Y48: =+SUM(Y45:Y47) -> 31960 | Z48: =+SUM(Z45:Z47) -> 33596 | AA48: =+SUM(AA45:AA47) -> 41836
B49: Operating Lease Liabilties | T49: 0 | U49: 9524 | V49: 9631 | W49: 12746 | X49: 15301 | Y49: 17226 | Z49: 18292 | AA49: 22940
B50: Debt | T50: 0 | U50: 0 | V50: 0 | W50: 0 | X50: 9923 | Y50: 18385 | Z50: 28826 | AA50: 58744
B51: Tax Payables | T51: 0 | U51: 0 | V51: 0 | W51: 0 | X51: 0 | Y51: 7514 | Z51: 9987 | AA51: 21005
B52: Other | T52: 6190 | U52: 7745 | V52: 6414 | W52: 7227 | X52: 7764 | Y52: 1370 | Z52: 2716 | AA52: 4253
B53: Non-current Liabilties | T53: =+SUM(T49:T52) -> 6190 | U53: =+SUM(U49:U52) -> 17269 | V53: =+SUM(V49:V52) -> 16045 | W53: =+SUM(W49:W52) -> 19973 | X53: =+SUM(X49:X52) -> 32988 | Y53: =+SUM(Y49:Y52) -> 44495 | Z53: =+SUM(Z49:Z52) -> 59821 | AA53: =+SUM(AA49:AA52) -> 106942
B54: Total Liabilities | T54: =+T48+T53 -> 13207 | U54: =+U48+U53 -> 32322 | V54: =+V48+V53 -> 31026 | W54: =+W48+W53 -> 41108 | X54: =+X48+X53 -> 60014 | Y54: =+Y48+Y53 -> 76455 | Z54: =+Z48+Z53 -> 93417 | AA54: =+AA48+AA53 -> 148778
B55: Equity | T55: 84127 | U55: 101054 | V55: 128290 | W55: 124879 | X55: 125713 | Y55: 153168 | Z55: 182637 | AA55: 217243
B56: Liabilities & Equity | T56: =+T54+T55 -> 97334 | U56: =+U54+U55 -> 133376 | V56: =+V54+V55 -> 159316 | W56: =+W54+W55 -> 165987 | X56: =+X54+X55 -> 185727 | Y56: =+Y54+Y55 -> 229623 | Z56: =+Z54+Z55 -> 276054 | AA56: =+AA54+AA55 -> 366021
B58: Net Income | T58: =+T22+1 -> 22112 | U58: =+U22 -> 18485 | V58: =+V22 -> 29146 | W58: =+W22 -> 39370 | X58: =+X22 -> 23200 | Y58: =+Y22 -> 39098 | Z58: =+Z22 -> 62360 | AA58: 60458
B59: D&A | T59: 4315 | U59: 5741 | V59: 6862 | W59: 7967 | X59: 8686 | Y59: 11178 | Z59: 15498 | AA59: 18616
B60: Share-based compensations | T60: 4152 | U60: 4836 | V60: 6536 | W60: 9164 | X60: 11992 | Y60: 14027 | Z60: 16690 | AA60: 20427
B61: Deffered Income Taxes | T61: 286 | U61: -37 | V61: -1192 | W61: 609 | X61: -3286 | Y61: 131 | Z61: -4738 | AA61: 18738
B62: Impairment for facilities consolid. | T62: 0 | U62: 0 | V62: 0 | W62: 0 | X62: 2218 | Y62: 2432 | Z62: 383 | AA62: -1138
B63: Data Center Assets abdondment | T63: 0 | U63: 0 | V63: 0 | W63: 0 | X63: 1341 | Y63: -224 | Z63: 0 | AA63: 0
B64: Other | T64: -64 | U64: 39 | V64: =33+85 -> 118 | W64: =105-232 -> -127 | X64: 641 | Y64: 635 | Z64: 87 | AA64: -416
B65: Change in AR | T65: -1892 | U65: -1961 | V65: -1512 | W65: -3110 | X65: 231 | Y65: -2399 | Z65: -1485 | AA65: -1815
B66: Change in Prepaid Expenses | T66: -690 | U66: 47 | V66: 135 | W66: -1750 | X66: 162 | Y66: 559 | Z66: -698 | AA66: -89
B67: Cahnge in other Assets | T67: -159 | U67: 41 | V67: -34 | W67: -349 | X67: -106 | Y67: -80 | Z67: -270 | AA67: -481
B68: Changes in AP | T68: =221+157 -> 378 | U68: =113+348 -> 461 | V68: =-17+178 -> 161 | W68: =1436-12 -> 1424 | X68: 210 | Y68: 51 | Z68: 373 | AA68: -14
B69: Change in accrued Expenses | T69: =1417+53 -> 1470 | U69: =7300+123 -> 7423 | V69: -946 | W69: 3544 | X69: 4300 | Y69: 5081 | Z69: 323 | AA69: 1077
B70: Change in other Liabilities | T70: -634 | U70: 1239 | V70: -527 | W70: 941 | X70: 886 | Y70: 624 | Z70: 2805 | AA70: 437
B71: Change in WC | T71: =+SUM(T65:T70) -> -1527 | U71: =+SUM(U65:U70) -> 7250 | V71: =+SUM(V65:V70) -> -2723 | W71: =+SUM(W65:W70) -> 700 | X71: =+SUM(X65:X70) -> 5683 | Y71: =+SUM(Y65:Y70) -> 3836 | Z71: =+SUM(Z65:Z70) -> 1048 | AA71: =+SUM(AA65:AA70) -> -885
B72: CFFO | T72: =+T58+SUM(T59:T64)+T71 -> 29274 | U72: =+U58+SUM(U59:U64)+U71 -> 36314 | V72: =+V58+SUM(V59:V64)+V71 -> 38747 | W72: =+W58+SUM(W59:W64)+W71 -> 57683 | X72: =+X58+SUM(X59:X64)+X71 -> 50475 | Y72: =+Y58+SUM(Y59:Y64)+Y71 -> 71113 | Z72: =+Z58+SUM(Z59:Z64)+Z71 -> 91328 | AA72: =+AA58+SUM(AA59:AA64)+AA71 -> 115800
B73: CapEx | T73: -13915 | U73: -15102 | V73: =-15163+48 -> -15115 | W73: =-18690+123 -> -18567 | X73: -31186 | Y73: -27045 | Z73: -37256 | AA73: -69691
B74: Purchase of MS | T74: -14656 | U74: -23910 | V74: -33930 | W74: -30407 | X74: -9626 | Y74: -2982 | Z74: -25542 | AA74: -36929
B75: Sale of MS | T75: =12358+4772 -> 17130 | U75: =9565+10152 -> 19717 | V75: =11787+13984 -> 25771 | W75: =31671+10915 -> 42586 | X75: 13158 | Y75: 6184 | Z75: 15789 | AA75: 26874
B76: Acquisiton of Intangibles | T76: -137 | U76: -508 | V76: =-6361-388 -> -6749 | W76: =-47-851 -> -898 | X76: -1312 | Y76: -629 | Z76: -270 | AA76: -4231
B77: Other | T77: -25 | U77: -61 | V77: -36 | W77: -284 | X77: -4 | Y77: -23 | Z77: 129 | AA77: =-2432+2554-18330+182 -> -18026
B78: CFFI | T78: =+SUM(T73:T77) -> -11603 | U78: =+SUM(U73:U77) -> -19864 | V78: =+SUM(V73:V77) -> -30059 | W78: =+SUM(W73:W77) -> -7570 | X78: =+SUM(X73:X77) -> -28970 | Y78: =+SUM(Y73:Y77) -> -24495 | Z78: =+SUM(Z73:Z77) -> -47150 | AA78: =+SUM(AA73:AA77) -> -102003
B79: Taxes paid settlement of equity awards | T79: -3208 | U79: -2337 | V79: -3564 | W79: -5515 | X79: -3595 | Y79: -7012 | Z79: -13770 | AA79: -18400
B80: Stock Buybacks | T80: -12879 | U80: -4202 | V80: -6272 | W80: =-44537 -> -44537 | X80: -27956 | Y80: -19774 | Z80: -30125 | AA80: -26248
B81: Dividends | T81: 0 | U81: 0 | V81: 0 | W81: 0 | X81: 0 | Y81: 0 | Z81: -5072 | AA81: -5324
B82: Issuance of Debt | T82: 0 | U82: 0 | V82: 0 | W82: 0 | X82: 9921 | Y82: 8455 | Z82: 10432 | AA82: 29906
B83: Lease Payments | T83: 0 | U83: -552 | V83: -604 | W83: -677 | X83: -850 | Y83: -1058 | Z83: -1969 | AA83: -2524
B84: Other | T84: =500+15 -> 515 | U84: =-223+15 -> -208 | V84: 148 | W84: 1 | X84: 344 | Y84: -111 | Z84: -277 | AA84: 2220
B85: CFFF | T85: =+SUM(T79:T84) -> -15572 | U85: =+SUM(U79:U84) -> -7299 | V85: =+SUM(V79:V84) -> -10292 | W85: =+SUM(W79:W84) -> -50728 | X85: =+SUM(X79:X84) -> -22136 | Y85: =+SUM(Y79:Y84) -> -19500 | Z85: =+SUM(Z79:Z84) -> -40781 | AA85: =+SUM(AA79:AA84) -> -20370
B86: FX Effect | T86: -179 | U86: 4 | V86: 279 | W86: -474 | X86: -638 | Y86: 113 | Z86: -786 | AA86: 235
B87: Change in Cash | T87: =+T85+T86+T78+T72 -> 1920 | U87: =+U85+U86+U78+U72 -> 9155 | V87: =+V85+V86+V78+V72 -> -1325 | W87: =+W85+W86+W78+W72 -> -1089 | X87: =+X85+X86+X78+X72 -> -1269 | Y87: =+Y85+Y86+Y78+Y72 -> 27231 | Z87: =+Z85+Z86+Z78+Z72 -> 2611 | AA87: =+AA85+AA86+AA78+AA72 -> -6338
B88: Cash BoP | T88: =+T89-T87 -> 8204 | U88: =+U89-U87 -> 10124 | V88: =+V89-V87 -> 19279 | W88: =+W89-W87 -> 17954 | X88: =+X89-X87 -> 16865 | Y88: =+Y89-Y87 -> 15596 | Z88: 42827 | AA88: 42827
B89: Cash EoP | T89: =+U88 -> 10124 | U89: =+V88 -> 19279 | V89: =+W88 -> 17954 | W89: =+X88 -> 16865 | X89: =+Y88 -> 15596 | Y89: =+Z88 -> 42827 | Z89: =+Z87+Z88 -> 45438 | AA89: =+AA87+AA88 -> 36489

Sheet KPIs
A1: Main
B2: Ratios | C2: 18 | D2: =+C2+1 -> 19 | E2: =+D2+1 -> 20 | F2: =+E2+1 -> 21 | G2: =+F2+1 -> 22 | H2: =+G2+1 -> 23 | I2: =+H2+1 -> 24 | J2: =+I2+1 -> 25
B3: Price | C3: 135.04 | D3: 208.8 | E3: 267.68 | F3: 336.95 | G3: 124.15 | H3: 346.29 | I3: 598.71 | J3: 694
B4: Shares o/s | C4: =+Model!T25 -> 2890 | D4: =+Model!U25 -> 2854 | E4: =+Model!V25 -> 2851 | F4: =+Model!W25 -> 2815 | G4: =+Model!X25 -> 2687 | H4: =+Model!Y25 -> 2574 | I4: =+Model!Z25 -> 2534 | J4: =+Model!AA25 -> 2521
B5: Market Cap | C5: =+C3*C4 -> 390265.6 | D5: =+D3*D4 -> 595915.2 | E5: =+E3*E4 -> 763155.68 | F5: =+F3*F4 -> 948514.25 | G5: =+G3*G4 -> 333591.05 | H5: =+H3*H4 -> 891350.46 | I5: =+I3*I4 -> 1517131.1 | J5: =+J3*J4 -> 1749574
B6: Net Debt | C6: =+Model!T33+Model!T34-Model!T50 -> 41114 | D6: =+Model!U33+Model!U34-Model!U50 -> 54855 | E6: =+Model!V33+Model!V34-Model!V50 -> 61954 | F6: =+Model!W33+Model!W34-Model!W50 -> 47998 | G6: =+Model!X33+Model!X34-Model!X50 -> 30815 | H6: =+Model!Y33+Model!Y34-Model!Y50 -> 47018 | I6: =+Model!Z33+Model!Z34-Model!Z50 -> 48989 | J6: =+Model!AA33+Model!AA34-Model!AA50 -> 22848
B7: EV | C7: =+C5-C6 -> 349151.6 | D7: =+D5-D6 -> 541060.2 | E7: =+E5-E6 -> 701201.68 | F7: =+F5-F6 -> 900516.25 | G7: =+G5-G6 -> 302776.05 | H7: =+H5-H6 -> 844332.46 | I7: =+I5-I6 -> 1468142.1 | J7: =+J5-J6 -> 1726726
B9: Value Driver
B10: Capital Emloyed | C10: =+Model!T43+SUM(Model!T35:T36)-Model!T45 -> 54859 | D10: =+Model!U43+SUM(Model!U35:U36)-Model!U45 -> 76272 | E10: =+Model!V43+SUM(Model!V35:V36)-Model!V45 -> 94938 | F10: =+Model!W43+SUM(Model!W35:W36)-Model!W45 -> 112854 | G10: =+Model!X43+SUM(Model!X35:X36)-Model!X45 -> 138882 | H10: =+Model!Y43+SUM(Model!Y35:Y36)-Model!Y45 -> 159371 | I10: =+Model!Z43+SUM(Model!Z35:Z36)-Model!Z45 -> 190552 | J10: =+Model!AA43+SUM(Model!AA35:AA36)-Model!AA45 -> 275535 | L10: =Long Term Assets + Working Capital (Exclusive of cash)-Accounts Payables
B11: Invested Capital (exl. Intangibles) | C11: =+Model!T39+SUM(Model!T35:T36)-SUM(Model!T45,L47)-Model!T46+Model!T40-Model!T49 -> 32688 | D11: =+Model!U39+SUM(Model!U35:U36)-SUM(Model!U45,M47)-Model!U46+Model!U40-Model!U49 -> 43580 | E11: =+Model!V39+SUM(Model!V35:V36)-SUM(Model!V45,N47)-Model!V46+Model!V40-Model!V49 -> 55619 | F11: =+Model!W39+SUM(Model!W35:W36)-SUM(Model!W45,O47)-Model!W46+Model!W40-Model!W49 -> 69624 | G11: =+Model!X39+SUM(Model!X35:X36)-SUM(Model!X45,P47)-Model!X46+Model!X40-Model!X49 -> 88227 | H11: =+Model!Y39+SUM(Model!Y35:Y36)-SUM(Model!Y45,Q47)-Model!Y46+Model!Y40-Model!Y49 -> 106145 | I11: =+Model!Z39+SUM(Model!Z35:Z36)-SUM(Model!Z45,R47)-Model!Z46+Model!Z40-Model!Z49 -> 130577 | J11: =+Model!AA39+SUM(Model!AA35:AA36)-SUM(Model!AA45,S47)-Model!AA46+Model!AA40-Model!AA49 -> 189887 | L11: =Net Working Capital + PP&E + Other Net Operating Assets (net of Liabilties) + (Intangibles)
B12: Invested Capital (incl. Intangibles) | C12: =+C11+Model!T41 -> 52283 | D12: =+D11+Model!U41 -> 63189 | E12: =+E11+Model!V41 -> 75292 | F12: =+F11+Model!W41 -> 89455 | G12: =+G11+Model!X41 -> 109430 | H12: =+H11+Model!Y41 -> 126799 | I12: =+I11+Model!Z41 -> 151231 | J12: =+J11+Model!AA41 -> 214421
B13: Total Funds Invested | C13: =+C12+Model!T33+Model!T34+Model!T38 -> 93397 | D13: =+D12+Model!U33+Model!U34+Model!U38 -> 118044 | E13: =+E12+Model!V33+Model!V34+Model!V38 -> 143480 | F13: =+F12+Model!W33+Model!W34+Model!W38 -> 144228 | G13: =+G12+Model!X33+Model!X34+Model!X38 -> 156369 | H13: =+H12+Model!Y33+Model!Y34+Model!Y38 -> 198343 | I13: =+I12+Model!Z33+Model!Z34+Model!Z38 -> 235116 | J13: =+J12+Model!AA33+Model!AA34+Model!AA38 -> 323537 | L13: Invested Capital + Non-Operating Assets
B14: NOPAT | C14: =+Model!T18*(1-Model!T31) -> 21720.411 | D14: =+Model!U18*(1-Model!U31) -> 17869.628 | E14: =+Model!V18*(1-Model!V31) -> 28698.884 | F14: =+Model!W18*(1-Model!W31) -> 38927.874 | G14: =+Model!X18*(1-Model!X31) -> 23300.628 | H14: =+Model!Y18*(1-Model!Y31) -> 38539.905 | I14: =+Model!Z18*(1-Model!Z31) -> 61227.754 | J14: =+Model!AA18*(1-Model!AA31) -> 58589.354 | L14: EBITA * (1-Marginal Tax Rate)
B15: Net Investment | D15: =+D12-C12 -> 10906 | E15: =+E12-D12 -> 12103 | F15: =+F12-E12 -> 14163 | G15: =+G12-F12 -> 19975 | H15: =+H12-G12 -> 17369 | I15: =+I12-H12 -> 24432 | J15: =+J12-I12 -> 63190 | L15: =Invested Capital (t+1)-Invested Capital (t)
B16: FCF | D16: =+D14-D15+Model!U59+Model!U60 -> 17540.628 | E16: =+E14-E15+Model!V59+Model!V60 -> 29993.884 | F16: =+F14-F15+Model!W59+Model!W60 -> 41895.874 | G16: =+G14-G15+Model!X59+Model!X60 -> 24003.628 | H16: =+H14-H15+Model!Y59+Model!Y60 -> 46375.905 | I16: =+I14-I15+Model!Z59+Model!Z60 -> 68983.754 | J16: =+J14-J15+Model!AA59+Model!AA60 -> 34442.354 | L16: =NOPAT + non-cash Expenses - Investments in Invested Capital
B17: Investment Rate | D17: =+D15/D14 -> 0.61030929 | E17: =+E15/E14 -> 0.42172372 | F17: =+F15/F14 -> 0.3638267 | G17: =+G15/G14 -> 0.85727303 | H17: =+H15/H14 -> 0.45067574 | I17: =+I15/I14 -> 0.39903472 | J17: =+J15/J14 -> 1.0785236 | L17: =Net Investment/NOPAT
B18: Economic Profit | C18: =+C12*(C24-DCF!$E$18) -> 16492.111 | D18: =+D12*(D24-DCF!$E$18) -> 11550.728 | E18: =+E12*(E24-DCF!$E$18) -> 21169.684 | F18: =+F12*(F24-DCF!$E$18) -> 29982.374 | G18: =+G12*(G24-DCF!$E$18) -> 12357.628 | H18: =+H12*(H24-DCF!$E$18) -> 25860.005 | I18: =+I12*(I24-DCF!$E$18) -> 46104.654 | J18: =+J12*(J24-DCF!$E$18) -> 37147.254 | L18: =Invested Capital *(ROIC-WACC)
B20: Efficency-Ratios
B21: Capital Turnover | C21: =+Model!T12/Model!T55 -> 0.66373459 | D21: =+Model!U12/Model!U55 -> 0.69959626 | E21: =+Model!V12/Model!V55 -> 0.6700834 | F21: =+Model!W12/Model!W55 -> 0.94434613 | G21: =+Model!X12/Model!X55 -> 0.92758108 | H21: =+Model!Y12/Model!Y55 -> 0.88074533 | I21: =+Model!Z12/Model!Z55 -> 0.9006992 | J21: =+Model!AA12/Model!AA55 -> 0.92507469 | L21: =Revenue/Equity
B22: Return on Equity (ROE) | C22: =+Model!T22/Model!T55 -> 0.26282882 | D22: =+Model!U22/Model!U55 -> 0.182922 | E22: =+Model!V22/Model!V55 -> 0.2271884 | F22: =+Model!W22/Model!W55 -> 0.31526518 | G22: =+Model!X22/Model!X55 -> 0.18454734 | H22: =+Model!Y22/Model!Y55 -> 0.2552622 | I22: =+Model!Z22/Model!Z55 -> 0.34144231 | J22: =+Model!AA22/Model!AA55 -> 0.27829665 | L22: =Net Income/Book Value of Equity
B23: Return on Capital Employed (ROCE) | C23: =+Model!T18/KPIs!C10 -> 0.45412786 | D23: =+Model!U18/KPIs!D10 -> 0.31447976 | E23: =+Model!V18/KPIs!E10 -> 0.34412985 | F23: =+Model!W18/KPIs!F10 -> 0.41427863 | G23: =+Model!X18/KPIs!G10 -> 0.20840714 | H23: =+Model!Y18/KPIs!H10 -> 0.29334697 | I23: =+Model!Z18/KPIs!I10 -> 0.36410009 | J23: =+Model!AA18/KPIs!J10 -> 0.30223384 | L23: =EBIT/Capital Employed
B24: Return on Capital Invested (ROIC) | C24: =+C14/C12 -> 0.41543926 | D24: =+D14/D12 -> 0.2827965 | E24: =+E14/E12 -> 0.38116777 | F24: =+F14/F12 -> 0.43516712 | G24: =+G14/G12 -> 0.21292724 | H24: =+H14/H12 -> 0.30394486 | I24: =+I14/I12 -> 0.40486246 | J24: =+J14/J12 -> 0.27324448 | L24: =NOPAT/Invested Capital
B25: ROIC without Intangibles | C25: =+C14/C11 -> 0.6644766 | D25: =+D14/D11 -> 0.41004195 | E25: =+E14/E11 -> 0.51599065 | F25: =+F14/F11 -> 0.55911574 | G25: =+G14/G11 -> 0.26409861 | H25: =+H14/H11 -> 0.36308733 | I25: =+I14/I11 -> 0.46890152 | J25: =+J14/J11 -> 0.30854853 | L25: =NOPAT/(Invested Capital exclusive of Intangibles)
B26: Decomposed ROIC | L26: = ROIC = (1-operating cash tax)* (EBITA/Revenues) * (Revenue/Invested Capital)
B28: Retention Rate | C28: =1-(-Model!T80+Model!T81)/Model!T22 -> 0.41752974 | D28: =1-(-Model!U80+Model!U81)/Model!U22 -> 0.77268055 | E28: =1-(-Model!V80+Model!V81)/Model!V22 -> 0.78480752 | F28: =1-(-Model!W80+Model!W81)/Model!W22 -> -0.13124206 | G28: =1-(-Model!X80+Model!X81)/Model!X22 -> -0.205 | H28: =1-(-Model!Y80+Model!Y81)/Model!Y22 -> 0.49424523 | I28: =1-(-Model!Z80+Model!Z81)/Model!Z22 -> 0.59825208 | J28: =1-(-Model!AA80+Model!AA81)/Model!AA22 -> 0.6539085 | L28: =1 - Dividends/Net Income
B29: Reinvestment Rate | C29: =-(Model!T73+Model!T70)/KPIs!C14 -> 0.66983079 | D29: =-(Model!U73+Model!U70)/KPIs!D14 -> 0.7757856 | E29: =-(Model!V73+Model!V70)/KPIs!E14 -> 0.54503862 | F29: =-(Model!W73+Model!W70)/KPIs!F14 -> 0.45278609 | G29: =-(Model!X73+Model!X70)/KPIs!G14 -> 1.3003941 | H29: =-(Model!Y73+Model!Y70)/KPIs!H14 -> 0.68554918 | I29: =-(Model!Z73+Model!Z70)/KPIs!I14 -> 0.56266967 | J29: =-(Model!AA73+Model!AA70)/KPIs!J14 -> 1.1820236 | L29: =Net CapEx + Change in WC / EBIT * (1-t)
B30: Epected Growth in Net Income | C30: =+C28*C22 -> 0.10973885 | D30: =+D28*D22 -> 0.14134027 | E30: =+E28*E22 -> 0.17829917 | F30: =+F28*F22 -> -0.041376052 | G30: =+G28*G22 -> -0.037832205 | H30: =+H28*H22 -> 0.12616212 | I30: =+I28*I22 -> 0.20426858 | J30: =+J28*J22 -> 0.18198055 | L30: =ROE * Retention Rate
B31: Expected Growth in NOPAT | C31: =+C29*C24 -> 0.27827401 | D31: =+D29*D24 -> 0.21938945 | E31: =+E29*E24 -> 0.20775116 | F31: =+F29*F24 -> 0.19703762 | G31: =+G29*G24 -> 0.27688934 | H31: =+H29*H24 -> 0.20836915 | I31: =+I29*I24 -> 0.22780382 | J31: =+J29*J24 -> 0.32298142 | L31: =ROIC * Reinvestment Rate
B33: Finacial Stability Ratios
B34: Equity/Debt Ratio | L34: =Book Value of Equtiy/Book Value of Debt
B35: Gearing | L35: =(Debt - Cash (Net Debt))/Book Value of Equity
B36: Interest Coverage Ratio | L36: =EBIT/Interest Expenses
B37: Net Debt / EBITDA | L37: =Net Debt/EBITDA
B38: Cash Burn Rate | L38: =Book Value of Equity/Absolute value of Loss
B40: WC-Managment Ratios
B41: Debitor-Duration | C41: =+Model!T35/Model!T12*360 -> 48.915076 | D41: =+Model!U35/Model!U12*360 -> 48.46712 | E41: =+Model!V35/Model!V12*360 -> 47.468156 | F41: =+Model!W35/Model!W12*360 -> 42.856634 | G41: =+Model!X35/Model!X12*360 -> 41.572777 | H41: =+Model!Y35/Model!Y12*360 -> 43.148656 | I41: =+Model!Z35/Model!Z12*360 -> 37.190291 | J41: =+Model!AA35/Model!AA12*360 -> 35.413154 | L41: =Accounts Receivables/Revenue*360
B42: Creditor-Duration | C42: =+Model!T45/Model!T12*360 -> 8.7746696 | D42: =+Model!U45/Model!U12*360 -> 11.452254 | E42: =+Model!V45/Model!V12*360 -> 10.151108 | F42: =+Model!W45/Model!W12*360 -> 15.675534 | G42: =+Model!X45/Model!X12*360 -> 18.853776 | H42: =+Model!Y45/Model!Y12*360 -> 12.94006 | I42: =+Model!Z45/Model!Z12*360 -> 16.822512 | J42: =+Model!AA45/Model!AA12*360 -> 15.932247 | L42: =Accounts Payable/Revenue*360
B43: Inventory Intensity | C43: n.a. | D43: n.a. | E43: n.a. | F43: n.a. | G43: n.a. | H43: n.a. | I43: n.a. | J43: n.a. | L43: =Inventory/Balance Sheet Total
B44: Invetory Turnover | C44: n.a. | D44: n.a. | E44: n.a. | F44: n.a. | G44: n.a. | H44: n.a. | I44: n.a. | J44: n.a. | L44: =Cogs/Inventory
B45: Storage-Duration | C45: n.a. | D45: n.a. | E45: n.a. | F45: n.a. | G45: n.a. | H45: n.a. | I45: n.a. | J45: n.a. | L45: =360/Inventory Turnover
B46: Cash Conversion Cycle | C46: =+C41-C42 -> 40.140406 | D46: =+D41-D42 -> 37.014866 | E46: =+E41-E42 -> 37.317048 | F46: =+F41-F42 -> 27.1811 | G46: =+G41-G42 -> 22.719001 | H46: =+H41-H42 -> 30.208596 | I46: =+I41-I42 -> 20.367779 | J46: =+J41-J42 -> 19.480907 | L46: =Debitor Duration + Storage Duration - Creditor Duration
B48: Multipliers
B49: Equitymultiples
B50: P/E Ratio | C50: =+C5/Model!T22 -> 17.650292 | D50: =+D5/Model!U22 -> 32.237771 | E50: =+E5/Model!V22 -> 26.183891 | F50: =+F5/Model!W22 -> 24.09231 | G50: =+G5/Model!X22 -> 14.378925 | H50: =+H5/Model!Y22 -> 22.797853 | I50: =+I5/Model!Z22 -> 24.328594 | J50: =+J5/Model!AA22 -> 28.938668 | L50: =Share Price/EPS
B51: PEG Ratio | D51: =+D50/((Model!U22/Model!T22-1)*100) -> -1.9658283 | E51: =+E50/((Model!V22/Model!U22-1)*100) -> 0.45399983 | F51: =+F50/((Model!W22/Model!V22-1)*100) -> 0.68680993 | G51: =+G50/((Model!X22/Model!W22-1)*100) -> -0.35009169 | H51: =+H50/((Model!Y22/Model!X22-1)*100) -> 0.33268977 | I51: =+I50/((Model!Z22/Model!Y22-1)*100) -> 0.40890696 | J51: =+J50/((Model!AA22/Model!Z22-1)*100) -> -9.4879882 | L51: =P/E Ratio / Growth
B52: P/B Ratio | C52: =+C5/Model!T44 -> 4.0095506 | D52: =+D5/Model!U44 -> 4.4679343 | E52: =+E5/Model!V44 -> 4.7902011 | F52: =+F5/Model!W44 -> 5.7143888 | G52: =+G5/Model!X44 -> 1.7961365 | H52: =+H5/Model!Y44 -> 3.8817996 | I52: =+I5/Model!Z44 -> 5.4957767 | J52: =+J5/Model!AA44 -> 4.7799826 | L52: =Market Cap/Book Vakue of Equity
B53: P/TB Ratio | L53: =Market Cap / Tangible Book Value
B54: P/Cf Ratio | C54: =+C5/C16 -> #DIV/0! | D54: =+D5/D16 -> 33.973424 | E54: =+E5/E16 -> 25.44371 | F54: =+F5/F16 -> 22.639801 | G54: =+G5/G16 -> 13.897526 | H54: =+H5/H16 -> 19.22012 | I54: =+I5/I16 -> 21.992586 | J54: =+J5/J16 -> 50.797166 | L54: =Share Price/Cashflow per share
B55: P/R Ratio | C55: =+C5/Model!T12 -> 6.9892475 | D55: =+D5/Model!U12 -> 8.4291441 | E55: =+E5/Model!V12 -> 8.8775162 | F55: =+F5/Model!W12 -> 8.0430958 | G55: =+G5/Model!X12 -> 2.8607659 | H55: =+H5/Model!Y12 -> 6.6073925 | I55: =+I5/Model!Z12 -> 9.2226256 | J55: =+J5/Model!AA12 -> 8.7058209 | L55: =Share Price/Revenue per Share
B56: Entitymultiples
B57: EV/EBITDA | C57: =+C7/(Model!T18+Model!T59) -> 11.945792 | D57: =+D7/(Model!U18+Model!U59) -> 18.200969 | E57: =+E7/(Model!V18+Model!V59) -> 17.737123 | F57: =+F7/(Model!W18+Model!W59) -> 16.456803 | G57: =+G7/(Model!X18+Model!X59) -> 8.0461347 | H57: =+H7/(Model!Y18+Model!Y59) -> 14.575298 | I57: =+I7/(Model!Z18+Model!Z59) -> 17.297087 | J57: =+J7/(Model!AA18+Model!AA59) -> 16.94663 | L57: =EV/EBITDA
B58: EV/EBIT | C58: =+C7/Model!T18 -> 14.014836 | D58: =+D7/Model!U18 -> 22.557333 | E58: =+E7/Model!V18 -> 21.46251 | F58: =+F7/Model!W18 -> 19.261144 | G58: =+G7/Model!X18 -> 10.460754 | H58: =+H7/Model!Y18 -> 18.060201 | I58: =+I7/Model!Z18 -> 21.160884 | J58: =+J7/Model!AA18 -> 20.734978 | L58: =EV/EBIT
B59: EV/FCF | D59: =+D7/D16 -> 30.846113 | E59: =+E7/E16 -> 23.378155 | F59: =+F7/F16 -> 21.494151 | G59: =+G7/G16 -> 12.613762 | H59: =+H7/H16 -> 18.206275 | I59: =+I7/I16 -> 21.282433 | J59: =+J7/J16 -> 50.133797 | L59: =EV/FCF
B60: EV/Sales | C60: =+C7/Model!T12 -> 6.2529389 | D60: =+D7/Model!U12 -> 7.6532272 | E60: =+E7/Model!V12 -> 8.1568275 | F60: =+F7/Model!W12 -> 7.6360882 | G60: =+G7/Model!X12 -> 2.5965067 | H60: =+H7/Model!Y12 -> 6.258858 | I60: =+I7/Model!Z12 -> 8.924822 | J60: =+J7/Model!AA12 -> 8.59213 | L60: =EV/Revenue

Sheet Coc
A1: Main
B3: Cost of Capital
A4: x | B4: Cost of Equity (CAPM)
B5: Riskfree Rate
B6: Expected Inflation | H6: =(1+Nominal Rate)/(1+Real Rate)-1
B7: Average Real Interest Rate | H7: = Average Interest Rate of the Past
B8: Riskfree Rate | F8: =F6+F7 -> 0 | H8: =Goverment Bond or Expected Inflation + Average Real Interest Rate
A10: x | B10: Adjustments for Industry/Company Risk
B11: Raw Beta | H11: =Raw beta slope of regression line aginst total market -> Ri= alpha + beta*Rm + standard error
B12: Debt to Value Ratio | H12: Value of Debt/Enterpries Value
B13: Unlevered Beta | H13: = Raw Beta* Debt-to-Equity Ratio (Book Value)
B14: Unlevered Industry Beta | H14: =Median of Peer Group
B15: Levered Industry Beta | H15: =Unlevered Industry Beta * Market Value of Debt to Market Value of Equity
A17: x | B17: Expected Equity Risk Premium
B18: Estimated Future Market Return | H18: = 1/P/E * (1.g/ROE) + g , g = real growth in GDP, P/E => P/E ratio for S&P500 or MSCI World Index, ROE = Average ROE in S&P500 or MSCI World
B19: Riskfree Rate
B20: Expected Equity Risk Premium | F20: =F18-F19 -> 0
A22: x | B22: Cost of Equity (CAPM) | F22: =F8+F15*F20 -> 0 | H22: => ER(i)=rf+beta(i)*(Er(m)-rf)
A25: x | B25: Cost of Debt
B26: Yield to Maturity on Trading Bonds | H26: => Price = Coupon/(1+YTM)+Coupon(1+YTM)^2 + … + (Face Value + Coupon)/(1+YTM)^n => solve for YTM
B27: or
B28: Riskfree Rate
B29: Credit Default Spread
B30: Country Rsik Premium
A32: x | B32: Cost of Debt | F32: =F28+F29+F30 -> 0
A34: x | B34: Capital Structure
B35: Market Value of Debt
B36: Market Value of Equity
B37: Total Enterprise Value | F37: =F35+F36 -> 0
B39: Marginal Tax Rate
A41: x | B41: WACC | F41: =(F32*(F35/F37)*(1-F39))+((F36/F38)*F22) -> #DIV/0! | H41: => WACC = (D/D+E)*kd * (1-t) + (E/D+E) * ke
I47: =SLOPE(H48:H52,K48:K52) -> #DIV/0!
H48: Change

Sheet DCF
A1: Main | B1: META DCF
B3: Ticker | E3: META | G3: Share Price | J3: =+Main!I2 -> 535 | L3: Share Price | O3: =+J3 -> 535
B4: Date | E4: =+TODAY() -> 46233 | G4: Fair Share Price | J4: =V62 -> 408.82167 | L4: Scneario DCF Price | O4: =+J15+O15+T15 -> 0
B5: End of FY | E5: 46022 | G5: Implied Upside | J5: =J4/J3-1 -> -0.23584735 | L5: Implied Upside | O5: =O4/O3-1 -> -1
A7: x | B7: Assumptions
B9: Switches | G9: Conservative Case | L9: Base Case | Q9: Optimistic Case
B10: Assuptions | G10: Assuptions | I10: Year | J10: Metic | L10: Assuptions | N10: Year | O10: Metic | Q10: Assuptions | S10: Year | T10: Metic
B11: Revenue | E11: 2 | G11: Revenue | L11: Revenue | Q11: Revenue
B12: EBIT | E12: 2 | G12: EBIT | L12: EBIT | Q12: EBIT
B13: WACC | E13: 2 | G13: Implied Share Price
B14: TGR | E14: 2 | G14: Probability | L14: Probability | Q14: Probability
B15: ROIC | E15: 2 | G15: Implied Share Price * p | L15: Implied Share Price * p | Q15: Implied Share Price * p
B17: Valuation
B18: WACC | E18: =CHOOSE(E13,J18,O18,T18) -> 0.1 | G18: WACC | L18: WACC | O18: 0.1 | Q18: WACC
B19: TGR | E19: =CHOOSE(E14,J19,O19,T19) -> 0.03 | G19: TGR | L19: TGR | O19: 0.03 | Q19: TGR
B20: RONIC | E20: =CHOOSE(E15,J20,O20,T20) -> 0.15 | G20: RONIC | L20: RONIC | O20: 0.15 | Q20: RONIC
A24: x | B24: Model | F24: 18 | G24: 19 | H24: =G24+1 -> 20 | I24: =H24+1 -> 21 | J24: =I24+1 -> 22 | K24: =J24+1 -> 23 | L24: =K24+1 -> 24 | M24: =L24+1 -> 25 | N24: =M24+1 -> 26 | O24: =N24+1 -> 27 | ... V24: =U24+1 -> 34
B25: Revenue | F25: =+Model!T12 -> 55838 | G25: =+Model!U12 -> 70697 | H25: =+Model!V12 -> 85965 | I25: =+Model!W12 -> 117929 | J25: =+Model!X12 -> 116609 | K25: =+Model!Y12 -> 134902 | L25: =+Model!Z12 -> 164501 | M25: =L25*(1+M26) -> 200966 | N25: =M25*(1+N26) -> 213520 | O25: =N25*(1+O26) -> 225524.4 | P25: =O25*(1+P26) -> 236935.78 | Q25: =P25*(1+Q26) -> 247725.69 | R25: =Q25*(1+R26) -> 257878.84 | S25: =R25*(1+S26) -> 267391.18 | T25: =S25*(1+T26) -> 276268.09 | ... V25: =U25*(1+V26) -> 292173.5
B26: Growth (%) | G26: =G25/F25-1 -> 0.2661091 | H26: =H25/G25-1 -> 0.2159639 | I26: =I25/H25-1 -> 0.37182574 | J26: =J25/I25-1 -> -0.011193176 | K26: =K25/J25-1 -> 0.15687468 | L26: =L25/K25-1 -> 0.21941113 | M26: {=OFFSET(M26,$E$11,,)} -> 0.22167038 | N26: {=OFFSET(N26,$E$11,,)} -> 0.062468278 | O26: {=OFFSET(O26,$E$11,,)} -> 0.05622145 | P26: {=OFFSET(P26,$E$11,,)} -> 0.050599305 | Q26: {=OFFSET(Q26,$E$11,,)} -> 0.045539375 | R26: {=OFFSET(R26,$E$11,,)} -> 0.040985437 | S26: {=OFFSET(S26,$E$11,,)} -> 0.036886894 | T26: {=OFFSET(T26,$E$11,,)} -> 0.033198204 | ... V26: {=OFFSET(V26,$E$11,,)} -> 0.026890545
B27: Conservative Case
B28: Base Case | M28: =+Model!AA28 -> 0.22167038 | N28: =+Model!AB28 -> 0.062468278 | O28: =+Model!AC28 -> 0.05622145 | P28: =+Model!AD28 -> 0.050599305 | Q28: =+Model!AE28 -> 0.045539375 | R28: =+Model!AF28 -> 0.040985437 | S28: =+Model!AG28 -> 0.036886894 | T28: =+Model!AH28 -> 0.033198204 | ... V28: =+Model!AJ28 -> 0.026890545
B29: Optimisitic Case
B31: EBIT | F31: =+Model!T18 -> 24913 | G31: =+Model!U18 -> 23986 | H31: =+Model!V18 -> 32671 | I31: =+Model!W18 -> 46753 | J31: =+Model!X18 -> 28944 | K31: =+Model!Y18 -> 46751 | L31: =+Model!Z18 -> 69380 | M31: =M32*M25 -> 84405.72 | N31: =N32*N25 -> 90746 | O31: =O32*O25 -> 96975.494 | P31: =P32*P25 -> 104251.74 | Q31: =Q32*Q25 -> 111476.56 | R31: =R32*R25 -> 116045.48 | S31: =S32*S25 -> 120326.03 | T31: =T32*T25 -> 124320.64 | ... V31: =V32*V25 -> 131478.08
B32: % of Sales | F32: =F31/F25 -> 0.44616569 | G32: =G31/G25 -> 0.33927889 | H32: =H31/H25 -> 0.38005002 | I32: =I31/I25 -> 0.39645041 | J32: =J31/J25 -> 0.24821412 | K32: =K31/K25 -> 0.34655528 | L32: =L31/L25 -> 0.42176035 | M32: {=OFFSET(M32,$E$12,,)} -> 0.42 | N32: {=OFFSET(N32,$E$12,,)} -> 0.425 | O32: {=OFFSET(O32,$E$12,,)} -> 0.43 | P32: {=OFFSET(P32,$E$12,,)} -> 0.44 | Q32: {=OFFSET(Q32,$E$12,,)} -> 0.45 | R32: {=OFFSET(R32,$E$12,,)} -> 0.45 | S32: {=OFFSET(S32,$E$12,,)} -> 0.45 | T32: {=OFFSET(T32,$E$12,,)} -> 0.45 | ... V32: {=OFFSET(V32,$E$12,,)} -> 0.45
B33: Conservative Case
B34: Base Case | M34: 0.42 | N34: 0.425 | O34: 0.43 | P34: 0.44 | Q34: 0.45 | R34: 0.45 | S34: 0.45 | T34: 0.45 | U34: 0.45 | V34: 0.45
B35: Optimisitic Case
B37: Taxes | F37: =+Model!T21 -> 3250 | G37: =+Model!U21 -> 6327 | H37: =+Model!V21 -> 4034 | I37: =+Model!W21 -> 7914 | J37: =+Model!X21 -> 5619 | K37: =+Model!Y21 -> 8330 | L37: =+Model!Z21 -> 8303 | M37: =M38*M31 -> 12660.858 | N37: =N38*N31 -> 13611.9 | O37: =O38*O31 -> 14546.324 | P37: =P38*P31 -> 15637.762 | Q37: =Q38*Q31 -> 16721.484 | R37: =R38*R31 -> 17406.821 | S37: =S38*S31 -> 18048.905 | T37: =T38*T31 -> 18648.096 | ... V37: =V38*V31 -> 19721.711
B38: Tax Rate (%) | F38: =F37/F31 -> 0.13045398 | G38: =G37/G31 -> 0.26377887 | H38: =H37/H31 -> 0.12347342 | I38: =I37/I31 -> 0.16927256 | J38: =J37/J31 -> 0.1941335 | K38: =K37/K31 -> 0.17817801 | L38: =L37/L31 -> 0.11967426 | M38: 0.15 | N38: 0.15 | O38: 0.15 | P38: 0.15 | Q38: 0.15 | R38: 0.15 | S38: 0.15 | T38: 0.15 | U38: 0.15 | V38: 0.15
B40: Nopat | F40: =F31-F37 -> 21663 | G40: =G31-G37 -> 17659 | H40: =H31-H37 -> 28637 | I40: =I31-I37 -> 38839 | J40: =J31-J37 -> 23325 | K40: =K31-K37 -> 38421 | L40: =L31-L37 -> 61077 | M40: =M31-M37 -> 71744.862 | ... V40: =V31-V37 -> 111756.36
B42: D&A and other non-cash Expenses | F42: =+Model!T59+Model!T60 -> 8467 | G42: =+Model!U59+Model!U60 -> 10577 | H42: =+Model!V59+Model!V60 -> 13398 | I42: =+Model!W59+Model!W60 -> 17131 | J42: =+Model!X59+Model!X60 -> 20678 | K42: =+Model!Y59+Model!Y60 -> 25205 | L42: =+Model!Z59+Model!Z60 -> 32188 | M42: =M43*M25 -> 38183.54 | N42: =N43*N25 -> 40568.8 | O42: =O43*O25 -> 42849.637 | P42: =P43*P25 -> 45017.799 | Q42: =Q43*Q25 -> 47067.881 | R42: =R43*R25 -> 48996.979 | S42: =S43*S25 -> 50804.325 | T42: =T43*T25 -> 52490.937 | ... V42: =V43*V25 -> 55512.965
B43: % of Sales | F43: =F42/F25 -> 0.15163509 | G43: =G42/G25 -> 0.14961031 | H43: =H42/H25 -> 0.15585413 | I43: =I42/I25 -> 0.14526537 | J43: =J42/J25 -> 0.17732765 | K43: =K42/K25 -> 0.18683934 | L43: =L42/L25 -> 0.19567054 | M43: 0.19 | N43: 0.19 | O43: 0.19 | P43: 0.19 | Q43: 0.19 | R43: 0.19 | S43: 0.19 | T43: 0.19 | U43: 0.19 | V43: 0.19
B45: CapEx | F45: =+Model!T73 -> -13915 | G45: =+Model!U73 -> -15102 | H45: =+Model!V73 -> -15115 | I45: =+Model!W73 -> -18567 | J45: =+Model!X73 -> -31186 | K45: =+Model!Y73 -> -27045 | L45: =+Model!Z73 -> -37256 | M45: =M46*M25 -> -46222.18 | N45: =N46*N25 -> -49109.6 | O45: =O46*O25 -> -51870.613 | P45: =P46*P25 -> -54495.23 | Q45: =Q46*Q25 -> -56976.909 | R45: =R46*R25 -> -59312.132 | S45: =S46*S25 -> -61499.972 | T45: =T46*T25 -> -63541.661 | ... V45: =V46*V25 -> -67199.905
B46: % of Sales | F46: =F45/F25 -> -0.24920305 | G46: =G45/G25 -> -0.21361585 | H46: =H45/H25 -> -0.17582737 | I46: =I45/I25 -> -0.15744219 | J46: =J45/J25 -> -0.26744076 | K46: =K45/K25 -> -0.20047887 | L46: =L45/L25 -> -0.22647887 | M46: -0.23 | N46: -0.23 | O46: -0.23 | P46: -0.23 | Q46: -0.23 | R46: -0.23 | S46: -0.23 | T46: -0.23 | U46: -0.23 | V46: -0.23
B48: Change in WC | F48: =+Model!T71 -> -1527 | G48: =+Model!U71 -> 7250 | H48: =+Model!V71 -> -2723 | I48: =+Model!W71 -> 700 | J48: =+Model!X71 -> 5683 | K48: =+Model!Y71 -> 3836 | L48: =+Model!Z71 -> 1048 | M48: =M49*M25 -> 2009.66 | N48: =N49*N25 -> 2135.2 | O48: =O49*O25 -> 2255.244 | P48: =P49*P25 -> 2369.3578 | Q48: =Q49*Q25 -> 2477.2569 | R48: =R49*R25 -> 2578.7884 | S48: =S49*S25 -> 2673.9118 | T48: =T49*T25 -> 2762.6809 | ... V48: =V49*V25 -> 2921.735
B49: % of Sales | F49: =F48/F25 -> -0.027346968 | G49: =G48/G25 -> 0.10255032 | H49: =H48/H25 -> -0.031675682 | I49: =I48/I25 -> 0.0059357749 | J49: =J48/J25 -> 0.048735518 | K49: =K48/K25 -> 0.028435457 | L49: =L48/L25 -> 0.0063707819 | M49: 0.01 | N49: 0.01 | O49: 0.01 | P49: 0.01 | Q49: 0.01 | R49: 0.01 | S49: 0.01 | T49: 0.01 | U49: 0.01 | V49: 0.01
B51: Unlevered Free Cashflow | F51: =F40+F42+F45+F48 -> 14688 | G51: =G40+G42+G45+G48 -> 20384 | H51: =H40+H42+H45+H48 -> 24197 | I51: =I40+I42+I45+I48 -> 38103 | J51: =J40+J42+J45+J48 -> 18500 | K51: =K40+K42+K45+K48 -> 40417 | L51: =L40+L42+L45+L48 -> 57057 | M51: =M40+M42+M45+M48 -> 65715.882 | ... V51: =V40+V42+V45+V48 -> 102991.16
B52: Present Value of unlevered FC | M52: =(M51/(1+$E$18)^M53)*M53 -> 36261.136 | N52: =N51/(1+$E$18)^N53 -> 60821.346 | O52: =O51/(1+$E$18)^O53 -> 59150.029 | P52: =P51/(1+$E$18)^P53 -> 57924.902 | Q52: =Q51/(1+$E$18)^Q53 -> 56417.481 | R52: =R51/(1+$E$18)^R53 -> 53390.706 | S52: =S51/(1+$E$18)^S53 -> 50327.385 | T52: =T51/(1+$E$18)^T53 -> 47271.058 | U52: =U51/(1+$E$18)^U53 -> 44257.673 | V52: =V51/(1+$E$18)^V53 -> 41316.169
B53: Discount Period | M53: =YEARFRAC(E4,E5) -> 0.58333333 | N53: =M53+1 -> 1.5833333 | O53: =N53+1 -> 2.5833333 | P53: =O53+1 -> 3.5833333 | Q53: =P53+1 -> 4.5833333 | R53: =Q53+1 -> 5.5833333 | S53: =R53+1 -> 6.5833333 | T53: =S53+1 -> 7.5833333 | U53: =T53+1 -> 8.5833333 | V53: =U53+1 -> 9.5833333
B54: Sum of Present Value | V54: =SUM(M52:V52) -> 507137.89
B55: Terminal Value | V55: =+(V40*(1+E19))*(1-(E19/E20))/(E18-E19) -> 1315532.1 | X55: => CV(t) = NOPAT(t+1)*(1-g/RONIC)/(WACC - g) => equal pertuity formula: CV = FCF*(1+g) /(WACC-g)
B56: Present Value of TV | V56: =V55/(1+E18)^V53 -> 527741.85
B57: Enterprise Value | V57: =V54+V56 -> 1034879.7
B58: (+) Cash and other non-operating assets | V58: =+Main!I5 -> 90260
B59: (-) Debt and other non-equity claims | V59: =+Main!I6 -> 83664
B60: Equity Value | V60: =V57+V58-V59 -> 1041475.7
B61: Number of Shares | V61: =+Main!I3 -> 2547.5062
B62: Share Price | V62: =V60/V61 -> 408.82167
A66: x | B66: Sensitivity Analysis
C68: TGR | N68: ROINC
B69: WACC | C69: =+J4 -> 408.82167 | M69: WACC | N69: =+J4 -> 408.82167
