Workbook
Name WACC: DCF!$E$17

Sheet Main
A1: Frosta AG
A2: numbers in mio EUR | G2: Price | H2: 101.5 | K2: Management
G3: Shares | H3: 6.812598 | I3: Q226 | K3: CEO | L3: Felix Ahlers
B4: NLM | G4: MC | H4: =+H2*H3 -> 691.4787 | K4: CFO | L4: Maik Busse
B5: IR | G5: Cash | H5: 83.239 | I5: Q226 | K5: CMO | L5: Frank Brede
G6: Debt | H6: =10.385+5.079 -> 15.464 | I6: Q226
B7: Segments | C7: % of Rev | D7: Products/Brands | E7: Competitors | G7: EV | H7: =+H4-H5+H6 -> 623.7037
B8: Fisch | C8: 0.46 | D8: FRoSTA, Copack | E8: Nomad Foods | K8: Float
B9: Gemüse | C9: 0.22 | D9: FRoSTA, Copack | E9: Discounter Eigenmarken | G9: 1760 | H9: Employee Count | K9: 0.1 | L9: Dirk Ahlers
B10: Kräuter&Gerichte | C10: 0.32 | D10: FRoSTAm Copack | E10: Discounter Eigenmarken | G10: 1905 | H10: Founded | K10: 0.337 | L10: Felix Ahlers
G11: Founder: | H11: Adolf Ahlers | K11: =1-K9-K10 -> 0.563 | L11: Free Float
G12: Familienbetrieb in 3. Genaration
B14: Notes
B15: produziert schockgefrostete Produkte in drei Werken in Deutschland (Bremerhaven, Bobenheim-Roxheim, Lommatzsch) und einem Werk in Polen (Bydgoszc)
B16: In Deutschland vetreibt man unter der Marke FRoSTA Tiefkühlgerichte der Kategorien in Deutschland, Italien, Polen, Österreich und Osteuropa
B17: In Italien unter der Marke La Valle degli Orti -> Tiefkühlgemüse
B18: Seit 2003 verzichtet man auf den Zusatz von Farbstoffen, Aromen, Geschmacksverstärkern und sonstigen Zusatzstoffen (Reinheitsgebot)
B19: FRoSTA auch im Supermarkt erhältlich, auch vegetarische Gerichte, seit Herbst 2020 pflanzliche Alternativen zu Fisch
B20: Konzern entwickelt und produziert hochwertige Handelsmarken, Zweitmarken Tiko (Fisch und Gerichte), Elbtal (Gemüse)
B21: Marken: Out of Home, Heimdienst, Industriegescäft
B22: Gerichte: Butter Chicken, Hackbällchen Pfanne
B23: Fisch: Fischstäbchen (Chili Crunch, Bio Panade, glutenfrei), Alaska Seelachs-Filet (Kräuter&Butter, mediterran)
B24: Bio Gemüsepfannen/Gerichte: Bio Tagliatelle Cherrytomate, Bio Gelbes Curry, Bio Reis Champignon Pfanne, Gemüsepfanne a la Mexicana
B25: Bio Gemüsepfanne Gartengemüse, Bio Gemüsepfanne a la Ratatouille
... B39: 10.01.2025: Frosta: Leichtes Top und Bottom Beat für FY24

Sheet Model
A1: Main
C2: H122 | D2: H222 | E2: H123 | F2: H223 | G2: H124 | H2: H224 | I2: H125 | J2: H225 | K2: H126 | L2: H226 | N2: FY18 | O2: FY19 | P2: FY20 | Q2: FY21 | R2: FY22 | S2: FY23 | T2: FY24 | U2: FY25 | V2: FY26 | W2: FY27 | X2: FY28 | Y2: FY29
B3: TAM Tiefkühlgerichte DE | N3: =+O3*(1-4%) -> 6597.7089 | O3: =+P3*(1-4%) -> 6872.6134 | P3: =+Q3*(1-4%) -> 7158.9723 | Q3: =+R3*(1-4%) -> 7457.2628 | R3: =+S3*(1-4%) -> 7767.9821 | S3: =+T3*(1-4%) -> 8091.648 | T3: =+U3*(1-4%) -> 8428.8 | U3: 8780 | V3: =+U3*(1+3.82%) -> 9115.396 | W3: =+V3*(1+3.82%) -> 9463.6041 | X3: =+W3*(1+3.82%) -> 9825.1138 | Y3: =+X3*(1+3.82%) -> 10200.433
B4: Marktanteil DE | N4: =+N11/N3 -> 0.043227127 | O4: =+O11/O3 -> 0.043622416 | P4: =+P11/P3 -> 0.04461632 | Q4: =+Q11/Q3 -> 0.041649062 | R4: =+R11/R3 -> 0.044935737 | S4: =+S11/S3 -> 0.049662318 | T4: =+T11/T3 -> 0.046928388 | U4: 0.048 | V4: 0.05 | W4: 0.05 | X4: 0.05 | Y4: 0.05
B5: TAM Tiefkühlgerichte Europa | N5: =+O5*(1-4.5%) -> 65210.366 | O5: =+P5*(1-4.5%) -> 68283.106 | P5: =+Q5*(1-4.5%) -> 71500.634 | Q5: =+R5*(1-4.5%) -> 74869.774 | R5: =+S5*(1-4.5%) -> 78397.669 | S5: =+T5*(1-4.5%) -> 82091.8 | T5: 85960 | U5: 104500 | V5: =+U5*(1+5%) -> 109725 | W5: =+V5*(1+5%) -> 115211.25 | X5: =+W5*(1+5%) -> 120971.81 | Y5: =+X5*(1+5%) -> 127020.4
B6: Marktanteil Europa | N6: =+N16/N5 -> 0.0078098626 | O6: =+O16/O5 -> 0.0076583658 | P6: =+P16/P5 -> 0.0077167008 | Q6: =+Q16/Q5 -> 0.0070415733 | R6: =+R16/R5 -> 0.0073864058 | S6: =+S16/S5 -> 0.0077898158 | T6: =+T16/T5 -> 0.0074226617 | U6: 0.0076 | V6: 0.008 | W6: 0.008 | X6: 0.008 | Y6: 0.008
B7: TAM EU excl. DE | N7: =+N5-N3 -> 58612.657 | O7: =+O5-O3 -> 61410.492 | P7: =+P5-P3 -> 64341.662 | Q7: =+Q5-Q3 -> 67412.511 | R7: =+R5-R3 -> 70629.687 | S7: =+S5-S3 -> 74000.152 | T7: =+T5-T3 -> 77531.2 | U7: =+U5-U3 -> 95720 | ... Y7: =+Y5-Y3 -> 116819.97
B8: Marktanteil EU excl DE | N8: =+N12/N7 -> 0.0038234063 | O8: =+O12/O7 -> 0.0036329297 | P8: =+P12/P7 -> 0.0036110662 | Q8: =+Q12/Q7 -> 0.0032132463 | R8: =+R12/R7 -> 0.0032566618 | S8: =+S12/S7 -> 0.0032112096 | T8: =+T12/T7 -> 0.0031277989 | U8: 0.0030496349 | V8: 0.0030496349 | W8: 0.0030496349 | X8: 0.0030496349 | Y8: 0.0030496349
A10: x | B10: Income Statement
B11: Domestic | N11: 285.2 | O11: 299.8 | P11: 319.407 | Q11: 310.588 | R11: 349.06 | S11: 401.85 | T11: 395.55 | U11: 430.575 | V11: =+V3*V4 -> 455.7698 | W11: =+W3*W4 -> 473.18021 | X11: =+X3*X4 -> 491.25569 | Y11: =+Y3*Y4 -> 510.02166
B12: International | N12: 224.1 | O12: 223.1 | P12: 232.342 | Q12: 216.613 | R12: 230.017 | S12: 237.63 | T12: 242.502 | U12: 250.969 | V12: =+V7*V8 -> 306.82256 | W12: =+W7*W8 -> 322.49171 | X12: =+X7*X8 -> 338.95685 | Y12: =+Y7*Y8 -> 356.25825
B13: Fish | N13: n.a | O13: n.a | P13: 253.763 | Q13: 243.87 | R13: 272.501 | S13: 293.704 | T13: 288.367 | U13: 296.511 | V13: =46%*V16 -> 350.79248 | W13: =46%*W16 -> 366.00908 | X13: =46%*X16 -> 381.89777 | Y13: =46%*Y16 -> 398.48876
B14: Gemüse&Obst | N14: n.a | O14: n.a | P14: 150.479 | Q14: 136.833 | R14: 133.717 | S14: 141.058 | T14: 132.306 | U14: 128.251 | V14: =22%*V16 -> 167.77032 | W14: =22%*W16 -> 175.04782 | X14: =22%*X16 -> 182.64676 | Y14: =22%*Y16 -> 190.58158
B15: Fertiggerichte & Andere | N15: n.a | O15: n.a | P15: 147.507 | Q15: 146.498 | R15: 172.859 | S15: 204.718 | T15: 217.379 | U15: 256.782 | V15: =32%*V16 -> 244.02955 | W15: =32%*W16 -> 254.61501 | X15: =32%*X16 -> 265.66801 | Y15: =32%*Y16 -> 277.20957
B16: Revenue | C16: 275.829 | D16: =+Q16-C16 -> 251.372 | E16: 316.804 | F16: =+S16-E16 -> 322.676 | G16: 315.941 | H16: =+T16-G16 -> 322.111 | I16: 329.891 | J16: =+U16-I16 -> 351.652 | K16: 368.381 | N16: 509.284 | O16: 522.937 | P16: 551.749 | Q16: 527.201 | R16: 579.077 | S16: 639.48 | T16: 638.052 | U16: 681.543 | V16: =+SUM(V11:V12) -> 762.59236 | W16: =+SUM(W11:W12) -> 795.67191 | X16: =+SUM(X11:X12) -> 830.21254 | Y16: =+SUM(Y11:Y12) -> 866.27991
B17: Other | C17: =0.59+4.828 -> 5.418 | D17: =+Q17-C17 -> 15.204 | E17: =-3.481+4.974 -> 1.493 | F17: =+S17-E17 -> 10.172 | G17: =0.627+3.246 -> 3.873 | H17: =+T17-G17 -> 3.865 | I17: =11.538+7.046 -> 18.584 | J17: =+U17-I17 -> 6.625 | K17: =2.355-5.311 -> -2.956 | N17: =-5.613+9.315 -> 3.702 | O17: =1.432+0.056+7.396 -> 8.884 | P17: =4.384+0.128+9.323 -> 13.835 | Q17: =11.669+8.953 -> 20.622 | R17: =-0.744+12.546 -> 11.802 | S17: =-4.836+16.501 -> 11.665 | T17: =7.897-0.159 -> 7.738 | U17: =15.882+9.327 -> 25.209 | V17: 11.7 | W17: 11.7 | X17: 11.7 | Y17: 11.7
B18: Operating Performance | C18: =+C16+C17 -> 281.247 | D18: =+D16+D17 -> 266.576 | E18: =+E16+E17 -> 318.297 | F18: =+F16+F17 -> 332.848 | G18: =+G16+G17 -> 319.814 | H18: =+H16+H17 -> 325.976 | I18: =+I16+I17 -> 348.475 | J18: =+J16+J17 -> 358.277 | K18: =+K16+K17 -> 365.425 | N18: =+N16+N17 -> 512.986 | O18: =+O16+O17 -> 531.821 | P18: =+P16+P17 -> 565.584 | Q18: =+Q16+Q17 -> 547.823 | R18: =+R16+R17 -> 590.879 | S18: =+S16+S17 -> 651.145 | T18: =+T16+T17 -> 645.79 | U18: =+U16+U17 -> 706.752 | ... Y18: =+Y16+Y17 -> 877.97991
B19: COGS | C19: 167.399 | D19: =+Q19-C19 -> 142.446 | E19: 184.017 | F19: =+S19-E19 -> 182.058 | G19: 168.783 | H19: =+T19-G19 -> 161.421 | I19: =170.817+8.556 -> 179.373 | J19: =+U19-I19 -> 181.292 | K19: =179.109+8.37 -> 187.479 | N19: 300.273 | O19: 327.034 | P19: 332.104 | Q19: 309.845 | R19: 346.109 | S19: 366.075 | T19: 330.204 | U19: 360.665 | V19: =+V18-V20 -> 415.87395 | W19: =+W18-W20 -> 433.40611 | X19: =+X18-X20 -> 451.71264 | Y19: =+Y18-Y20 -> 470.82835
B20: Gross Profit | C20: =+C18-C19 -> 113.848 | D20: =+D18-D19 -> 124.13 | E20: =+E18-E19 -> 134.28 | F20: =+F18-F19 -> 150.79 | G20: =+G18-G19 -> 151.031 | H20: =+H18-H19 -> 164.555 | I20: =+I18-I19 -> 169.102 | J20: =+J18-J19 -> 176.985 | K20: =+K18-K19 -> 177.946 | N20: =+N18-N19 -> 212.713 | O20: =+O18-O19 -> 204.787 | P20: =+P18-P19 -> 233.48 | Q20: =+Q18-Q19 -> 237.978 | R20: =+R18-R19 -> 244.77 | S20: =+S18-S19 -> 285.07 | T20: =+T18-T19 -> 315.586 | U20: =+U18-U19 -> 346.087 | V20: =+V16*V41 -> 358.41841 | W20: =+W16*W41 -> 373.9658 | X20: =+X16*X41 -> 390.19989 | Y20: =+Y16*Y41 -> 407.15156
B21: Emplyoee Payroll | C21: 38.631 | D21: =+Q21-C21 -> 40.369 | E21: 40.385 | F21: =+S21-E21 -> 43.699 | G21: 46.203 | H21: =+T21-G21 -> 49.007 | I21: 51.819 | J21: =+U21-I21 -> 54.038 | K21: 55.207 | N21: 74.275 | O21: 75.722 | P21: 78.957 | Q21: 79 | R21: 76.612 | S21: 84.084 | T21: 95.21 | U21: 105.857 | V21: =+(V20-V24)*35% -> 106.76293 | W21: =+(W20-W24)*35% -> 111.39407 | X21: =+(X20-X24)*35% -> 116.22976 | Y21: =+(Y20-Y24)*35% -> 121.27919
B22: D&A | C22: 9.548 | D22: =+Q22-C22 -> 8.898 | E22: 10.353 | F22: =+S22-E22 -> 10.126 | G22: 10.415 | H22: =+T22-G22 -> 9.992 | I22: 10.861 | J22: =+U22-I22 -> 9.557 | K22: 10.813 | N22: 16.538 | O22: 18.752 | P22: 18.495 | Q22: 18.446 | R22: 20.322 | S22: 20.479 | T22: 20.407 | U22: 20.418 | V22: =+(V20-V24)*9% -> 27.453325 | W22: =+(W20-W24)*9% -> 28.644189 | X22: =+(X20-X24)*9% -> 29.887651 | Y22: =+(Y20-Y24)*9% -> 31.186077
B23: Other operating Expenses | C23: 54.493 | D23: =+Q23-C23 -> 47.465 | E23: 61.095 | F23: =+S23-E23 -> 71.336 | G23: 72.471 | H23: =+T23-G23 -> 68.585 | I23: 82.716 | J23: =+U23-I23 -> 86.841 | K23: 86.913 | N23: 91.861 | O23: 94.13 | P23: 98.943 | Q23: 101.958 | R23: 113.312 | S23: 132.431 | T23: 141.056 | U23: 169.557 | V23: =+(V20-V24)*56% -> 170.82069 | W23: =+(W20-W24)*56% -> 178.23051 | X23: =+(X20-X24)*56% -> 185.96761 | Y23: =+(Y20-Y24)*56% -> 194.0467
B24: Operating Income | C24: =+C20-SUM(C21:C23) -> 11.176 | D24: =+D20-SUM(D21:D23) -> 27.398 | E24: =+E20-SUM(E21:E23) -> 22.447 | F24: =+F20-SUM(F21:F23) -> 25.629 | G24: =+G20-SUM(G21:G23) -> 21.942 | H24: =+H20-SUM(H21:H23) -> 36.971 | I24: =+I20-SUM(I21:I23) -> 23.706 | J24: =+J20-SUM(J21:J23) -> 26.549 | K24: =+K20-SUM(K21:K23) -> 25.013 | N24: =+N20-SUM(N21:N23) -> 30.039 | O24: =+O20-SUM(O21:O23) -> 16.183 | P24: =+P20-SUM(P21:P23) -> 37.085 | Q24: =+Q20-SUM(Q21:Q23) -> 38.574 | R24: =+R20-SUM(R21:R23) -> 34.524 | S24: =+S20-SUM(S21:S23) -> 48.076 | T24: =+T20-SUM(T21:T23) -> 58.913 | U24: =+U20-SUM(U21:U23) -> 50.255 | V24: =+V16*V42 -> 53.381465 | W24: =+W16*W42 -> 55.697034 | X24: =+X16*X42 -> 58.114878 | Y24: =+Y16*Y42 -> 60.639594
B25: Interest Income | C25: 0 | D25: =+Q25-C25 -> 0.023 | E25: 0.007 | F25: =+S25-E25 -> 0.721 | G25: 1.054 | H25: =+T25-G25 -> 1.682 | I25: 1.016 | J25: =+U25-I25 -> 1.451 | K25: 0.565 | N25: 0.055 | O25: 0.18 | P25: 0.051 | Q25: 0.023 | R25: 0.044 | S25: 0.728 | T25: 2.736 | U25: 2.467 | V25: =+U25*(1+3%) -> 2.54101 | W25: =+V25*(1+3%) -> 2.6172403 | X25: =+W25*(1+3%) -> 2.6957575 | Y25: =+X25*(1+3%) -> 2.7766302
B26: Interes Expense | C26: 0.141 | D26: =+Q26-C26 -> 0.297 | E26: 0.632 | F26: =+S26-E26 -> 0.493 | G26: 0.52 | H26: =+T26-G26 -> 0.485 | I26: 0.444 | J26: =+U26-I26 -> 0.436 | K26: 0.35 | N26: 0.792 | O26: 0.635 | P26: 0.563 | Q26: 0.438 | R26: 0.656 | S26: 1.125 | T26: 1.005 | U26: 0.88 | V26: 0.5 | W26: 0.5 | X26: 0.5 | Y26: 0.5
B27: Other | C27: 0 | D27: =+Q27-C27 -> 0 | E27: 0 | F27: =+S27-E27 -> -0.132 | G27: 0 | H27: =+T27-G27 -> 0 | I27: 0 | J27: =+U27-I27 -> 0 | K27: =+V27-J27 -> 0 | N27: 0.049 | O27: 0.566 | P27: 0.115 | Q27: 0 | R27: 0 | S27: -0.132 | T27: 0 | U27: 0 | V27: 0 | W27: 0 | X27: 0 | Y27: 0
B28: Pretax Income | C28: =+C24+C25-C26+C27 -> 11.035 | D28: =+D24+D25-D26+D27 -> 27.124 | E28: =+E24+E25-E26+E27 -> 21.822 | F28: =+F24+F25-F26+F27 -> 25.725 | G28: =+G24+G25-G26+G27 -> 22.476 | H28: =+H24+H25-H26+H27 -> 38.168 | I28: =+I24+I25-I26+I27 -> 24.278 | J28: =+J24+J25-J26+J27 -> 27.564 | K28: =+K24+K25-K26+K27 -> 25.228 | N28: =+N24+N25-N26+N27 -> 29.351 | O28: =+O24+O25-O26+O27 -> 16.294 | P28: =+P24+P25-P26+P27 -> 36.688 | Q28: =+Q24+Q25-Q26+Q27 -> 38.159 | R28: =+R24+R25-R26+R27 -> 33.912 | S28: =+S24+S25-S26+S27 -> 47.547 | T28: =+T24+T25-T26+T27 -> 60.644 | U28: =+U24+U25-U26+U27 -> 51.842 | ... Y28: =+Y24+Y25-Y26+Y27 -> 62.916224
B29: Tax Expense | C29: =2.732+0.157 -> 2.889 | D29: =+Q29-C29 -> 6.636 | E29: =6.054+0.273 -> 6.327 | F29: =+S29-E29 -> 7.17 | G29: =6.671+0.305 -> 6.976 | H29: =+T29-G29 -> 11.173 | I29: =6.231+0.305 -> 6.536 | J29: =+U29-I29 -> 8.283 | K29: =6.708+0.356 -> 7.064 | N29: =-0.482+9.85 -> 9.368 | O29: =-0.045+3.747 -> 3.702 | P29: =11.219+0.385 -> 11.604 | Q29: =9.122+0.403 -> 9.525 | R29: =9.19+0.418 -> 9.608 | S29: =13.022+0.475 -> 13.497 | T29: 18.149 | U29: =14.268+0.551 -> 14.819 | V29: =+V28*V43 -> 15.518293 | W29: =+W28*W43 -> 16.187997 | X29: =+X28*X43 -> 16.886978 | Y29: =+Y28*Y43 -> 17.616543
B30: Net Income | C30: =+C28-C29 -> 8.146 | D30: =+D28-D29 -> 20.488 | E30: =+E28-E29 -> 15.495 | F30: =+F28-F29 -> 18.555 | G30: =+G28-G29 -> 15.5 | H30: =+H28-H29 -> 26.995 | I30: =+I28-I29 -> 17.742 | J30: =+J28-J29 -> 19.281 | K30: =+K28-K29 -> 18.164 | N30: =+N28-N29 -> 19.983 | O30: =+O28-O29 -> 12.592 | P30: =+P28-P29 -> 25.084 | Q30: =+Q28-Q29 -> 28.634 | R30: =+R28-R29 -> 24.304 | S30: =+S28-S29 -> 34.05 | T30: =+T28-T29 -> 42.495 | U30: =+U28-U29 -> 37.023 | ... Y30: =+Y28-Y29 -> 45.299681
B32: EPS | C32: =+C30/C33 -> 1.1957259 | D32: =+D30/D33 -> 3.0073696 | E32: =+E30/E33 -> 2.2744627 | F32: =+F30/F33 -> 2.7236305 | G32: =+G30/G33 -> 2.2751966 | H32: =+H30/H33 -> 3.9625118 | I32: =+I30/I33 -> 2.6042928 | J32: =+J30/J33 -> 2.8301978 | K32: =+K30/K33 -> 2.6662369 | N32: =+N30/N33 -> 2.9330691 | O32: =+O30/O33 -> 1.8482313 | P32: =+P30/P33 -> 3.6817848 | Q32: =+Q30/Q33 -> 4.2028475 | R32: =+R30/R33 -> 3.5672978 | S32: =+S30/S33 -> 4.9977983 | T32: =+T30/T33 -> 6.2373404 | U32: =+U30/U33 -> 5.43417 | ... Y32: =+Y30/Y33 -> 6.6490065
B33: Shares | C33: 6.812598 | D33: 6.812598 | E33: 6.812598 | F33: 6.812598 | G33: 6.812598 | H33: 6.812598 | I33: 6.812598 | J33: 6.812598 | K33: 6.812598 | N33: 6.813 | O33: 6.813 | P33: 6.813 | Q33: 6.813 | R33: 6.813 | S33: 6.813 | T33: 6.813 | U33: 6.813 | V33: 6.813 | W33: 6.813 | X33: 6.813 | Y33: 6.813
B35: Domestic Growth | N35: n.a | O35: =+O11/N11-1 -> 0.051192146 | P35: =+P11/O11-1 -> 0.065400267 | Q35: =+Q11/P11-1 -> -0.027610541 | R35: =+R11/Q11-1 -> 0.12386828 | S35: =+S11/R11-1 -> 0.15123474 | T35: =+T11/S11-1 -> -0.015677492 | U35: =+U11/T11-1 -> 0.088547592 | V35: =+V11/U11-1 -> 0.058514312 | ... Y35: =+Y11/X11-1 -> 0.0382
B36: International Growth | N36: n.a | O36: =+O12/N12-1 -> -0.0044622936 | P36: =+P12/O12-1 -> 0.04142537 | Q36: =+Q12/P12-1 -> -0.067697618 | R36: =+R12/Q12-1 -> 0.061879943 | S36: =+S12/R12-1 -> 0.033097554 | T36: =+T12/S12-1 -> 0.020502462 | U36: =+U12/T12-1 -> 0.034915176 | V36: =+V12/U12-1 -> 0.22255161 | ... Y36: =+Y12/X12-1 -> 0.051043093
B37: Fisch Growth | N37: n.a | O37: n.a | P37: n.a | Q37: =+Q13/P13-1 -> -0.038985195 | R37: =+R13/Q13-1 -> 0.11740271 | S37: =+S13/R13-1 -> 0.077808889 | T37: =+T13/S13-1 -> -0.018171356 | U37: =+U13/T13-1 -> 0.028241789 | V37: =+V13/U13-1 -> 0.18306735 | W37: =+W13/V13-1 -> 0.043377773 | X37: =+X13/W13-1 -> 0.043410636 | Y37: =+Y13/X13-1 -> 0.043443542
B38: Gemüse&Obst Growth | N38: n.a | O38: n.a | P38: n.a | Q38: =+Q14/P14-1 -> -0.09068375 | R38: =+R14/Q14-1 -> -0.022772284 | S38: =+S14/R14-1 -> 0.054899527 | T38: =+T14/S14-1 -> -0.0620454 | U38: =+U14/T14-1 -> -0.030648648 | V38: =+V14/U14-1 -> 0.30814043 | W38: =+W14/V14-1 -> 0.043377773 | X38: =+X14/W14-1 -> 0.043410636 | Y38: =+Y14/X14-1 -> 0.043443542
B39: Andere Gerichte Growth | N39: n.a | O39: n.a | P39: n.a | Q39: =+Q15/P15-1 -> -0.0068403533 | R39: =+R15/Q15-1 -> 0.17994102 | S39: =+S15/R15-1 -> 0.18430628 | T39: =+T15/S15-1 -> 0.061846052 | U39: =+U15/T15-1 -> 0.18126406 | V39: =+V15/U15-1 -> -0.04966254 | W39: =+W15/V15-1 -> 0.043377773 | X39: =+X15/W15-1 -> 0.043410636 | Y39: =+Y15/X15-1 -> 0.043443542
B40: Revenue Growth | G40: =+G16/E16-1 -> -0.0027240818 | H40: =+H16/F16-1 -> -0.0017509824 | I40: =+I16/G16-1 -> 0.044153814 | J40: =+J16/H16-1 -> 0.091710621 | K40: =+K16/I16-1 -> 0.1166749 | N40: n.a | O40: =+O16/N16-1 -> 0.026808225 | P40: =+P16/O16-1 -> 0.055096503 | Q40: =+Q16/P16-1 -> -0.044491245 | R40: =+R16/Q16-1 -> 0.098398903 | S40: =+S16/R16-1 -> 0.1043091 | T40: =+T16/S16-1 -> -0.0022330644 | U40: =+U16/T16-1 -> 0.068162156 | V40: =+V16/U16-1 -> 0.11892038 | ... Y40: =+Y16/X16-1 -> 0.043443542
B41: Gross Margin | C41: =+C20/C18 -> 0.40479721 | D41: =+D20/D18 -> 0.46564582 | E41: =+E20/E18 -> 0.42187014 | F41: =+F20/F18 -> 0.45302961 | G41: =+G20/G18 -> 0.47224637 | H41: =+H20/H18 -> 0.5048071 | I41: =+I20/I18 -> 0.48526293 | J41: =+J20/J18 -> 0.49398929 | K41: =+K20/K18 -> 0.48695628 | N41: =+N20/N18 -> 0.41465654 | O41: =+O20/O18 -> 0.38506753 | P41: =+P20/P18 -> 0.41281224 | Q41: =+Q20/Q18 -> 0.43440673 | R41: =+R20/R18 -> 0.41424725 | S41: =+S20/S18 -> 0.43779803 | T41: 0.47 | U41: 0.47 | V41: 0.47 | W41: 0.47 | X41: 0.47 | Y41: 0.47
B42: Operating Margin | C42: =+C24/C18 -> 0.039737313 | D42: =+D24/D18 -> 0.10277744 | E42: =+E24/E18 -> 0.070522185 | F42: =+F24/F18 -> 0.076999111 | G42: =+G24/G18 -> 0.068608629 | H42: =+H24/H18 -> 0.11341633 | I42: =+I24/I18 -> 0.068027836 | J42: =+J24/J18 -> 0.074101882 | K42: =+K24/K18 -> 0.068449066 | N42: =+N24/N18 -> 0.058557154 | O42: =+O24/O18 -> 0.030429411 | P42: =+P24/P18 -> 0.065569394 | Q42: =+Q24/Q18 -> 0.070413254 | R42: =+R24/R18 -> 0.058428206 | S42: =+S24/S18 -> 0.073833017 | T42: 0.07 | U42: 0.07 | V42: 0.07 | W42: 0.07 | X42: 0.07 | Y42: 0.07
B43: Tax Rate | C43: =+C29/C28 -> 0.26180335 | D43: =+D29/D28 -> 0.24465418 | E43: =+E29/E28 -> 0.28993676 | F43: =+F29/F28 -> 0.2787172 | G43: =+G29/G28 -> 0.31037551 | H43: =+H29/H28 -> 0.29273213 | I43: =+I29/I28 -> 0.26921493 | J43: =+J29/J28 -> 0.30050065 | K43: =+K29/K28 -> 0.28000634 | N43: =+N29/N28 -> 0.31917141 | O43: =+O29/O28 -> 0.2272002 | P43: =+P29/P28 -> 0.3162887 | Q43: =+Q29/Q28 -> 0.24961346 | R43: =+R29/R28 -> 0.28332154 | S43: =+S29/S28 -> 0.28386649 | T43: 0.28 | U43: 0.28 | V43: 0.28 | W43: 0.28 | X43: 0.28 | Y43: 0.28
A45: x | B45: Balance Sheet
B46: Intangible Assets | E46: 8.662 | F46: 9.861 | G46: 8.986 | N46: 9.935 | O46: 12.234 | P46: 11.334 | Q46: 11.496 | R46: 9.632 | S46: 9.861 | T46: 8.372 | U46: 7.43
B47: PP&E | E47: 113.983 | F47: 112.738 | G47: 107.41 | N47: 122.963 | O47: 126.421 | P47: 113.938 | Q47: 109.946 | R47: 112.103 | S47: 112.738 | T47: 107.198 | U47: 110.141
B48: Financial Assets | E48: 0.186 | F48: 0.036 | G48: 0.036 | N48: 0.125 | O48: 0.165 | P48: 0.176 | Q48: 0.186 | R48: 0.186 | S48: 0.036 | T48: 0.036 | U48: 0.036
B49: Deferrd Tax Assets | E49: 0 | F49: 0 | G49: 0 | N49: 2.063 | O49: 2.789 | P49: 0 | Q49: 0 | R49: 0 | S49: 0 | T49: 0 | U49: 0
B50: Non-Current Assets | C50: =+SUM(C46:C49) -> 0 | D50: =+SUM(D46:D49) -> 0 | E50: =+SUM(E46:E49) -> 122.831 | F50: =+SUM(F46:F49) -> 122.635 | G50: =+SUM(G46:G49) -> 116.432 | H50: =+SUM(H46:H49) -> 0 | N50: =+SUM(N46:N49) -> 135.086 | O50: =+SUM(O46:O49) -> 141.609 | P50: =+SUM(P46:P49) -> 125.448 | Q50: =+SUM(Q46:Q49) -> 121.628 | R50: =+SUM(R46:R49) -> 121.921 | S50: =+SUM(S46:S49) -> 122.635 | T50: =+SUM(T46:T48) -> 115.606 | U50: =+SUM(U46:U48) -> 117.607
B51: Inventory | E51: 137.368 | F51: 147.754 | G51: 122.653 | N51: 89.065 | O51: 88.729 | P51: 89.108 | Q51: 120.026 | R51: 167.733 | S51: 147.754 | T51: 142.268 | U51: 165.877
B52: Accounts Receivable | E52: 70.529 | F52: 81.717 | G52: 72.07 | N52: 82.2 | O52: 75.039 | P52: =69.349+0.001 -> 69.35 | Q52: 66.677 | R52: 80.675 | S52: 81.717 | T52: 84.719 | U52: 91.636
B53: Other current Assets | E53: 9.167 | F53: 13.132 | G53: 9.468 | N53: =9.297+0.659+1.275 -> 11.231 | O53: =5.878+0.719+5.319 -> 11.916 | P53: 6.111 | Q53: 8.643 | R53: 9.309 | S53: 13.132 | T53: 6.752 | U53: =7.471 -> 7.471
B54: Cash & Cash-Equivalents | E54: 18.651 | F54: 67.083 | G54: 72.838 | N54: 11.045 | O54: 14.666 | P54: 17.018 | Q54: 7.208 | R54: 1.103 | S54: 67.083 | T54: 110.736 | U54: 116.907
B55: Current Assets | C55: =+SUM(C51:C54) -> 0 | D55: =+SUM(D51:D54) -> 0 | E55: =+SUM(E51:E54) -> 235.715 | F55: =+SUM(F51:F54) -> 309.686 | G55: =+SUM(G51:G54) -> 277.029 | H55: =+SUM(H51:H54) -> 0 | N55: =+SUM(N51:N54) -> 193.541 | O55: =+SUM(O51:O54) -> 190.35 | P55: =+SUM(P51:P54) -> 181.587 | Q55: =+SUM(Q51:Q54) -> 202.554 | R55: =+SUM(R51:R54) -> 258.82 | S55: =+SUM(S51:S54) -> 309.686 | T55: =+SUM(T51:T54) -> 344.475 | U55: =+SUM(U51:U54) -> 381.891
B56: Prepaid Expenses | E56: =0.388+0.028 -> 0.416 | F56: 1.021 | G56: =0.699+0.008 -> 0.707 | N56: 0 | O56: 0 | P56: =0.755+0.088 -> 0.843 | Q56: =1.327+0.124 -> 1.451 | R56: 2.032 | S56: 1.021 | T56: 0.519 | U56: 0.603
B57: Total Assets | C57: =+C50+C55+C56 -> 0 | D57: =+D50+D55+D56 -> 0 | E57: =+E50+E55+E56 -> 358.962 | F57: =+F50+F55+F56 -> 433.342 | G57: =+G50+G55+G56 -> 394.168 | H57: =+H50+H55+H56 -> 0 | N57: =+N50+N55+N56 -> 328.627 | O57: =+O50+O55+O56 -> 331.959 | P57: =+P50+P55+P56 -> 307.878 | Q57: =+Q50+Q55+Q56 -> 325.633 | R57: =+R50+R55+R56 -> 382.773 | S57: =+S50+S55+S56 -> 433.342 | T57: =+T50+T55+T56 -> 460.6 | U57: =+U50+U55+U56 -> 500.101
B58: Equity | E58: 211.759 | F58: 232.178 | G58: 232.91 | N58: 169.456 | O58: 171.197 | P58: 175.861 | Q58: 193.049 | R58: 205.255 | S58: 232.178 | T58: 261.048 | U58: 282.279
B59: Pension Liabilties | E59: 1.18 | F59: 1.28 | G59: 1.355 | N59: 1.069 | O59: 0.758 | P59: 0.868 | Q59: 0.975 | R59: 1.105 | S59: 1.28 | T59: 1.496 | U59: 1.723
B60: Tax Provisions | E60: 7.202 | F60: 9.107 | G60: 13.666 | N60: 1.983 | O60: 2.655 | P60: 4.377 | Q60: 4.065 | R60: 4.017 | S60: 9.107 | T60: 15.007 | U60: 12.847
B61: Other Provisions | E61: 57.959 | F61: 52.615 | G61: 61.795 | N61: 2.628 | O61: 2.917 | P61: 39.374 | Q61: 39.802 | R61: 43.656 | S61: 52.615 | T61: 53.599 | U61: 55.892
B62: Debt | E62: 23.021 | F62: 20.842 | G62: 19.061 | N62: =23.704+18.509+2.702 -> 44.915 | O62: =16.83+38.868+2.464 -> 58.162 | P62: 28.79 | Q62: 14.049 | R62: 42.52 | S62: 20.842 | T62: 16.056 | U62: 12.127
B63: Account Payables | E63: 52.367 | F63: 106.184 | G63: 58.438 | N63: 92.646 | O63: 84.104 | P63: 50.866 | Q63: 64.894 | R63: 78.052 | S63: 106.184 | T63: 103.119 | U63: 124.33
B64: Other Liabilties | E64: 5.001 | F64: 10.337 | G64: 6.145 | N64: =0.312+11.749 -> 12.061 | O64: =9.08+0.767 -> 9.847 | P64: 7.742 | Q64: 8.569 | R64: 7.694 | S64: 10.337 | T64: 10.274 | U64: 10.903
B65: Defered Taxes | E65: 0.474 | F65: 0.799 | G65: 0.799 | N65: 3.869 | O65: 2.319 | P65: 0 | Q65: 0.23 | R65: 0.474 | S65: 0.799 | T65: 0 | U65: 0
B66: Total Liabilities | C66: =+SUM(C59:C65) -> 0 | D66: =+SUM(D59:D65) -> 0 | E66: =+SUM(E59:E65) -> 147.204 | F66: =+SUM(F59:F65) -> 201.164 | G66: =+SUM(G59:G65) -> 161.259 | H66: =+SUM(H59:H65) -> 0 | N66: =+SUM(N59:N65) -> 159.171 | O66: =+SUM(O59:O65) -> 160.762 | P66: =+SUM(P59:P65) -> 132.017 | Q66: =+SUM(Q59:Q65) -> 132.584 | R66: =+SUM(R59:R65) -> 177.518 | S66: =+SUM(S59:S65) -> 201.164 | T66: =+SUM(T59:T65) -> 199.551 | U66: =+SUM(U59:U65) -> 217.822
B67: Liabilities & Equity | C67: =+C66+C58 -> 0 | D67: =+D66+D58 -> 0 | E67: =+E66+E58 -> 358.963 | F67: =+F66+F58 -> 433.342 | G67: =+G66+G58 -> 394.169 | H67: =+H66+H58 -> 0 | N67: =+N66+N58 -> 328.627 | O67: =+O66+O58 -> 331.959 | P67: =+P66+P58 -> 307.878 | Q67: =+Q66+Q58 -> 325.633 | R67: =+R66+R58 -> 382.773 | S67: =+S66+S58 -> 433.342 | T67: =+T66+T58 -> 460.599 | U67: =+U66+U58 -> 500.101
A69: x | B69: Cashflow Statement
B70: Net Income | C70: =+C30 -> 8.146 | D70: =+D30 -> 20.488 | E70: =+E30 -> 15.495 | F70: =+F30 -> 18.555 | G70: =+G30 -> 15.5 | H70: =+H30 -> 26.995 | N70: =+N30 -> 19.983 | O70: =+O30 -> 12.592 | P70: =+P30 -> 25.084 | Q70: =+Q30 -> 28.634 | R70: =+R30 -> 24.304 | S70: =+S30 -> 34.05 | T70: 41.974 | U70: 37.023
B71: Taxes | E71: 6.328 | G71: 6.671 | N71: =+N29 -> 9.368 | O71: =+O29 -> 3.702 | P71: 11.219 | Q71: 9.122 | R71: 9.19 | S71: 13.022 | T71: 0 | U71: 0
B72: D&A | E72: 10.353 | G72: 10.415 | N72: 16.538 | O72: 18.752 | P72: 18.495 | Q72: 18.446 | R72: 20.322 | S72: 20.479 | T72: 20.407 | U72: 20.418
B73: Sale of Current Assets | E73: -0.034 | G73: 0 | N73: -0.26 | O73: -0.024 | P73: -0.084 | Q73: -0.021 | R73: -0.04 | S73: -0.042 | T73: 0 | U73: 0
B74: Interest Income | E74: 0 | G74: 0 | N74: -0.055 | O74: -0.18 | P74: -0.051 | Q74: -0.023 | R74: -0.044 | S74: -0.729 | T74: 0 | U74: -1.708
B75: Interest Expense | E75: 0 | G75: 0 | N75: 0.792 | O75: 0.635 | P75: 0.563 | Q75: 0.438 | R75: 0.656 | S75: 1.126 | T75: -0.013 | U75: 0.039
B76: Interest Received | E76: 0 | G76: 0 | N76: -0.506 | O76: 0.119 | P76: 0 | Q76: 0 | R76: -0.586 | S76: -1.115 | T76: 0 | U76: 0
B77: Interest Paid | E77: 0 | G77: 0 | N77: 0.004 | O77: -0.524 | P77: -0.52 | Q77: -0.291 | R77: 0 | S77: 0.624 | T77: -1.731 | U77: -1.588
B78: Taxes Paid | E78: -4.879 | G78: -4.268 | N78: -11.308 | O78: -11.878 | P78: -10.15 | Q78: -11.417 | R78: -9.465 | S78: -9.119 | T78: -9.26 | U78: -16.462
B79: Taxes Received | E79: 0 | G79: 0.052 | N79: 0 | O79: 2.561 | P79: 5.082 | Q79: 0.078 | R79: 2.568 | S79: 0 | T79: 0 | U79: 0
B80: Change in non-current Provisions | E80: 0 | G80: 9.255 | N80: 0.205 | O80: -0.021 | P80: 0.593 | Q80: 0.253 | R80: 0.008 | S80: 0.814 | T80: 1.156 | U80: 4.456
B81: Change in current Provisions | E81: 0 | G81: 1.171 | N81: -0.78 | O81: 0.456 | P81: 0.937 | Q81: -0.696 | R81: 0.117 | S81: -0.292 | T81: 0 | U81: 0
B82: Other Income | E82: 0 | G82: 0 | N82: -8.384 | O82: 2.06 | P82: 2.601 | Q82: -0.467 | R82: -0.08 | S82: 1.743 | T82: 18.916 | U82: 14.268
B83: Change in non-operating Assets | E83: 14.648 | G83: 0 | N83: -2.349 | O83: 3.42 | P83: 0 | Q83: 0 | R83: -1.973 | S83: -0.41 | T83: 2.877 | U83: -1.243
... B86: Change in Accounts Payables | E86: -25.685 | G86: -47.746 | N86: 16.766 | O86: -5.98 | P86: -4.329 | Q86: 14.029 | R86: 8.662 | S86: 28.132 | T86: -3.064 | U86: 19.296
B87: Change in Working Capital | C87: =+C85+C86 -> 0 | D87: =+D85+D86 -> 0 | E87: =+E85+E86 -> 14.826 | F87: =+F85+F86 -> 0 | G87: =+G85+G86 -> -12.998 | H87: =+H85+H86 -> 0 | N87: =+N85+N86 -> 18.15 | O87: =+O85+O86 -> 1.517 | P87: =+P85+P86 -> 1.073 | Q87: =+Q85+Q86 -> -14.116 | R87: =+R85+R86 -> -48.46 | S87: =+S85+S86 -> 46.708 | T87: =+T85+T86 -> -0.579 | U87: =+U85+U86 -> -9.315
B88: CFFO | C88: =+SUM(C70:C84)+C87 -> 8.146 | D88: =+SUM(D70:D84)+D87 -> 20.488 | E88: =+SUM(E70:E84)+E87 -> 59.314 | F88: =+SUM(F70:F84)+F87 -> 18.555 | G88: =+SUM(G70:G84)+G87 -> 25.798 | H88: =+SUM(H70:H84)+H87 -> 26.995 | N88: =+SUM(N70:N84)+N87 -> 47.22 | O88: =+SUM(O70:O84)+O87 -> 25.848 | P88: =+SUM(P70:P84)+P87 -> 54.842 | Q88: =+SUM(Q70:Q84)+Q87 -> 29.94 | R88: =+SUM(R70:R84)+R87 -> -2.146 | S88: =+SUM(S70:S84)+S87 -> 117.783 | T88: =+SUM(T70:T84)+T87 -> 73.077 | U88: =+SUM(U70:U84)+U87 -> 47.425
B89: Sale of PP&E | E89: 0.005 | G89: 0.006 | N89: 0.016 | O89: 0.031 | P89: 0.01 | Q89: =0.005+0.808 -> 0.813 | R89: 0 | S89: 0.005 | T89: 0.007 | U89: 0.413
B90: Subsidies | E90: -0.008 | G90: 0 | N90: 0 | O90: 0 | P90: 0 | Q90: 0.106 | R90: 0 | S90: 0.187 | T90: =0.158+2.67 -> 2.828 | U90: =0.071+2.872 -> 2.943
B91: Investments in PP&E | E91: -9.728 | G91: -3.358 | N91: -35.448 | O91: -22.284 | P91: -13.896 | Q91: -12.999 | R91: -19.559 | S91: -17.767 | T91: -11.353 | U91: -20.039
B92: Investments in Intangibles | E92: -0.213 | G92: -0.664 | N92: -1.877 | O92: =-1.992-0.04 -> -2.032 | P92: =-1.238-0.01 -> -1.248 | Q92: =-1.974-0.028 -> -2.002 | R92: -1.572 | S92: -1.79 | T92: -1.879 | U92: -2.614
B93: CFFI | C93: =+SUM(C89:C92) -> 0 | D93: =+SUM(D89:D92) -> 0 | E93: =+SUM(E89:E92) -> -9.944 | F93: =+SUM(F89:F92) -> 0 | G93: =+SUM(G89:G92) -> -4.016 | H93: =+SUM(H89:H92) -> 0 | N93: =+SUM(N89:N92) -> -37.309 | O93: =+SUM(O89:O92) -> -24.285 | P93: =+SUM(P89:P92) -> -15.134 | Q93: =+SUM(Q89:Q92) -> -14.082 | R93: =+SUM(R89:R92) -> -21.131 | S93: =+SUM(S89:S92) -> -19.365 | T93: =+SUM(T89:T92) -> -10.397 | U93: =+SUM(U89:U92) -> -19.297
B94: Stock Repurchaes | E94: -0.953 | G94: -1.507 | N94: -3.367 | O94: -1.789 | P94: -0.996 | Q94: -3.388 | R94: -2.213 | S94: -1.595 | T94: -1.981 | U94: -6.511
B95: Issuance of Stock | E95: 0.08 | G95: 0.275 | N95: 3.307 | O95: 1.224 | P95: 1.632 | Q95: 3.388 | R95: 1.775 | S95: 1.656 | T95: 2.236 | U95: 6.139
B96: Dividends | E96: -10.884 | G96: -13.605 | N96: -10.876 | O96: -10.885 | P96: -10.867 | Q96: -10.9 | R96: -10.891 | S96: -10.884 | T96: -13.6 | U96: -16.328
B97: Issuance of Debt | E97: 0 | G97: 0 | N97: 5.15 | O97: 0 | P97: 0 | Q97: 0 | R97: 20 | S97: 0 | T97: 0 | U97: 0
B98: Redemption of Debt | E98: =-2.602+0.001-0.624 -> -3.225 | G98: =-1.782+1.043-0.475 -> -1.214 | N98: -7.502 | O98: -7.258 | P98: -6.873 | Q98: -6.412 | R98: -4.581 | S98: -4.995 | T98: -4.787 | U98: -3.928
B99: Increase in other financial liabilties | E99: -16.897 | G99: 0 | N99: 0 | O99: 20.743 | P99: -20.035 | Q99: -8.33 | R99: 13.052 | S99: -16.682 | T99: -0.943 | U99: -1.437
B100: CFFI | C100: =+SUM(C94:C99) -> 0 | D100: =+SUM(D94:D99) -> 0 | E100: =+SUM(E94:E99) -> -31.879 | F100: =+SUM(F94:F99) -> 0 | G100: =+SUM(G94:G99) -> -16.051 | H100: =+SUM(H94:H99) -> 0 | N100: =+SUM(N94:N99) -> -13.288 | O100: =+SUM(O94:O99) -> 2.035 | P100: =+SUM(P94:P99) -> -37.139 | Q100: =+SUM(Q94:Q99) -> -25.642 | R100: =+SUM(R94:R99) -> 17.142 | S100: =+SUM(S94:S99) -> -32.5 | T100: =+SUM(T94:T99) -> -19.075 | U100: =+SUM(U94:U99) -> -22.065
B101: Currency Exchange Rate Effect | E101: 0.042 | G101: 0.024 | N101: -0.156 | O101: 0.023 | P101: -0.217 | Q101: -0.026 | R101: -0.003 | S101: 0.062 | T101: 0.05 | U101: 0.109
B102: Change in Cash | C102: =+C88+C93+C100+C101 -> 8.146 | D102: =+D88+D93+D100+D101 -> 20.488 | E102: =+E88+E93+E100+E101 -> 17.533 | F102: =+F88+F93+F100+F101 -> 18.555 | G102: =+G88+G93+G100+G101 -> 5.755 | H102: =+H88+H93+H100+H101 -> 26.995 | N102: =+N88+N93+N100+N101 -> -3.533 | O102: =+O88+O93+O100+O101 -> 3.621 | P102: =+P88+P93+P100+P101 -> 2.352 | Q102: =+Q88+Q93+Q100+Q101 -> -9.81 | R102: =+R88+R93+R100+R101 -> -6.138 | S102: =+S88+S93+S100+S101 -> 65.98 | T102: =+T88+T93+T100+T101 -> 43.655 | U102: =+U88+U93+U100+U101 -> 6.172
B103: Cash BOP | E103: 1.103 | G103: 67.083 | N103: =+N104-N102 -> 14.578 | O103: =+O104-O102 -> 11.045 | P103: =+P104-P102 -> 14.666 | Q103: =+Q104-Q102 -> 17.018 | R103: =+R104-R102 -> 7.241 | S103: 1.103 | T103: =+S104 -> 67.083 | U103: =+T104 -> 110.738
B104: Cash EOP | E104: =+E102+E103 -> 18.636 | G104: =+G102+G103 -> 72.838 | N104: =+O103 -> 11.045 | O104: 14.666 | P104: =+Q103 -> 17.018 | Q104: 7.208 | R104: =+S103 -> 1.103 | S104: =+S102+S103 -> 67.083 | T104: =+T102+T103 -> 110.738 | U104: =+U102+U103 -> 116.91

Sheet WC
A1: Main
C2: H122 | D2: H222 | E2: H123 | F2: H223 | G2: H124 | H2: H224 | J2: FY18 | K2: FY19 | L2: FY20 | M2: FY21 | N2: FY22 | O2: FY23 | P2: FY24 | Q2: FY25 | R2: FY26 | S2: FY27 | T2: FY28 | U2: FY29
B3: TAM Tiefkühlgerichte DE | J3: =+K3*(1-4%) -> 6597.7089 | K3: =+L3*(1-4%) -> 6872.6134 | L3: =+M3*(1-4%) -> 7158.9723 | M3: =+N3*(1-4%) -> 7457.2628 | N3: =+O3*(1-4%) -> 7767.9821 | O3: =+P3*(1-4%) -> 8091.648 | P3: =+Q3*(1-4%) -> 8428.8 | Q3: 8780 | R3: =+Q3*(1+1.82%) -> 8939.796 | S3: =+R3*(1+1.82%) -> 9102.5003 | T3: =+S3*(1+1.82%) -> 9268.1658 | U3: =+T3*(1+1.82%) -> 9436.8464
B4: Marktanteil DE | J4: =+J11/J3 -> 0.043227127 | K4: =+K11/K3 -> 0.043622416 | L4: =+L11/L3 -> 0.04461632 | M4: =+M11/M3 -> 0.041649062 | N4: =+N11/N3 -> 0.044935737 | O4: =+O11/O3 -> 0.049662318 | P4: =+P11/P3 -> 0.047437447 | Q4: 0.045 | R4: 0.043 | S4: 0.042 | T4: 0.041 | U4: 0.04
B5: TAM Tiefkühlgerichte Europa | J5: =+K5*(1-4.5%) -> 65210.366 | K5: =+L5*(1-4.5%) -> 68283.106 | L5: =+M5*(1-4.5%) -> 71500.634 | M5: =+N5*(1-4.5%) -> 74869.774 | N5: =+O5*(1-4.5%) -> 78397.669 | O5: =+P5*(1-4.5%) -> 82091.8 | P5: 85960 | Q5: 104500 | R5: =+Q5*(1+3%) -> 107635 | S5: =+R5*(1+3%) -> 110864.05 | T5: =+S5*(1+3%) -> 114189.97 | U5: =+T5*(1+3%) -> 117615.67
B6: Marktanteil Europa | J6: =+J16/J5 -> 0.0078098626 | K6: =+K16/K5 -> 0.0076583658 | L6: =+L16/L5 -> 0.0077167008 | M6: =+M16/M5 -> 0.0070415733 | N6: =+N16/N5 -> 0.0073864058 | O6: =+O16/O5 -> 0.0077898158 | P6: =+P16/P5 -> 0.0074020777 | Q6: 0.006 | R6: 0.005 | S6: 0.005 | T6: 0.005 | U6: 0.005
B7: TAM EU excl. DE | J7: =+J5-J3 -> 58612.657 | K7: =+K5-K3 -> 61410.492 | L7: =+L5-L3 -> 64341.662 | M7: =+M5-M3 -> 67412.511 | N7: =+N5-N3 -> 70629.687 | O7: =+O5-O3 -> 74000.152 | P7: =+P5-P3 -> 77531.2 | Q7: =+Q5-Q3 -> 95720 | ... U7: =+U5-U3 -> 108178.82
B8: Marktanteil EU excl DE | J8: =+J12/J7 -> 0.0038234063 | K8: =+K12/K7 -> 0.0036329297 | L8: =+L12/L7 -> 0.0036110662 | M8: =+M12/M7 -> 0.0032132463 | N8: =+N12/N7 -> 0.0032566618 | O8: =+O12/O7 -> 0.0032112096 | P8: =+P12/P7 -> 0.0030496349 | Q8: 0.002 | R8: 0.002 | S8: 0.002 | T8: 0.002 | U8: 0.002
A10: x | B10: Income Statement
B11: Domestic | J11: 285.2 | K11: 299.8 | L11: 319.407 | M11: 310.588 | N11: 349.06 | O11: 401.85 | P11: =+O11*(1-0.5%) -> 399.84075 | Q11: =+Q3*Q4 -> 395.1 | R11: =+R3*R4 -> 384.41123 | S11: =+S3*S4 -> 382.30501 | T11: =+T3*T4 -> 379.9948 | U11: =+U3*U4 -> 377.47386
B12: International | J12: 224.1 | K12: 223.1 | L12: 232.342 | M12: 216.613 | N12: 230.017 | O12: 237.63 | P12: =+O12*(1-0.5%) -> 236.44185 | Q12: =+Q7*Q8 -> 191.44 | R12: =+R7*R8 -> 197.39041 | S12: =+S7*S8 -> 203.5231 | T12: =+T7*T8 -> 209.84361 | U12: =+U7*U8 -> 216.35765
B13: Fish | J13: n.a | K13: n.a | L13: 253.763 | M13: 243.87 | N13: 272.501 | O13: 293.704 | P13: =46%*P16 -> 292.69 | Q13: =46%*Q16 -> 269.8084 | R13: =46%*R16 -> 267.62875 | S13: =46%*S16 -> 269.48093 | T13: =46%*T16 -> 271.32567 | U13: =46%*U16 -> 273.16249
B14: Gemüse&Obst | J14: n.a | K14: n.a | L14: 150.479 | M14: 136.833 | N14: 133.717 | O14: 141.058 | P14: =22%*P16 -> 139.98217 | Q14: =22%*Q16 -> 129.0388 | R14: =22%*R16 -> 127.99636 | S14: =22%*S16 -> 128.88218 | T14: =22%*T16 -> 129.76445 | U14: =22%*U16 -> 130.64293
B15: Fertiggerichte & Andere | J15: n.a | K15: n.a | L15: 147.507 | M15: 146.498 | N15: 172.859 | O15: 204.718 | P15: =32%*P16 -> 203.61043 | Q15: =32%*Q16 -> 187.6928 | R15: =32%*R16 -> 186.17652 | S15: =32%*S16 -> 187.465 | T15: =32%*T16 -> 188.74829 | U15: =32%*U16 -> 190.02608
B16: Revenue | E16: 316.804 | G16: 315.941 | J16: 509.284 | K16: 522.937 | L16: 551.749 | M16: 527.201 | N16: 579.077 | O16: 639.48 | P16: =+SUM(P11:P12) -> 636.2826 | Q16: =+SUM(Q11:Q12) -> 586.54 | R16: =+SUM(R11:R12) -> 581.80164 | S16: =+SUM(S11:S12) -> 585.82811 | T16: =+SUM(T11:T12) -> 589.83841 | U16: =+SUM(U11:U12) -> 593.8315
B17: Other | E17: =-3.481+4.974 -> 1.493 | G17: =0.627+3.246 -> 3.873 | J17: =-5.613+9.315 -> 3.702 | K17: =1.432+0.056+7.396 -> 8.884 | L17: =4.384+0.128+9.323 -> 13.835 | M17: =11.669+8.953 -> 20.622 | N17: =-0.744+12.546 -> 11.802 | O17: =-4.836+16.501 -> 11.665 | P17: 11.7 | Q17: 11.7 | R17: 11.7 | S17: 11.7 | T17: 11.7 | U17: 11.7
B18: Operating Performance | C18: =+C16+C17 -> 0 | D18: =+D16+D17 -> 0 | E18: =+E16+E17 -> 318.297 | F18: =+F16+F17 -> 0 | G18: =+G16+G17 -> 319.814 | H18: =+H16+H17 -> 0 | J18: =+J16+J17 -> 512.986 | K18: =+K16+K17 -> 531.821 | L18: =+L16+L17 -> 565.584 | M18: =+M16+M17 -> 547.823 | N18: =+N16+N17 -> 590.879 | O18: =+O16+O17 -> 651.145 | P18: =+P16+P17 -> 647.9826 | Q18: =+Q16+Q17 -> 598.24 | ... U18: =+U16+U17 -> 605.5315
B19: COGS | E19: 184.017 | G19: 168.783 | J19: 300.273 | K19: 327.034 | L19: 332.104 | M19: 309.845 | N19: 346.109 | O19: 366.075 | P19: =+P18-P20 -> 348.92978 | Q19: =+Q18-Q20 -> 322.5662 | R19: =+R18-R20 -> 320.05487 | S19: =+S18-S20 -> 322.1889 | T19: =+T18-T20 -> 324.31436 | U19: =+U18-U20 -> 326.4307
B20: Gross Profit | C20: =+C18-C19 -> 0 | D20: =+D18-D19 -> 0 | E20: =+E18-E19 -> 134.28 | F20: =+F18-F19 -> 0 | G20: =+G18-G19 -> 151.031 | H20: =+H18-H19 -> 0 | J20: =+J18-J19 -> 212.713 | K20: =+K18-K19 -> 204.787 | L20: =+L18-L19 -> 233.48 | M20: =+M18-M19 -> 237.978 | N20: =+N18-N19 -> 244.77 | O20: =+O18-O19 -> 285.07 | P20: =+P16*P41 -> 299.05282 | Q20: =+Q16*Q41 -> 275.6738 | R20: =+R16*R41 -> 273.44677 | S20: =+S16*S41 -> 275.33921 | T20: =+T16*T41 -> 277.22405 | U20: =+U16*U41 -> 279.10081
B21: Emplyoee Payroll | E21: 40.385 | G21: 46.203 | J21: 74.275 | K21: 75.722 | L21: 78.957 | M21: 79 | N21: 76.612 | O21: 84.084 | P21: =+(P20-P24)*35% -> 89.079564 | Q21: =+(Q20-Q24)*35% -> 83.142045 | R21: =+(R20-R24)*35% -> 83.488535 | S21: =+(S20-S24)*35% -> 84.066334 | T21: =+(T20-T24)*35% -> 84.641812 | U21: =+(U20-U24)*35% -> 85.214821
B22: D&A | E22: 10.353 | G22: 10.415 | J22: 16.538 | K22: 18.752 | L22: 18.495 | M22: 18.446 | N22: 20.322 | O22: 20.479 | P22: =+(P20-P24)*9% -> 22.906174 | Q22: =+(Q20-Q24)*9% -> 21.379383 | R22: =+(R20-R24)*9% -> 21.46848 | S22: =+(S20-S24)*9% -> 21.617057 | T22: =+(T20-T24)*9% -> 21.765037 | U22: =+(U20-U24)*9% -> 21.912383
B23: Other operating Expenses | E23: 61.095 | G23: 72.471 | J23: 91.861 | K23: 94.13 | L23: 98.943 | M23: 101.958 | N23: 113.312 | O23: 132.431 | P23: =+(P20-P24)*56% -> 142.5273 | Q23: =+(Q20-Q24)*56% -> 133.02727 | R23: =+(R20-R24)*56% -> 133.58166 | S23: =+(S20-S24)*56% -> 134.50613 | T23: =+(T20-T24)*56% -> 135.4269 | U23: =+(U20-U24)*56% -> 136.34371
B24: Operating Income | C24: =+C20-SUM(C21:C23) -> 0 | D24: =+D20-SUM(D21:D23) -> 0 | E24: =+E20-SUM(E21:E23) -> 22.447 | F24: =+F20-SUM(F21:F23) -> 0 | G24: =+G20-SUM(G21:G23) -> 21.942 | H24: =+H20-SUM(H21:H23) -> 0 | J24: =+J20-SUM(J21:J23) -> 30.039 | K24: =+K20-SUM(K21:K23) -> 16.183 | L24: =+L20-SUM(L21:L23) -> 37.085 | M24: =+M20-SUM(M21:M23) -> 38.574 | N24: =+N20-SUM(N21:N23) -> 34.524 | O24: =+O20-SUM(O21:O23) -> 48.076 | P24: =+P16*P42 -> 44.539782 | Q24: =+Q16*Q42 -> 38.1251 | R24: =+R16*R42 -> 34.908098 | S24: =+S16*S42 -> 35.149687 | T24: =+T16*T42 -> 35.390305 | U24: =+U16*U42 -> 35.62989
B25: Interest Income | E25: 0.007 | G25: 1.054 | J25: 0.055 | K25: 0.18 | L25: 0.051 | M25: 0.023 | N25: 0.044 | O25: 0.728 | P25: 2.2 | Q25: 2.5 | R25: =+Q25*(1+3%) -> 2.575 | S25: =+R25*(1+3%) -> 2.65225 | T25: =+S25*(1+3%) -> 2.7318175 | U25: =+T25*(1+3%) -> 2.813772
B26: Interes Expense | E26: 0.632 | G26: 0.52 | J26: 0.792 | K26: 0.635 | L26: 0.563 | M26: 0.438 | N26: 0.656 | O26: 1.125 | P26: 0.5 | Q26: 0.5 | R26: 0.5 | S26: 0.5 | T26: 0.5 | U26: 0.5
B27: Other | J27: 0.049 | K27: 0.566 | L27: 0.115 | M27: 0 | N27: 0 | O27: -0.132 | P27: 0 | Q27: 0 | R27: 0 | S27: 0 | T27: 0 | U27: 0
B28: Pretax Income | C28: =+C24+C25-C26+C27 -> 0 | D28: =+D24+D25-D26+D27 -> 0 | E28: =+E24+E25-E26+E27 -> 21.822 | F28: =+F24+F25-F26+F27 -> 0 | G28: =+G24+G25-G26+G27 -> 22.476 | H28: =+H24+H25-H26+H27 -> 0 | J28: =+J24+J25-J26+J27 -> 29.351 | K28: =+K24+K25-K26+K27 -> 16.294 | L28: =+L24+L25-L26+L27 -> 36.688 | M28: =+M24+M25-M26+M27 -> 38.159 | N28: =+N24+N25-N26+N27 -> 33.912 | O28: =+O24+O25-O26+O27 -> 47.547 | P28: =+P24+P25-P26+P27 -> 46.239782 | Q28: =+Q24+Q25-Q26+Q27 -> 40.1251 | ... U28: =+U24+U25-U26+U27 -> 37.943662
B29: Tax Expense | E29: =6.054+0.273 -> 6.327 | G29: =6.671+0.305 -> 6.976 | J29: =-0.482+9.85 -> 9.368 | K29: =-0.045+3.747 -> 3.702 | L29: =11.219+0.385 -> 11.604 | M29: =9.122+0.403 -> 9.525 | N29: =9.19+0.418 -> 9.608 | O29: =13.022+0.475 -> 13.497 | P29: =+P28*P43 -> 12.947139 | Q29: =+Q28*Q43 -> 11.235028 | R29: =+R28*R43 -> 10.355267 | S29: =+S28*S43 -> 10.444542 | T29: =+T28*T43 -> 10.534194 | U29: =+U28*U43 -> 10.624225
B30: Net Income | C30: =+C28-C29 -> 0 | D30: =+D28-D29 -> 0 | E30: =+E28-E29 -> 15.495 | F30: =+F28-F29 -> 0 | G30: =+G28-G29 -> 15.5 | H30: =+H28-H29 -> 0 | J30: =+J28-J29 -> 19.983 | K30: =+K28-K29 -> 12.592 | L30: =+L28-L29 -> 25.084 | M30: =+M28-M29 -> 28.634 | N30: =+N28-N29 -> 24.304 | O30: =+O28-O29 -> 34.05 | P30: =+P28-P29 -> 33.292643 | Q30: =+Q28-Q29 -> 28.890072 | ... U30: =+U28-U29 -> 27.319437
B32: EPS | J32: =+J30/J33 -> 2.9330691 | K32: =+K30/K33 -> 1.8482313 | L32: =+L30/L33 -> 3.6817848 | M32: =+M30/M33 -> 4.2028475 | N32: =+N30/N33 -> 3.5672978 | O32: =+O30/O33 -> 4.9977983 | P32: =+P30/P33 -> 4.8866348 | Q32: =+Q30/Q33 -> 4.2404333 | ... U32: =+U30/U33 -> 4.0098983
B33: Shares | J33: 6.813 | K33: 6.813 | L33: 6.813 | M33: 6.813 | N33: 6.813 | O33: 6.813 | P33: 6.813 | Q33: 6.813 | R33: 6.813 | S33: 6.813 | T33: 6.813 | U33: 6.813
B35: Domestic Growth | J35: n.a | K35: =+K11/J11-1 -> 0.051192146 | L35: =+L11/K11-1 -> 0.065400267 | M35: =+M11/L11-1 -> -0.027610541 | N35: =+N11/M11-1 -> 0.12386828 | O35: =+O11/N11-1 -> 0.15123474 | P35: =+P11/O11-1 -> -0.005 | Q35: =+Q11/P11-1 -> -0.011856595 | R35: =+R11/Q11-1 -> -0.027053333 | ... U35: =+U11/T11-1 -> -0.0066341463
B36: International Growth | J36: n.a | K36: =+K12/J12-1 -> -0.0044622936 | L36: =+L12/K12-1 -> 0.04142537 | M36: =+M12/L12-1 -> -0.067697618 | N36: =+N12/M12-1 -> 0.061879943 | O36: =+O12/N12-1 -> 0.033097554 | P36: =+P12/O12-1 -> -0.005 | Q36: =+Q12/P12-1 -> -0.19032946 | R36: =+R12/Q12-1 -> 0.031082365 | ... U36: =+U12/T12-1 -> 0.031042342
B37: Fisch Growth | J37: n.a | K37: n.a | L37: n.a | M37: =+M13/L13-1 -> -0.038985195 | N37: =+N13/M13-1 -> 0.11740271 | O37: =+O13/N13-1 -> 0.077808889 | P37: =+P13/O13-1 -> -0.0034524692 | Q37: =+Q13/P13-1 -> -0.078176898 | R37: =+R13/Q13-1 -> -0.008078501 | S37: =+S13/R13-1 -> 0.0069207016 | T37: =+T13/S13-1 -> 0.0068455189 | U37: =+U13/T13-1 -> 0.0067698134
B38: Gemüse&Obst Growth | J38: n.a | K38: n.a | L38: n.a | M38: =+M14/L14-1 -> -0.09068375 | N38: =+N14/M14-1 -> -0.022772284 | O38: =+O14/N14-1 -> 0.054899527 | P38: =+P14/O14-1 -> -0.0076268485 | Q38: =+Q14/P14-1 -> -0.078176898 | R38: =+R14/Q14-1 -> -0.008078501 | S38: =+S14/R14-1 -> 0.0069207016 | T38: =+T14/S14-1 -> 0.0068455189 | U38: =+U14/T14-1 -> 0.0067698134
B39: Andere Gerichte Growth | J39: n.a | K39: n.a | L39: n.a | M39: =+M15/L15-1 -> -0.0068403533 | N39: =+N15/M15-1 -> 0.17994102 | O39: =+O15/N15-1 -> 0.18430628 | P39: =+P15/O15-1 -> -0.0054102131 | Q39: =+Q15/P15-1 -> -0.078176898 | R39: =+R15/Q15-1 -> -0.008078501 | S39: =+S15/R15-1 -> 0.0069207016 | T39: =+T15/S15-1 -> 0.0068455189 | U39: =+U15/T15-1 -> 0.0067698134
B40: Revenue Growth | G40: =+G16/E16-1 -> -0.0027240818 | J40: n.a | K40: =+K16/J16-1 -> 0.026808225 | L40: =+L16/K16-1 -> 0.055096503 | M40: =+M16/L16-1 -> -0.044491245 | N40: =+N16/M16-1 -> 0.098398903 | O40: =+O16/N16-1 -> 0.1043091 | P40: =+P16/O16-1 -> -0.005 | Q40: =+Q16/P16-1 -> -0.078176898 | R40: =+R16/Q16-1 -> -0.008078501 | ... U40: =+U16/T16-1 -> 0.0067698134
B41: Gross Margin | C41: =+C20/C18 -> #DIV/0! | D41: =+D20/D18 -> #DIV/0! | E41: =+E20/E18 -> 0.42187014 | F41: =+F20/F18 -> #DIV/0! | G41: =+G20/G18 -> 0.47224637 | H41: =+H20/H18 -> #DIV/0! | J41: =+J20/J18 -> 0.41465654 | K41: =+K20/K18 -> 0.38506753 | L41: =+L20/L18 -> 0.41281224 | M41: =+M20/M18 -> 0.43440673 | N41: =+N20/N18 -> 0.41424725 | O41: =+O20/O18 -> 0.43779803 | P41: 0.47 | Q41: 0.47 | R41: 0.47 | S41: 0.47 | T41: 0.47 | U41: 0.47
B42: Operating Margin | C42: =+C24/C18 -> #DIV/0! | D42: =+D24/D18 -> #DIV/0! | E42: =+E24/E18 -> 0.070522185 | F42: =+F24/F18 -> #DIV/0! | G42: =+G24/G18 -> 0.068608629 | H42: =+H24/H18 -> #DIV/0! | J42: =+J24/J18 -> 0.058557154 | K42: =+K24/K18 -> 0.030429411 | L42: =+L24/L18 -> 0.065569394 | M42: =+M24/M18 -> 0.070413254 | N42: =+N24/N18 -> 0.058428206 | O42: =+O24/O18 -> 0.073833017 | P42: 0.07 | Q42: 0.065 | R42: 0.06 | S42: 0.06 | T42: 0.06 | U42: 0.06
B43: Tax Rate | C43: =+C29/C28 -> #DIV/0! | D43: =+D29/D28 -> #DIV/0! | E43: =+E29/E28 -> 0.28993676 | F43: =+F29/F28 -> #DIV/0! | G43: =+G29/G28 -> 0.31037551 | H43: =+H29/H28 -> #DIV/0! | J43: =+J29/J28 -> 0.31917141 | K43: =+K29/K28 -> 0.2272002 | L43: =+L29/L28 -> 0.3162887 | M43: =+M29/M28 -> 0.24961346 | N43: =+N29/N28 -> 0.28332154 | O43: =+O29/O28 -> 0.28386649 | P43: 0.28 | Q43: 0.28 | R43: 0.28 | S43: 0.28 | T43: 0.28 | U43: 0.28
A45: x | B45: Balance Sheet
B46: Intangible Assets | J46: 9.935 | K46: 12.234 | L46: 11.334 | M46: 11.496 | N46: 9.632 | O46: 9.861
B47: PP&E | J47: 122.963 | K47: 126.421 | L47: 113.938 | M47: 109.946 | N47: 112.103 | O47: 112.738
B48: Financial Assets | J48: 0.125 | K48: 0.165 | L48: 0.176 | M48: 0.186 | N48: 0.186 | O48: 0.036
B49: Deferrd Tax Assets | J49: 2.063 | K49: 2.789 | L49: 0 | M49: 0 | N49: 0 | O49: 0
B50: Non-Current Assets | J50: =+SUM(J46:J49) -> 135.086 | K50: =+SUM(K46:K49) -> 141.609 | L50: =+SUM(L46:L49) -> 125.448 | M50: =+SUM(M46:M49) -> 121.628 | N50: =+SUM(N46:N49) -> 121.921 | O50: =+SUM(O46:O49) -> 122.635 | P50: =+SUM(P46:P48) -> 0
B51: Inventory | J51: 89.065 | K51: 88.729 | L51: 89.108 | M51: 120.026 | N51: 167.733 | O51: 147.754
B52: Accounts Receivable | J52: 82.2 | K52: 75.039 | L52: =69.349+0.001 -> 69.35 | M52: 66.677 | N52: 80.675 | O52: 81.717
B53: Other current Assets | J53: =9.297+0.659+1.275 -> 11.231 | K53: =5.878+0.719+5.319 -> 11.916 | L53: 6.111 | M53: 8.643 | N53: 9.309 | O53: 13.132
B54: Cash & Cash-Equivalents | J54: 11.045 | K54: 14.666 | L54: 17.018 | M54: 7.208 | N54: 1.103 | O54: 67.083
B55: Current Assets | J55: =+SUM(J51:J54) -> 193.541 | K55: =+SUM(K51:K54) -> 190.35 | L55: =+SUM(L51:L54) -> 181.587 | M55: =+SUM(M51:M54) -> 202.554 | N55: =+SUM(N51:N54) -> 258.82 | O55: =+SUM(O51:O54) -> 309.686 | P55: =+SUM(P51:P54) -> 0
B56: Prepaid Expenses | J56: 0 | K56: 0 | L56: =0.755+0.088 -> 0.843 | M56: =1.327+0.124 -> 1.451 | N56: 2.032 | O56: 1.021
B57: Total Assets | J57: =+J50+J55+J56 -> 328.627 | K57: =+K50+K55+K56 -> 331.959 | L57: =+L50+L55+L56 -> 307.878 | M57: =+M50+M55+M56 -> 325.633 | N57: =+N50+N55+N56 -> 382.773 | O57: =+O50+O55+O56 -> 433.342
B58: Equity | J58: 169.456 | K58: 171.197 | L58: 175.861 | M58: 193.049 | N58: 205.255 | O58: 232.178
B59: Pension Liabilties | J59: 1.069 | K59: 0.758 | L59: 0.868 | M59: 0.975 | N59: 1.105 | O59: 1.28
B60: Tax Provisions | J60: 1.983 | K60: 2.655 | L60: 4.377 | M60: 4.065 | N60: 4.017 | O60: 9.107
B61: Other Provisions | J61: 2.628 | K61: 2.917 | L61: 39.374 | M61: 39.802 | N61: 43.656 | O61: 52.615
B62: Debt | J62: =23.704+18.509+2.702 -> 44.915 | K62: =16.83+38.868+2.464 -> 58.162 | L62: 28.79 | M62: 14.049 | N62: 42.52 | O62: 20.842
B63: Account Payables | J63: 92.646 | K63: 84.104 | L63: 50.866 | M63: 64.894 | N63: 78.052 | O63: 106.184
B64: Other Liabilties | J64: =0.312+11.749 -> 12.061 | K64: =9.08+0.767 -> 9.847 | L64: 7.742 | M64: 8.569 | N64: 7.694 | O64: 10.337
B65: Defered Taxes | J65: 3.869 | K65: 2.319 | L65: 0 | M65: 0.23 | N65: 0.474 | O65: 0.799
B66: Total Liabilities | H66: =+SUM(H59:H65) -> 0 | J66: =+SUM(J59:J65) -> 159.171 | K66: =+SUM(K59:K65) -> 160.762 | L66: =+SUM(L59:L65) -> 132.017 | M66: =+SUM(M59:M65) -> 132.584 | N66: =+SUM(N59:N65) -> 177.518 | O66: =+SUM(O59:O65) -> 201.164
B67: Liabilities & Equity | J67: =+J66+J58 -> 328.627 | K67: =+K66+K58 -> 331.959 | L67: =+L66+L58 -> 307.878 | M67: =+M66+M58 -> 325.633 | N67: =+N66+N58 -> 382.773 | O67: =+O66+O58 -> 433.342 | P67: =+P66+P58 -> 0
A69: x | B69: Cashflow Statement
B70: Net Income | J70: =+J30 -> 19.983 | K70: =+K30 -> 12.592 | L70: =+L30 -> 25.084 | M70: =+M30 -> 28.634 | N70: =+N30 -> 24.304 | O70: =+O30 -> 34.05
B71: Taxes | J71: =+J29 -> 9.368 | K71: =+K29 -> 3.702 | L71: 11.219 | M71: 9.122 | N71: 9.19 | O71: 13.022
B72: D&A | J72: 16.538 | K72: 18.752 | L72: 18.495 | M72: 18.446 | N72: 20.322 | O72: 20.479
B73: Sale of Current Assets | J73: -0.26 | K73: -0.024 | L73: -0.084 | M73: -0.021 | N73: -0.04 | O73: -0.042
B74: Interest Income | J74: -0.055 | K74: -0.18 | L74: -0.051 | M74: -0.023 | N74: -0.044 | O74: -0.729
B75: Interest Expense | J75: 0.792 | K75: 0.635 | L75: 0.563 | M75: 0.438 | N75: 0.656 | O75: 1.126
B76: Interest Received | J76: -0.506 | K76: 0.119 | L76: 0 | M76: 0 | N76: -0.586 | O76: -1.115
B77: Interest Paid | J77: 0.004 | K77: -0.524 | L77: -0.52 | M77: -0.291 | N77: 0 | O77: 0.624
B78: Taxes Paid | J78: -11.308 | K78: -11.878 | L78: -10.15 | M78: -11.417 | N78: -9.465 | O78: -9.119
B79: Taxes Received | J79: 0 | K79: 2.561 | L79: 5.082 | M79: 0.078 | N79: 2.568 | O79: 0
B80: Change in non-current Provisions | J80: 0.205 | K80: -0.021 | L80: 0.593 | M80: 0.253 | N80: 0.008 | O80: 0.814
B81: Change in current Provisions | J81: -0.78 | K81: 0.456 | L81: 0.937 | M81: -0.696 | N81: 0.117 | O81: -0.292
B82: Other Income | J82: -8.384 | K82: 2.06 | L82: 2.601 | M82: -0.467 | N82: -0.08 | O82: 1.743
B83: Change in other operating Assets | J83: -2.349 | K83: 3.42 | L83: 0 | M83: 0 | N83: -1.973 | O83: -0.41
... B86: Change in Accounts Payables | J86: 16.766 | K86: -5.98 | L86: -4.329 | M86: 14.029 | N86: 8.662 | O86: 28.132
B87: Change in Working Capital | J87: =+J85+J86 -> 18.15 | K87: =+K85+K86 -> 1.517 | L87: =+L85+L86 -> 1.073 | M87: =+M85+M86 -> -14.116 | N87: =+N85+N86 -> -48.46 | O87: =+O85+O86 -> 46.708 | P87: =+P85+P86 -> 0
B88: CFFO | J88: =+SUM(J70:J84)+J87 -> 47.22 | K88: =+SUM(K70:K84)+K87 -> 25.848 | L88: =+SUM(L70:L84)+L87 -> 54.842 | M88: =+SUM(M70:M84)+M87 -> 29.94 | N88: =+SUM(N70:N84)+N87 -> -2.146 | O88: =+SUM(O70:O84)+O87 -> 117.783 | P88: =+SUM(P70:P84)+P87 -> 0
B89: Sale of PP&E | J89: 0.016 | K89: 0.031 | L89: 0.01 | M89: =0.005+0.808 -> 0.813 | N89: 0 | O89: 0.005
B90: Subsidies | J90: 0 | K90: 0 | L90: 0 | M90: 0.106 | N90: 0 | O90: 0.187
B91: Investments in PP&E | J91: -35.448 | K91: -22.284 | L91: -13.896 | M91: -12.999 | N91: -19.559 | O91: -17.767
B92: Investments in Intangibles | J92: -1.877 | K92: =-1.992-0.04 -> -2.032 | L92: =-1.238-0.01 -> -1.248 | M92: =-1.974-0.028 -> -2.002 | N92: -1.572 | O92: -1.79
B93: CFFI | J93: =+SUM(J89:J92) -> -37.309 | K93: =+SUM(K89:K92) -> -24.285 | L93: =+SUM(L89:L92) -> -15.134 | M93: =+SUM(M89:M92) -> -14.082 | N93: =+SUM(N89:N92) -> -21.131 | O93: =+SUM(O89:O92) -> -19.365 | P93: =+SUM(P89:P92) -> 0
B94: Stock Repurchaes | J94: -3.367 | K94: -1.789 | L94: -0.996 | M94: -3.388 | N94: -2.213 | O94: -1.595
B95: Issuance of Stock | J95: 3.307 | K95: 1.224 | L95: 1.632 | M95: 3.388 | N95: 1.775 | O95: 1.656
B96: Dividends | J96: -10.876 | K96: -10.885 | L96: -10.867 | M96: -10.9 | N96: -10.891 | O96: -10.884
B97: Issuance of Debt | J97: 5.15 | K97: 0 | L97: 0 | M97: 0 | N97: 20 | O97: 0
B98: Redemption of Debt | J98: -7.502 | K98: -7.258 | L98: -6.873 | M98: -6.412 | N98: -4.581 | O98: -4.995
B99: Increase in other financial liabilties | J99: 0 | K99: 20.743 | L99: -20.035 | M99: -8.33 | N99: 13.052 | O99: -16.682
B100: CFFI | J100: =+SUM(J94:J99) -> -13.288 | K100: =+SUM(K94:K99) -> 2.035 | L100: =+SUM(L94:L99) -> -37.139 | M100: =+SUM(M94:M99) -> -25.642 | N100: =+SUM(N94:N99) -> 17.142 | O100: =+SUM(O94:O99) -> -32.5 | P100: =+SUM(P94:P99) -> 0
B101: Currency Exchange Rate Effect | J101: -0.156 | K101: 0.023 | L101: -0.217 | M101: -0.026 | N101: -0.003 | O101: 0.062
B102: Change in Cash | J102: =+J88+J93+J100+J101 -> -3.533 | K102: =+K88+K93+K100+K101 -> 3.621 | L102: =+L88+L93+L100+L101 -> 2.352 | M102: =+M88+M93+M100+M101 -> -9.81 | N102: =+N88+N93+N100+N101 -> -6.138 | O102: =+O88+O93+O100+O101 -> 65.98 | P102: =+P88+P93+P100+P101 -> 0
B103: Cash BOP | J103: =+J104-J102 -> 14.578 | K103: =+K104-K102 -> 11.045 | L103: =+L104-L102 -> 14.666 | M103: =+M104-M102 -> 17.018 | N103: =+N104-N102 -> 7.241 | O103: 1.103
B104: Cash EOP | J104: =+K103 -> 11.045 | K104: 14.666 | L104: =+M103 -> 17.018 | M104: 7.208 | N104: =+O103 -> 1.103 | O104: =+O102+O103 -> 67.083

Sheet BC
A1: Main
C2: H122 | D2: H222 | E2: H123 | F2: H223 | G2: H124 | H2: H224 | J2: FY18 | K2: FY19 | L2: FY20 | M2: FY21 | N2: FY22 | O2: FY23 | P2: FY24 | Q2: FY25 | R2: FY26 | S2: FY27 | T2: FY28 | U2: FY29
B3: TAM Tiefkühlgerichte DE | J3: =+K3*(1-4%) -> 6597.7089 | K3: =+L3*(1-4%) -> 6872.6134 | L3: =+M3*(1-4%) -> 7158.9723 | M3: =+N3*(1-4%) -> 7457.2628 | N3: =+O3*(1-4%) -> 7767.9821 | O3: =+P3*(1-4%) -> 8091.648 | P3: =+Q3*(1-4%) -> 8428.8 | Q3: 8780 | R3: =+Q3*(1+4.2%) -> 9148.76 | S3: =+R3*(1+4.2%) -> 9533.0079 | T3: =+S3*(1+4.2%) -> 9933.3943 | U3: =+T3*(1+4.2%) -> 10350.597
B4: Marktanteil DE | J4: =+J11/J3 -> 0.043227127 | K4: =+K11/K3 -> 0.043622416 | L4: =+L11/L3 -> 0.04461632 | M4: =+M11/M3 -> 0.041649062 | N4: =+N11/N3 -> 0.044935737 | O4: =+O11/O3 -> 0.049662318 | P4: =+P11/P3 -> 0.047437447 | Q4: 0.048 | R4: 0.05 | S4: 0.055 | T4: 0.06 | U4: 0.06
B5: TAM Tiefkühlgerichte Europa | J5: =+K5*(1-4.5%) -> 65210.366 | K5: =+L5*(1-4.5%) -> 68283.106 | L5: =+M5*(1-4.5%) -> 71500.634 | M5: =+N5*(1-4.5%) -> 74869.774 | N5: =+O5*(1-4.5%) -> 78397.669 | O5: =+P5*(1-4.5%) -> 82091.8 | P5: 85960 | Q5: 104500 | R5: =+Q5*(1+6%) -> 110770 | S5: =+R5*(1+6%) -> 117416.2 | T5: =+S5*(1+6%) -> 124461.17 | U5: =+T5*(1+6%) -> 131928.84
B6: Marktanteil Europa | J6: =+J16/J5 -> 0.0078098626 | K6: =+K16/K5 -> 0.0076583658 | L6: =+L16/L5 -> 0.0077167008 | M6: =+M16/M5 -> 0.0070415733 | N6: =+N16/N5 -> 0.0073864058 | O6: =+O16/O5 -> 0.0077898158 | P6: =+P16/P5 -> 0.0074020777 | Q6: 0.008 | R6: 0.009 | S6: 0.01 | T6: 0.01 | U6: 0.01
B7: TAM EU excl. DE | J7: =+J5-J3 -> 58612.657 | K7: =+K5-K3 -> 61410.492 | L7: =+L5-L3 -> 64341.662 | M7: =+M5-M3 -> 67412.511 | N7: =+N5-N3 -> 70629.687 | O7: =+O5-O3 -> 74000.152 | P7: =+P5-P3 -> 77531.2 | Q7: =+Q5-Q3 -> 95720 | ... U7: =+U5-U3 -> 121578.25
B8: Marktanteil EU excl DE | J8: =+J12/J7 -> 0.0038234063 | K8: =+K12/K7 -> 0.0036329297 | L8: =+L12/L7 -> 0.0036110662 | M8: =+M12/M7 -> 0.0032132463 | N8: =+N12/N7 -> 0.0032566618 | O8: =+O12/O7 -> 0.0032112096 | P8: =+P12/P7 -> 0.0030496349 | Q8: 0.0035 | R8: 0.004 | S8: 0.0045 | T8: 0.005 | U8: 0.005
A10: x | B10: Income Statement
B11: Domestic | J11: 285.2 | K11: 299.8 | L11: 319.407 | M11: 310.588 | N11: 349.06 | O11: 401.85 | P11: =+O11*(1-0.5%) -> 399.84075 | Q11: =+Q3*Q4 -> 421.44 | R11: =+R3*R4 -> 457.438 | S11: =+S3*S4 -> 524.31544 | T11: =+T3*T4 -> 596.00366 | U11: =+U3*U4 -> 621.03581
B12: International | J12: 224.1 | K12: 223.1 | L12: 232.342 | M12: 216.613 | N12: 230.017 | O12: 237.63 | P12: =+O12*(1-0.5%) -> 236.44185 | Q12: =+Q7*Q8 -> 335.02 | R12: =+R7*R8 -> 406.48496 | S12: =+S7*S8 -> 485.47436 | T12: =+T7*T8 -> 572.63889 | U12: =+U7*U8 -> 607.89123
B13: Fish | J13: n.a | K13: n.a | L13: 253.763 | M13: 243.87 | N13: 272.501 | O13: 293.704 | P13: =46%*P16 -> 292.69 | Q13: =46%*Q16 -> 347.9716 | R13: =46%*R16 -> 397.40456 | S13: =46%*S16 -> 464.50331 | T13: =46%*T16 -> 537.57557 | U13: =46%*U16 -> 565.30644
B14: Gemüse&Obst | J14: n.a | K14: n.a | L14: 150.479 | M14: 136.833 | N14: 133.717 | O14: 141.058 | P14: =22%*P16 -> 139.98217 | Q14: =22%*Q16 -> 166.4212 | R14: =22%*R16 -> 190.06305 | S14: =22%*S16 -> 222.15376 | T14: =22%*T16 -> 257.10136 | U14: =22%*U16 -> 270.36395
B15: Fertiggerichte & Andere | J15: n.a | K15: n.a | L15: 147.507 | M15: 146.498 | N15: 172.859 | O15: 204.718 | P15: =32%*P16 -> 203.61043 | Q15: =32%*Q16 -> 242.0672 | R15: =32%*R16 -> 276.45535 | S15: =32%*S16 -> 323.13274 | T15: =32%*T16 -> 373.96561 | U15: =32%*U16 -> 393.25665
B16: Revenue | E16: 316.804 | G16: 315.941 | J16: 509.284 | K16: 522.937 | L16: 551.749 | M16: 527.201 | N16: 579.077 | O16: 639.48 | P16: =+SUM(P11:P12) -> 636.2826 | Q16: =+SUM(Q11:Q12) -> 756.46 | R16: =+SUM(R11:R12) -> 863.92296 | S16: =+SUM(S11:S12) -> 1009.7898 | T16: =+SUM(T11:T12) -> 1168.6425 | U16: =+SUM(U11:U12) -> 1228.927
B17: Other | E17: =-3.481+4.974 -> 1.493 | G17: =0.627+3.246 -> 3.873 | J17: =-5.613+9.315 -> 3.702 | K17: =1.432+0.056+7.396 -> 8.884 | L17: =4.384+0.128+9.323 -> 13.835 | M17: =11.669+8.953 -> 20.622 | N17: =-0.744+12.546 -> 11.802 | O17: =-4.836+16.501 -> 11.665 | P17: 11.7 | Q17: 11.7 | R17: 11.7 | S17: 11.7 | T17: 11.7 | U17: 11.7
B18: Operating Performance | C18: =+C16+C17 -> 0 | D18: =+D16+D17 -> 0 | E18: =+E16+E17 -> 318.297 | F18: =+F16+F17 -> 0 | G18: =+G16+G17 -> 319.814 | H18: =+H16+H17 -> 0 | J18: =+J16+J17 -> 512.986 | K18: =+K16+K17 -> 531.821 | L18: =+L16+L17 -> 565.584 | M18: =+M16+M17 -> 547.823 | N18: =+N16+N17 -> 590.879 | O18: =+O16+O17 -> 651.145 | P18: =+P16+P17 -> 647.9826 | Q18: =+Q16+Q17 -> 768.16 | ... U18: =+U16+U17 -> 1240.627
B19: COGS | E19: 184.017 | G19: 168.783 | J19: 300.273 | K19: 327.034 | L19: 332.104 | M19: 309.845 | N19: 346.109 | O19: 366.075 | P19: =+P18-P20 -> 348.92978 | Q19: =+Q18-Q20 -> 412.6238 | R19: =+R18-R20 -> 469.57917 | S19: =+S18-S20 -> 546.88859 | T19: =+T18-T20 -> 631.08055 | U19: =+U18-U20 -> 663.03133
B20: Gross Profit | C20: =+C18-C19 -> 0 | D20: =+D18-D19 -> 0 | E20: =+E18-E19 -> 134.28 | F20: =+F18-F19 -> 0 | G20: =+G18-G19 -> 151.031 | H20: =+H18-H19 -> 0 | J20: =+J18-J19 -> 212.713 | K20: =+K18-K19 -> 204.787 | L20: =+L18-L19 -> 233.48 | M20: =+M18-M19 -> 237.978 | N20: =+N18-N19 -> 244.77 | O20: =+O18-O19 -> 285.07 | P20: =+P16*P41 -> 299.05282 | Q20: =+Q16*Q41 -> 355.5362 | R20: =+R16*R41 -> 406.04379 | S20: =+S16*S41 -> 474.60121 | T20: =+T16*T41 -> 549.262 | U20: =+U16*U41 -> 577.59571
B21: Emplyoee Payroll | E21: 40.385 | G21: 46.203 | J21: 74.275 | K21: 75.722 | L21: 78.957 | M21: 79 | N21: 76.612 | O21: 84.084 | P21: =+(P20-P24)*35% -> 89.079564 | Q21: =+(Q20-Q24)*35% -> 104.58059 | R21: =+(R20-R24)*35% -> 117.92548 | S21: =+(S20-S24)*35% -> 136.06918 | T21: =+(T20-T24)*35% -> 155.42946 | U21: =+(U20-U24)*35% -> 163.4473
B22: D&A | E22: 10.353 | G22: 10.415 | J22: 16.538 | K22: 18.752 | L22: 18.495 | M22: 18.446 | N22: 20.322 | O22: 20.479 | P22: =+(P20-P24)*9% -> 22.906174 | Q22: =+(Q20-Q24)*9% -> 26.892153 | R22: =+(R20-R24)*9% -> 30.323696 | S22: =+(S20-S24)*9% -> 34.989217 | T22: =+(T20-T24)*9% -> 39.967575 | U22: =+(U20-U24)*9% -> 42.029305
B23: Other operating Expenses | E23: 61.095 | G23: 72.471 | J23: 91.861 | K23: 94.13 | L23: 98.943 | M23: 101.958 | N23: 113.312 | O23: 132.431 | P23: =+(P20-P24)*56% -> 142.5273 | Q23: =+(Q20-Q24)*56% -> 167.32895 | R23: =+(R20-R24)*56% -> 188.68077 | S23: =+(S20-S24)*56% -> 217.71068 | T23: =+(T20-T24)*56% -> 248.68713 | U23: =+(U20-U24)*56% -> 261.51567
B24: Operating Income | C24: =+C20-SUM(C21:C23) -> 0 | D24: =+D20-SUM(D21:D23) -> 0 | E24: =+E20-SUM(E21:E23) -> 22.447 | F24: =+F20-SUM(F21:F23) -> 0 | G24: =+G20-SUM(G21:G23) -> 21.942 | H24: =+H20-SUM(H21:H23) -> 0 | J24: =+J20-SUM(J21:J23) -> 30.039 | K24: =+K20-SUM(K21:K23) -> 16.183 | L24: =+L20-SUM(L21:L23) -> 37.085 | M24: =+M20-SUM(M21:M23) -> 38.574 | N24: =+N20-SUM(N21:N23) -> 34.524 | O24: =+O20-SUM(O21:O23) -> 48.076 | P24: =+P16*P42 -> 44.539782 | Q24: =+Q16*Q42 -> 56.7345 | R24: =+R16*R42 -> 69.113837 | S24: =+S16*S42 -> 85.832133 | T24: =+T16*T42 -> 105.17783 | U24: =+U16*U42 -> 110.60343
B25: Interest Income | E25: 0.007 | G25: 1.054 | J25: 0.055 | K25: 0.18 | L25: 0.051 | M25: 0.023 | N25: 0.044 | O25: 0.728 | P25: 2.2 | Q25: 2.5 | R25: =+Q25*(1+3%) -> 2.575 | S25: =+R25*(1+3%) -> 2.65225 | T25: =+S25*(1+3%) -> 2.7318175 | U25: =+T25*(1+3%) -> 2.813772
B26: Interes Expense | E26: 0.632 | G26: 0.52 | J26: 0.792 | K26: 0.635 | L26: 0.563 | M26: 0.438 | N26: 0.656 | O26: 1.125 | P26: 0.5 | Q26: 0.5 | R26: 0.5 | S26: 0.5 | T26: 0.5 | U26: 0.5
B27: Other | J27: 0.049 | K27: 0.566 | L27: 0.115 | M27: 0 | N27: 0 | O27: -0.132 | P27: 0 | Q27: 0 | R27: 0 | S27: 0 | T27: 0 | U27: 0
B28: Pretax Income | C28: =+C24+C25-C26+C27 -> 0 | D28: =+D24+D25-D26+D27 -> 0 | E28: =+E24+E25-E26+E27 -> 21.822 | F28: =+F24+F25-F26+F27 -> 0 | G28: =+G24+G25-G26+G27 -> 22.476 | H28: =+H24+H25-H26+H27 -> 0 | J28: =+J24+J25-J26+J27 -> 29.351 | K28: =+K24+K25-K26+K27 -> 16.294 | L28: =+L24+L25-L26+L27 -> 36.688 | M28: =+M24+M25-M26+M27 -> 38.159 | N28: =+N24+N25-N26+N27 -> 33.912 | O28: =+O24+O25-O26+O27 -> 47.547 | P28: =+P24+P25-P26+P27 -> 46.239782 | Q28: =+Q24+Q25-Q26+Q27 -> 58.7345 | ... U28: =+U24+U25-U26+U27 -> 112.91721
B29: Tax Expense | E29: =6.054+0.273 -> 6.327 | G29: =6.671+0.305 -> 6.976 | J29: =-0.482+9.85 -> 9.368 | K29: =-0.045+3.747 -> 3.702 | L29: =11.219+0.385 -> 11.604 | M29: =9.122+0.403 -> 9.525 | N29: =9.19+0.418 -> 9.608 | O29: =13.022+0.475 -> 13.497 | P29: =+P28*P43 -> 12.947139 | Q29: =+Q28*Q43 -> 16.44566 | R29: =+R28*R43 -> 19.932874 | S29: =+S28*S43 -> 24.635627 | T29: =+T28*T43 -> 30.074701 | U29: =+U28*U43 -> 31.616817
B30: Net Income | C30: =+C28-C29 -> 0 | D30: =+D28-D29 -> 0 | E30: =+E28-E29 -> 15.495 | F30: =+F28-F29 -> 0 | G30: =+G28-G29 -> 15.5 | H30: =+H28-H29 -> 0 | J30: =+J28-J29 -> 19.983 | K30: =+K28-K29 -> 12.592 | L30: =+L28-L29 -> 25.084 | M30: =+M28-M29 -> 28.634 | N30: =+N28-N29 -> 24.304 | O30: =+O28-O29 -> 34.05 | P30: =+P28-P29 -> 33.292643 | Q30: =+Q28-Q29 -> 42.28884 | ... U30: =+U28-U29 -> 81.300388
B32: EPS | J32: =+J30/J33 -> 2.9330691 | K32: =+K30/K33 -> 1.8482313 | L32: =+L30/L33 -> 3.6817848 | M32: =+M30/M33 -> 4.2028475 | N32: =+N30/N33 -> 3.5672978 | O32: =+O30/O33 -> 4.9977983 | P32: =+P30/P33 -> 4.8866348 | Q32: =+Q30/Q33 -> 6.2070806 | ... U32: =+U30/U33 -> 11.933126
B33: Shares | J33: 6.813 | K33: 6.813 | L33: 6.813 | M33: 6.813 | N33: 6.813 | O33: 6.813 | P33: 6.813 | Q33: 6.813 | R33: 6.813 | S33: 6.813 | T33: 6.813 | U33: 6.813
B35: Domestic Growth | J35: n.a | K35: =+K11/J11-1 -> 0.051192146 | L35: =+L11/K11-1 -> 0.065400267 | M35: =+M11/L11-1 -> -0.027610541 | N35: =+N11/M11-1 -> 0.12386828 | O35: =+O11/N11-1 -> 0.15123474 | P35: =+P11/O11-1 -> -0.005 | Q35: =+Q11/P11-1 -> 0.054019632 | R35: =+R11/Q11-1 -> 0.085416667 | ... U35: =+U11/T11-1 -> 0.042
B36: International Growth | J36: n.a | K36: =+K12/J12-1 -> -0.0044622936 | L36: =+L12/K12-1 -> 0.04142537 | M36: =+M12/L12-1 -> -0.067697618 | N36: =+N12/M12-1 -> 0.061879943 | O36: =+O12/N12-1 -> 0.033097554 | P36: =+P12/O12-1 -> -0.005 | Q36: =+Q12/P12-1 -> 0.41692344 | R36: =+R12/Q12-1 -> 0.2133155 | ... U36: =+U12/T12-1 -> 0.061561203
B37: Fisch Growth | J37: n.a | K37: n.a | L37: n.a | M37: =+M13/L13-1 -> -0.038985195 | N37: =+N13/M13-1 -> 0.11740271 | O37: =+O13/N13-1 -> 0.077808889 | P37: =+P13/O13-1 -> -0.0034524692 | Q37: =+Q13/P13-1 -> 0.18887425 | R37: =+R13/Q13-1 -> 0.14206033 | S37: =+S13/R13-1 -> 0.16884242 | T37: =+T13/S13-1 -> 0.15731268 | U37: =+U13/T13-1 -> 0.051585057
B38: Gemüse&Obst Growth | J38: n.a | K38: n.a | L38: n.a | M38: =+M14/L14-1 -> -0.09068375 | N38: =+N14/M14-1 -> -0.022772284 | O38: =+O14/N14-1 -> 0.054899527 | P38: =+P14/O14-1 -> -0.0076268485 | Q38: =+Q14/P14-1 -> 0.18887425 | R38: =+R14/Q14-1 -> 0.14206033 | S38: =+S14/R14-1 -> 0.16884242 | T38: =+T14/S14-1 -> 0.15731268 | U38: =+U14/T14-1 -> 0.051585057
B39: Andere Gerichte Growth | J39: n.a | K39: n.a | L39: n.a | M39: =+M15/L15-1 -> -0.0068403533 | N39: =+N15/M15-1 -> 0.17994102 | O39: =+O15/N15-1 -> 0.18430628 | P39: =+P15/O15-1 -> -0.0054102131 | Q39: =+Q15/P15-1 -> 0.18887425 | R39: =+R15/Q15-1 -> 0.14206033 | S39: =+S15/R15-1 -> 0.16884242 | T39: =+T15/S15-1 -> 0.15731268 | U39: =+U15/T15-1 -> 0.051585057
B40: Revenue Growth | G40: =+G16/E16-1 -> -0.0027240818 | J40: n.a | K40: =+K16/J16-1 -> 0.026808225 | L40: =+L16/K16-1 -> 0.055096503 | M40: =+M16/L16-1 -> -0.044491245 | N40: =+N16/M16-1 -> 0.098398903 | O40: =+O16/N16-1 -> 0.1043091 | P40: =+P16/O16-1 -> -0.005 | Q40: =+Q16/P16-1 -> 0.18887425 | R40: =+R16/Q16-1 -> 0.14206033 | ... U40: =+U16/T16-1 -> 0.051585057
B41: Gross Margin | C41: =+C20/C18 -> #DIV/0! | D41: =+D20/D18 -> #DIV/0! | E41: =+E20/E18 -> 0.42187014 | F41: =+F20/F18 -> #DIV/0! | G41: =+G20/G18 -> 0.47224637 | H41: =+H20/H18 -> #DIV/0! | J41: =+J20/J18 -> 0.41465654 | K41: =+K20/K18 -> 0.38506753 | L41: =+L20/L18 -> 0.41281224 | M41: =+M20/M18 -> 0.43440673 | N41: =+N20/N18 -> 0.41424725 | O41: =+O20/O18 -> 0.43779803 | P41: 0.47 | Q41: 0.47 | R41: 0.47 | S41: 0.47 | T41: 0.47 | U41: 0.47
B42: Operating Margin | C42: =+C24/C18 -> #DIV/0! | D42: =+D24/D18 -> #DIV/0! | E42: =+E24/E18 -> 0.070522185 | F42: =+F24/F18 -> #DIV/0! | G42: =+G24/G18 -> 0.068608629 | H42: =+H24/H18 -> #DIV/0! | J42: =+J24/J18 -> 0.058557154 | K42: =+K24/K18 -> 0.030429411 | L42: =+L24/L18 -> 0.065569394 | M42: =+M24/M18 -> 0.070413254 | N42: =+N24/N18 -> 0.058428206 | O42: =+O24/O18 -> 0.073833017 | P42: 0.07 | Q42: 0.075 | R42: 0.08 | S42: 0.085 | T42: 0.09 | U42: 0.09
B43: Tax Rate | C43: =+C29/C28 -> #DIV/0! | D43: =+D29/D28 -> #DIV/0! | E43: =+E29/E28 -> 0.28993676 | F43: =+F29/F28 -> #DIV/0! | G43: =+G29/G28 -> 0.31037551 | H43: =+H29/H28 -> #DIV/0! | J43: =+J29/J28 -> 0.31917141 | K43: =+K29/K28 -> 0.2272002 | L43: =+L29/L28 -> 0.3162887 | M43: =+M29/M28 -> 0.24961346 | N43: =+N29/N28 -> 0.28332154 | O43: =+O29/O28 -> 0.28386649 | P43: 0.28 | Q43: 0.28 | R43: 0.28 | S43: 0.28 | T43: 0.28 | U43: 0.28
A45: x | B45: Balance Sheet
B46: Intangible Assets | J46: 9.935 | K46: 12.234 | L46: 11.334 | M46: 11.496 | N46: 9.632 | O46: 9.861
B47: PP&E | J47: 122.963 | K47: 126.421 | L47: 113.938 | M47: 109.946 | N47: 112.103 | O47: 112.738
B48: Financial Assets | J48: 0.125 | K48: 0.165 | L48: 0.176 | M48: 0.186 | N48: 0.186 | O48: 0.036
B49: Deferrd Tax Assets | J49: 2.063 | K49: 2.789 | L49: 0 | M49: 0 | N49: 0 | O49: 0
B50: Non-Current Assets | J50: =+SUM(J46:J49) -> 135.086 | K50: =+SUM(K46:K49) -> 141.609 | L50: =+SUM(L46:L49) -> 125.448 | M50: =+SUM(M46:M49) -> 121.628 | N50: =+SUM(N46:N49) -> 121.921 | O50: =+SUM(O46:O49) -> 122.635 | P50: =+SUM(P46:P48) -> 0
B51: Inventory | J51: 89.065 | K51: 88.729 | L51: 89.108 | M51: 120.026 | N51: 167.733 | O51: 147.754
B52: Accounts Receivable | J52: 82.2 | K52: 75.039 | L52: =69.349+0.001 -> 69.35 | M52: 66.677 | N52: 80.675 | O52: 81.717
B53: Other current Assets | J53: =9.297+0.659+1.275 -> 11.231 | K53: =5.878+0.719+5.319 -> 11.916 | L53: 6.111 | M53: 8.643 | N53: 9.309 | O53: 13.132
B54: Cash & Cash-Equivalents | J54: 11.045 | K54: 14.666 | L54: 17.018 | M54: 7.208 | N54: 1.103 | O54: 67.083
B55: Current Assets | J55: =+SUM(J51:J54) -> 193.541 | K55: =+SUM(K51:K54) -> 190.35 | L55: =+SUM(L51:L54) -> 181.587 | M55: =+SUM(M51:M54) -> 202.554 | N55: =+SUM(N51:N54) -> 258.82 | O55: =+SUM(O51:O54) -> 309.686 | P55: =+SUM(P51:P54) -> 0
B56: Prepaid Expenses | J56: 0 | K56: 0 | L56: =0.755+0.088 -> 0.843 | M56: =1.327+0.124 -> 1.451 | N56: 2.032 | O56: 1.021
B57: Total Assets | J57: =+J50+J55+J56 -> 328.627 | K57: =+K50+K55+K56 -> 331.959 | L57: =+L50+L55+L56 -> 307.878 | M57: =+M50+M55+M56 -> 325.633 | N57: =+N50+N55+N56 -> 382.773 | O57: =+O50+O55+O56 -> 433.342
B58: Equity | J58: 169.456 | K58: 171.197 | L58: 175.861 | M58: 193.049 | N58: 205.255 | O58: 232.178
B59: Pension Liabilties | J59: 1.069 | K59: 0.758 | L59: 0.868 | M59: 0.975 | N59: 1.105 | O59: 1.28
B60: Tax Provisions | J60: 1.983 | K60: 2.655 | L60: 4.377 | M60: 4.065 | N60: 4.017 | O60: 9.107
B61: Other Provisions | J61: 2.628 | K61: 2.917 | L61: 39.374 | M61: 39.802 | N61: 43.656 | O61: 52.615
B62: Debt | J62: =23.704+18.509+2.702 -> 44.915 | K62: =16.83+38.868+2.464 -> 58.162 | L62: 28.79 | M62: 14.049 | N62: 42.52 | O62: 20.842
B63: Account Payables | J63: 92.646 | K63: 84.104 | L63: 50.866 | M63: 64.894 | N63: 78.052 | O63: 106.184
B64: Other Liabilties | J64: =0.312+11.749 -> 12.061 | K64: =9.08+0.767 -> 9.847 | L64: 7.742 | M64: 8.569 | N64: 7.694 | O64: 10.337
B65: Defered Taxes | J65: 3.869 | K65: 2.319 | L65: 0 | M65: 0.23 | N65: 0.474 | O65: 0.799
B66: Total Liabilities | H66: =+SUM(H59:H65) -> 0 | J66: =+SUM(J59:J65) -> 159.171 | K66: =+SUM(K59:K65) -> 160.762 | L66: =+SUM(L59:L65) -> 132.017 | M66: =+SUM(M59:M65) -> 132.584 | N66: =+SUM(N59:N65) -> 177.518 | O66: =+SUM(O59:O65) -> 201.164
B67: Liabilities & Equity | J67: =+J66+J58 -> 328.627 | K67: =+K66+K58 -> 331.959 | L67: =+L66+L58 -> 307.878 | M67: =+M66+M58 -> 325.633 | N67: =+N66+N58 -> 382.773 | O67: =+O66+O58 -> 433.342 | P67: =+P66+P58 -> 0
A69: x | B69: Cashflow Statement
B70: Net Income | J70: =+J30 -> 19.983 | K70: =+K30 -> 12.592 | L70: =+L30 -> 25.084 | M70: =+M30 -> 28.634 | N70: =+N30 -> 24.304 | O70: =+O30 -> 34.05
B71: Taxes | J71: =+J29 -> 9.368 | K71: =+K29 -> 3.702 | L71: 11.219 | M71: 9.122 | N71: 9.19 | O71: 13.022
B72: D&A | J72: 16.538 | K72: 18.752 | L72: 18.495 | M72: 18.446 | N72: 20.322 | O72: 20.479
B73: Sale of Current Assets | J73: -0.26 | K73: -0.024 | L73: -0.084 | M73: -0.021 | N73: -0.04 | O73: -0.042
B74: Interest Income | J74: -0.055 | K74: -0.18 | L74: -0.051 | M74: -0.023 | N74: -0.044 | O74: -0.729
B75: Interest Expense | J75: 0.792 | K75: 0.635 | L75: 0.563 | M75: 0.438 | N75: 0.656 | O75: 1.126
B76: Interest Received | J76: -0.506 | K76: 0.119 | L76: 0 | M76: 0 | N76: -0.586 | O76: -1.115
B77: Interest Paid | J77: 0.004 | K77: -0.524 | L77: -0.52 | M77: -0.291 | N77: 0 | O77: 0.624
B78: Taxes Paid | J78: -11.308 | K78: -11.878 | L78: -10.15 | M78: -11.417 | N78: -9.465 | O78: -9.119
B79: Taxes Received | J79: 0 | K79: 2.561 | L79: 5.082 | M79: 0.078 | N79: 2.568 | O79: 0
B80: Change in non-current Provisions | J80: 0.205 | K80: -0.021 | L80: 0.593 | M80: 0.253 | N80: 0.008 | O80: 0.814
B81: Change in current Provisions | J81: -0.78 | K81: 0.456 | L81: 0.937 | M81: -0.696 | N81: 0.117 | O81: -0.292
B82: Other Income | J82: -8.384 | K82: 2.06 | L82: 2.601 | M82: -0.467 | N82: -0.08 | O82: 1.743
B83: Change in other operating Assets | J83: -2.349 | K83: 3.42 | L83: 0 | M83: 0 | N83: -1.973 | O83: -0.41
... B86: Change in Accounts Payables | J86: 16.766 | K86: -5.98 | L86: -4.329 | M86: 14.029 | N86: 8.662 | O86: 28.132
B87: Change in Working Capital | J87: =+J85+J86 -> 18.15 | K87: =+K85+K86 -> 1.517 | L87: =+L85+L86 -> 1.073 | M87: =+M85+M86 -> -14.116 | N87: =+N85+N86 -> -48.46 | O87: =+O85+O86 -> 46.708 | P87: =+P85+P86 -> 0
B88: CFFO | J88: =+SUM(J70:J84)+J87 -> 47.22 | K88: =+SUM(K70:K84)+K87 -> 25.848 | L88: =+SUM(L70:L84)+L87 -> 54.842 | M88: =+SUM(M70:M84)+M87 -> 29.94 | N88: =+SUM(N70:N84)+N87 -> -2.146 | O88: =+SUM(O70:O84)+O87 -> 117.783 | P88: =+SUM(P70:P84)+P87 -> 0
B89: Sale of PP&E | J89: 0.016 | K89: 0.031 | L89: 0.01 | M89: =0.005+0.808 -> 0.813 | N89: 0 | O89: 0.005
B90: Subsidies | J90: 0 | K90: 0 | L90: 0 | M90: 0.106 | N90: 0 | O90: 0.187
B91: Investments in PP&E | J91: -35.448 | K91: -22.284 | L91: -13.896 | M91: -12.999 | N91: -19.559 | O91: -17.767
B92: Investments in Intangibles | J92: -1.877 | K92: =-1.992-0.04 -> -2.032 | L92: =-1.238-0.01 -> -1.248 | M92: =-1.974-0.028 -> -2.002 | N92: -1.572 | O92: -1.79
B93: CFFI | J93: =+SUM(J89:J92) -> -37.309 | K93: =+SUM(K89:K92) -> -24.285 | L93: =+SUM(L89:L92) -> -15.134 | M93: =+SUM(M89:M92) -> -14.082 | N93: =+SUM(N89:N92) -> -21.131 | O93: =+SUM(O89:O92) -> -19.365 | P93: =+SUM(P89:P92) -> 0
B94: Stock Repurchaes | J94: -3.367 | K94: -1.789 | L94: -0.996 | M94: -3.388 | N94: -2.213 | O94: -1.595
B95: Issuance of Stock | J95: 3.307 | K95: 1.224 | L95: 1.632 | M95: 3.388 | N95: 1.775 | O95: 1.656
B96: Dividends | J96: -10.876 | K96: -10.885 | L96: -10.867 | M96: -10.9 | N96: -10.891 | O96: -10.884
B97: Issuance of Debt | J97: 5.15 | K97: 0 | L97: 0 | M97: 0 | N97: 20 | O97: 0
B98: Redemption of Debt | J98: -7.502 | K98: -7.258 | L98: -6.873 | M98: -6.412 | N98: -4.581 | O98: -4.995
B99: Increase in other financial liabilties | J99: 0 | K99: 20.743 | L99: -20.035 | M99: -8.33 | N99: 13.052 | O99: -16.682
B100: CFFI | J100: =+SUM(J94:J99) -> -13.288 | K100: =+SUM(K94:K99) -> 2.035 | L100: =+SUM(L94:L99) -> -37.139 | M100: =+SUM(M94:M99) -> -25.642 | N100: =+SUM(N94:N99) -> 17.142 | O100: =+SUM(O94:O99) -> -32.5 | P100: =+SUM(P94:P99) -> 0
B101: Currency Exchange Rate Effect | J101: -0.156 | K101: 0.023 | L101: -0.217 | M101: -0.026 | N101: -0.003 | O101: 0.062
B102: Change in Cash | J102: =+J88+J93+J100+J101 -> -3.533 | K102: =+K88+K93+K100+K101 -> 3.621 | L102: =+L88+L93+L100+L101 -> 2.352 | M102: =+M88+M93+M100+M101 -> -9.81 | N102: =+N88+N93+N100+N101 -> -6.138 | O102: =+O88+O93+O100+O101 -> 65.98 | P102: =+P88+P93+P100+P101 -> 0
B103: Cash BOP | J103: =+J104-J102 -> 14.578 | K103: =+K104-K102 -> 11.045 | L103: =+L104-L102 -> 14.666 | M103: =+M104-M102 -> 17.018 | N103: =+N104-N102 -> 7.241 | O103: 1.103
B104: Cash EOP | J104: =+K103 -> 11.045 | K104: 14.666 | L104: =+M103 -> 17.018 | M104: 7.208 | N104: =+O103 -> 1.103 | O104: =+O102+O103 -> 67.083

Sheet Ratios
A1: Main
B2: Ratios | C2: 18 | D2: =+C2+1 -> 19 | E2: =+D2+1 -> 20 | F2: =+E2+1 -> 21 | G2: =+F2+1 -> 22 | H2: =+G2+1 -> 23 | I2: FY24
B3: Price | C3: 77.5 | D3: 59.9 | E3: 55.5 | F3: 74.4 | G3: 81.2 | H3: 59.2 | I3: 74.5 | J3: 95
B4: Shares o/s | C4: =+Model!N33 -> 6.813 | D4: =+Model!O33 -> 6.813 | E4: =+Model!P33 -> 6.813 | F4: =+Model!Q33 -> 6.813 | G4: =+Model!R33 -> 6.813 | H4: =+Model!S33 -> 6.813 | I4: 6.812598 | J4: 6.812598
B5: Market Cap | C5: =+C3*C4 -> 528.0075 | D5: =+D3*D4 -> 408.0987 | E5: =+E3*E4 -> 378.1215 | F5: =+F3*F4 -> 506.8872 | G5: =+G3*G4 -> 553.2156 | H5: =+H3*H4 -> 403.3296 | I5: =+I3*I4 -> 507.53855 | J5: =+J3*J4 -> 647.19681
B6: Net Debt | C6: =+Model!N62-Model!N54 -> 33.87 | D6: =+Model!O62-Model!O54 -> 43.496 | E6: =+Model!P62-Model!P54 -> 11.772 | F6: =+Model!Q62-Model!Q54 -> 6.841 | G6: =+Model!R62-Model!R54 -> 41.417 | H6: =+Model!S62-Model!S54 -> -46.241 | I6: =+Model!T62-Model!T54 -> -94.68 | J6: =+Model!U62-Model!U54 -> -104.78
B7: EV | C7: =+C5+C6 -> 561.8775 | D7: =+D5+D6 -> 451.5947 | E7: =+E5+E6 -> 389.8935 | F7: =+F5+F6 -> 513.7282 | G7: =+G5+G6 -> 594.6326 | H7: =+H5+H6 -> 357.0886 | I7: =+I5+I6 -> 412.85855 | J7: =+J5+J6 -> 542.41681
A9: x | B9: Value Driver
B10: Capital Emloyed | C10: =+Model!N50+Model!N52+Model!N53-Model!N63 -> 135.871 | D10: =+Model!O50+Model!O52+Model!O53-Model!O63 -> 144.46 | E10: =+Model!P50+Model!P52+Model!P53-Model!P63 -> 150.043 | F10: =+Model!Q50+Model!Q52+Model!Q53-Model!Q63 -> 132.054 | G10: =+Model!R50+Model!R52+Model!R53-Model!R63 -> 133.853 | H10: =+Model!S50+Model!S52+Model!S53-Model!S63 -> 111.3 | I10: =+Model!T50+Model!T52+Model!T53-Model!T63 -> 103.958 | J10: =+Model!U50+Model!U52+Model!U53-Model!U63 -> 92.384 | L10: =Long Term Assets + Working Capital (Exclusive of cash)-Accounts Payables
B11: Invested Capital | C11: =+Model!N47+Model!N51+Model!N52-Model!N63+Model!N46 -> 211.517 | D11: =+Model!O47+Model!O51+Model!O52-Model!O63+Model!O46 -> 218.319 | E11: =+Model!P47+Model!P51+Model!P52-Model!P63+Model!P46 -> 232.864 | F11: =+Model!Q47+Model!Q51+Model!Q52-Model!Q63+Model!Q46 -> 243.251 | G11: =+Model!R47+Model!R51+Model!R52-Model!R63+Model!R46 -> 292.091 | H11: =+Model!S47+Model!S51+Model!S52-Model!S63+Model!S46 -> 245.886 | I11: =+Model!T47+Model!T51+Model!T52-Model!T63+Model!T46 -> 239.438 | J11: =+Model!U47+Model!U51+Model!U52-Model!U63+Model!U46 -> 250.754 | L11: =Net Working Capital + PP&E + Other Net Operating Assets (net of Liabilties) + (Intangibles)
B12: Invested Capital (exl. Intangibles) | C12: =+Model!N47+Model!N51+Model!N52-Model!N63 -> 201.582 | D12: =+Model!O47+Model!O51+Model!O52-Model!O63 -> 206.085 | E12: =+Model!P47+Model!P51+Model!P52-Model!P63 -> 221.53 | F12: =+Model!Q47+Model!Q51+Model!Q52-Model!Q63 -> 231.755 | G12: =+Model!R47+Model!R51+Model!R52-Model!R63 -> 282.459 | H12: =+Model!S47+Model!S51+Model!S52-Model!S63 -> 236.025 | I12: =+Model!T47+Model!T51+Model!T52-Model!T63 -> 231.066 | J12: =+Model!U47+Model!U51+Model!U52-Model!U63 -> 243.324
B13: Total Funds Invested | C13: =+C12+Model!N54+Model!N49+Model!N48+Model!N56 -> 214.815 | D13: =+D12+Model!O54+Model!O49+Model!O48+Model!O56 -> 223.705 | E13: =+E12+Model!P54+Model!P49+Model!P48+Model!P56 -> 239.567 | F13: =+F12+Model!Q54+Model!Q49+Model!Q48+Model!Q56 -> 240.6 | G13: =+G12+Model!R54+Model!R49+Model!R48+Model!R56 -> 285.78 | H13: =+H12+Model!S54+Model!S49+Model!S48+Model!S56 -> 304.165 | I13: =+I12+Model!T54+Model!T49+Model!T48+Model!T56 -> 342.357 | J13: =+J12+Model!U54+Model!U49+Model!U48+Model!U56 -> 360.87 | L13: Invested Capital + Non-Operating Assets
B14: NOPAT | C14: =+(Model!N24+Model!N22)*(1-Model!N43) -> 31.710953 | D14: =+(Model!O24+Model!O22)*(1-Model!O43) -> 26.997761 | E14: =+(Model!P24+Model!P22)*(1-Model!P43) -> 38.000674 | F14: =+(Model!Q24+Model!Q22)*(1-Model!Q43) -> 42.787041 | G14: =+(Model!R24+Model!R22)*(1-Model!R43) -> 39.306947 | H14: =+(Model!S24+Model!S22)*(1-Model!S43) -> 49.094533 | I14: =+(Model!T24+Model!T22)*(1-Model!T43) -> 57.1104 | J14: =+(Model!U24+Model!U22)*(1-Model!U43) -> 50.88456 | L14: EBITA * (1-Marginal Tax Rate)
B15: Net Investment | D15: =+D13-C13 -> 8.89 | E15: =+E13-D13 -> 15.862 | F15: =+F13-E13 -> 1.033 | G15: =+G13-F13 -> 45.18 | H15: =+H13-G13 -> 18.385 | I15: =+I13-H13 -> 38.192 | J15: =+J13-I13 -> 18.513 | L15: =Invested Capital (t+1)-Invested Capital (t)
B16: FCF | D16: =+D14-D15 -> 18.107761 | E16: =+E14-E15 -> 22.138674 | F16: =+F14-F15 -> 41.754041 | G16: =+G14-G15 -> -5.8730531 | H16: =+H14-H15 -> 30.709533 | I16: =+I14-I15 -> 18.9184 | J16: =+J14-J15 -> 32.37156 | L16: =NOPAT + non-cash Expenses - Investments in Invested Capital
B17: Investment Rate | D17: =+D15/D14 -> 0.32928656 | E17: =+E15/E14 -> 0.41741365 | F17: =+F15/F14 -> 0.024142824 | G17: =+G15/G14 -> 1.1494151 | H17: =+H15/H14 -> 0.37448162 | I17: =+I15/I14 -> 0.66873984 | J17: =+J15/J14 -> 0.36382353 | L17: =Net Investment/NOPAT
B18: Economic Profit | L18: =Invested Capital *(ROIC-WACC)
A20: x | B20: Efficency-Ratios
B21: Capital Turnover | C21: =+Model!N16/Model!N57 -> 1.5497327 | D21: =+Model!O16/Model!O57 -> 1.575306 | E21: =+Model!P16/Model!P57 -> 1.7921027 | F21: =+Model!Q16/Model!Q57 -> 1.6190036 | G21: =+Model!R16/Model!R57 -> 1.512847 | H21: =+Model!S16/Model!S57 -> 1.4756936 | I21: =+Model!T16/Model!T57 -> 1.3852627 | J21: =+Model!U16/Model!U57 -> 1.3628107 | L21: =Revenue/Total Assets
B22: Return on Equity (ROE) | C22: =+Model!N30/Model!N58 -> 0.11792442 | D22: =+Model!O30/Model!O58 -> 0.073552691 | E22: =+Model!P30/Model!P58 -> 0.14263538 | F22: =+Model!Q30/Model!Q58 -> 0.14832504 | G22: =+Model!R30/Model!R58 -> 0.11840881 | H22: =+Model!S30/Model!S58 -> 0.14665472 | I22: =+Model!T30/Model!T58 -> 0.16278615 | J22: =+Model!U30/Model!U58 -> 0.13115747 | L22: =Net Income/Book Value of Equity
B23: Return on Capital Employed (ROCE) | C23: =+Model!N24/Ratios!C10 -> 0.22108471 | D23: =+Model!O24/Ratios!D10 -> 0.11202409 | E23: =+Model!P24/Ratios!E10 -> 0.24716248 | F23: =+Model!Q24/Ratios!F10 -> 0.29210777 | G23: =+Model!R24/Ratios!G10 -> 0.25792474 | H23: =+Model!S24/Ratios!H10 -> 0.43194969 | I23: =+Model!T24/Ratios!I10 -> 0.56670001 | J23: =+Model!U24/Ratios!J10 -> 0.54397948 | L23: =EBIT/Capital Employed
B24: Return on Capital Invested (ROIC) | C24: =+C14/C11 -> 0.14992154 | D24: =+D14/D11 -> 0.12366199 | E24: =+E14/E11 -> 0.16318827 | F24: =+F14/F11 -> 0.17589667 | G24: =+G14/G11 -> 0.13457089 | H24: =+H14/H11 -> 0.1996638 | I24: =+I14/I11 -> 0.23851853 | J24: =+J14/J11 -> 0.20292621 | L24: =NOPAT/Invested Capital
B25: ROIC without Intangibles | C25: =+C14/C12 -> 0.15731044 | D25: =+D14/D12 -> 0.13100304 | E25: =+E14/E12 -> 0.17153737 | F25: =+F14/F12 -> 0.18462187 | G25: =+G14/G12 -> 0.13915983 | H25: =+H14/H12 -> 0.20800565 | I25: =+I14/I12 -> 0.24716055 | J25: =+J14/J12 -> 0.20912265 | L25: =NOPAT/(Invested Capital exclusive of Intangibles)
B26: Decomposed ROIC | L26: = ROIC = (1-operating cash tax)* (EBITA/Revenues) * (Revenue/Invested Capital)
B28: Retention Rate | L28: =1 - Dividends/Net Income
B29: Reinvestment Rate | L29: =Net CapEx + Change in WC / EBIT * (1-t)
B30: Epected Growth in Net Income | L30: =ROE * Retention Rate
B31: Expected Growth in NOPAT | L31: =ROIC * Reinvestment Rate
A33: x | B33: Finacial Stability Ratios
B34: Equity/Debt Ratio | L34: =Book Value of Equtiy/Book Value of Debt
B35: Gearing | L35: =(Debt - Cash (Net Debt))/Book Value of Equity
B36: Interest Coverage Ratio | L36: =EBIT/Interest Expenses
B37: Net Debt / EBITDA | L37: =Net Debt/EBITDA
B38: Cash Burn Rate | L38: =Book Value of Equity/Absolute value of Loss
A40: x | B40: WC-Managment Ratios
B41: Debitor-Duration | C41: =+Model!N52/Model!N16*360 -> 58.105104 | D41: =+Model!O52/Model!O16*360 -> 51.658307 | E41: =+Model!P52/Model!P16*360 -> 45.248836 | F41: =+Model!Q52/Model!Q16*360 -> 45.53049 | G41: =+Model!R52/Model!R16*360 -> 50.153952 | H41: =+Model!S52/Model!S16*360 -> 46.00319 | I41: =+Model!T52/Model!T16*360 -> 47.799929 | J41: =+Model!U52/Model!U16*360 -> 48.403344 | L41: =Accounts Receivables/Revenue*360
B42: Creditor-Duration | C42: =+Model!N63/Model!N16*360 -> 65.489118 | D42: =+Model!O63/Model!O16*360 -> 57.898829 | E42: =+Model!P63/Model!P16*360 -> 33.188569 | F42: =+Model!Q63/Model!Q16*360 -> 44.312966 | G42: =+Model!R63/Model!R16*360 -> 48.523288 | H42: =+Model!S63/Model!S16*360 -> 59.777069 | I42: =+Model!T63/Model!T16*360 -> 58.181528 | J42: =+Model!U63/Model!U16*360 -> 65.672746 | L42: =Accounts Payable/Revenue*360
B43: Inventory Intensity | C43: =+Model!N51/Model!N57 -> 0.27102155 | D43: =+Model!O51/Model!O57 -> 0.26728903 | E43: =+Model!P51/Model!P57 -> 0.28942633 | F43: =+Model!Q51/Model!Q57 -> 0.36859286 | G43: =+Model!R51/Model!R57 -> 0.43820489 | H43: =+Model!S51/Model!S57 -> 0.34096395 | I43: =+Model!T51/Model!T57 -> 0.30887538 | J43: =+Model!U51/Model!U57 -> 0.331687 | L43: =Inventory/Balance Sheet Total
B44: Invetory Turnover | C44: =+Model!N19/Model!N51 -> 3.3713917 | D44: =+Model!O19/Model!O51 -> 3.6857623 | E44: =+Model!P19/Model!P51 -> 3.726983 | F44: =+Model!Q19/Model!Q51 -> 2.5814823 | G44: =+Model!R19/Model!R51 -> 2.063452 | H44: =+Model!S19/Model!S51 -> 2.4775979 | I44: =+Model!T19/Model!T51 -> 2.3209998 | J44: =+Model!U19/Model!U51 -> 2.1742918 | L44: =Cogs/Inventory
B45: Storage-Duration | C45: =360/C44 -> 106.78083 | D45: =360/D44 -> 97.673147 | E45: =360/E44 -> 96.592875 | F45: =360/F44 -> 139.45476 | G45: =360/G44 -> 174.46492 | H45: =360/H44 -> 145.30203 | I45: =360/I44 -> 155.10557 | J45: =360/J44 -> 165.57115 | L45: =360/Inventory Turnover
B46: Cash Conversion Cycle | C46: =+C41+C45-C42 -> 99.396816 | D46: =+D41+D45-D42 -> 91.432625 | E46: =+E41+E45-E42 -> 108.65314 | F46: =+F41+F45-F42 -> 140.67228 | G46: =+G41+G45-G42 -> 176.09559 | H46: =+H41+H45-H42 -> 131.52815 | I46: =+I41+I45-I42 -> 144.72397 | J46: =+J41+J45-J42 -> 148.30175 | L46: =Debitor Duration + Storage Duration - Creditor Duration
A48: x | B48: Multipliers
B49: Equitymultiples
B50: P/E Ratio | C50: =+C5/Model!N30 -> 26.422834 | D50: =+D5/Model!O30 -> 32.409363 | E50: =+E5/Model!P30 -> 15.074211 | F50: =+F5/Model!Q30 -> 17.702284 | G50: =+G5/Model!R30 -> 22.762327 | H50: =+H5/Model!S30 -> 11.845216 | I50: =+I5/Model!T30 -> 11.943489 | J50: =+J5/Model!U30 -> 17.480939 | L50: =Share Price/EPS
B51: PEG Ratio | C51: =+C50/((Model!S16/Model!R16-1)*100) -> 2.5331284 | D51: =+D50/((Model!T16/Model!S16-1)*100) -> -145.13403 | E51: =+E50/((Model!U16/Model!T16-1)*100) -> 2.211522 | F51: =+F50/((Model!V16/Model!U16-1)*100) -> 1.4885828 | G51: =+G50/((Model!W16/Model!V16-1)*100) -> 5.2474633 | H51: =+H50/((Model!X16/Model!W16-1)*100) -> 2.7286437 | I51: =+I50/((Model!Y16/Model!X16-1)*100) -> 2.7491977 | J51: =+J50/((Model!Z16/Model!Y16-1)*100) -> -0.17480939 | L51: =P/E Ratio / Growth
B52: P/B Ratio | C52: =+C5/Model!N58 -> 3.1158973 | D52: =+D5/Model!O58 -> 2.3837959 | E52: =+E5/Model!P58 -> 2.1501157 | F52: =+F5/Model!Q58 -> 2.6256919 | G52: =+G5/Model!R58 -> 2.69526 | H52: =+H5/Model!S58 -> 1.7371568 | I52: =+I5/Model!T58 -> 1.9442346 | J52: =+J5/Model!U58 -> 2.2927558 | L52: =Market Cap/Book Vakue of Equity
B53: P/TB Ratio | L53: =Market Cap / Tangible Book Value
B54: P/Cf Ratio | L54: =Share Price/Cashflow per share
B55: P/R Ratio | L55: =Share Price/Revenue per Share
B56: Entitymultiples
B57: EV/EBITDA | L57: =EV/EBITDA
B58: EV/EBIT | L58: =EV/EBIT
B59: EV/FCF | L59: =EV/FCF
B60: EV/Sales | L60: =EV/Revenue

Sheet DCF
A1: Main | B1: DCF
B2: Ticker | E2: NLM.F | G2: Share Price | J2: =+Main!H2 -> 101.5 | L2: Share Price | O2: =+Main!H2 -> 101.5
B3: Date | E3: 45838 | G3: Fair Share Price | J3: =V61 -> 97.407232 | L3: Scneario DCF Price | O3: =+J14+O14+T14 -> 97.911
B4: End of FY | E4: 46022 | G4: Implied Upside | J4: =J3/J2-1 -> -0.040322842 | L4: Implied Upside | O4: =O3/O2-1 -> -0.035359606
A6: x | B6: Assumptions
B8: Switches | G8: Conservative Case | L8: Base Case | Q8: Optimistic Case
B9: Assuptions | G9: Assuptions | I9: Year | J9: Metic | L9: Assuptions | N9: Year | O9: Metic | Q9: Assuptions | S9: Year | T9: Metic
B10: Revenue | E10: 2 | G10: Revenue | L10: Revenue | Q10: Revenue
B11: EBIT | E11: 2 | G11: EBIT | L11: EBIT | Q11: EBIT
B12: WACC | E12: 2 | G12: Implied Share Price | J12: 50.32 | L12: Implied Share Price | O12: 95.29 | Q12: Implied Share Price | T12: 211.44
B13: TGR | E13: 2 | G13: Probability | J13: 0.2 | L13: Probability | O13: 0.7 | Q13: Probability | T13: 0.1
B14: ROIC | E14: 2 | G14: Implied Share Price * p | J14: =+J12*J13 -> 10.064 | L14: Implied Share Price * p | O14: =+O12*O13 -> 66.703 | Q14: Implied Share Price * p | T14: =+T12*T13 -> 21.144
B16: Valuation
B17: WACC | E17: =CHOOSE(E12,J17,O17,T17) -> 0.08 | G17: WACC | J17: 0.09 | L17: WACC | O17: 0.08 | Q17: WACC | T17: 0.07
B18: TGR | E18: =CHOOSE(E13,J18,O18,T18) -> 0.03 | G18: TGR | J18: 0.007 | L18: TGR | O18: 0.03 | Q18: TGR | T18: 0.035
B19: RONIC | E19: =CHOOSE(E14,J19,O19,T19) -> 0.09 | G19: RONIC | J19: 0.09 | L19: RONIC | O19: 0.09 | Q19: RONIC | T19: 0.1
A23: x | B23: Model | G23: 18 | H23: =G23+1 -> 19 | I23: =H23+1 -> 20 | J23: =I23+1 -> 21 | K23: =J23+1 -> 22 | L23: =K23+1 -> 23 | M23: =L23+1 -> 24 | N23: =M23+1 -> 25 | O23: =N23+1 -> 26 | ... V23: =U23+1 -> 33
B24: Revenue | G24: =+Model!N16 -> 509.284 | H24: =+Model!O16 -> 522.937 | I24: =+Model!P16 -> 551.749 | J24: =+Model!Q16 -> 527.201 | K24: =+Model!R16 -> 579.077 | L24: =+Model!S16 -> 639.48 | M24: =L24*(1+M25) -> 638.052 | N24: =M24*(1+N25) -> 681.543 | O24: =N24*(1+O25) -> 762.59236 | P24: =O24*(1+P25) -> 795.67191 | Q24: =P24*(1+Q25) -> 830.21254 | R24: =Q24*(1+R25) -> 866.27991 | S24: =R24*(1+S25) -> 900.93111 | T24: =S24*(1+T25) -> 934.26556 | ... V24: =U24*(1+V25) -> 994.04921
B25: Growth (%) | H25: =H24/G24-1 -> 0.026808225 | I25: =I24/H24-1 -> 0.055096503 | J25: =J24/I24-1 -> -0.044491245 | K25: =K24/J24-1 -> 0.098398903 | L25: =L24/K24-1 -> 0.1043091 | M25: {=OFFSET(M25,$E$10,,)} -> -0.0022330644 | N25: {=OFFSET(N25,$E$10,,)} -> 0.068162156 | O25: {=OFFSET(O25,$E$10,,)} -> 0.11892038 | P25: {=OFFSET(P25,$E$10,,)} -> 0.043377773 | Q25: {=OFFSET(Q25,$E$10,,)} -> 0.043410636 | R25: {=OFFSET(R25,$E$10,,)} -> 0.043443542 | S25: {=OFFSET(S25,$E$10,,)} -> 0.04 | T25: {=OFFSET(T25,$E$10,,)} -> 0.037 | ... V25: {=OFFSET(V25,$E$10,,)} -> 0.03
B26: Conservative Case | M26: =+WC!P40 -> -0.005 | N26: =+WC!Q40 -> -0.078176898 | O26: =+WC!R40 -> -0.008078501 | P26: =+WC!S40 -> 0.0069207016 | Q26: =+WC!T40 -> 0.0068455189 | R26: =+WC!U40 -> 0.0067698134 | S26: 0.007 | T26: 0.007 | U26: 0.007 | V26: 0.007
B27: Base Case | M27: =+Model!T40 -> -0.0022330644 | N27: =+Model!U40 -> 0.068162156 | O27: =+Model!V40 -> 0.11892038 | P27: =+Model!W40 -> 0.043377773 | Q27: =+Model!X40 -> 0.043410636 | R27: =+Model!Y40 -> 0.043443542 | S27: 0.04 | T27: 0.037 | U27: 0.033 | V27: 0.03
B28: Optimisitic Case | M28: =+BC!P40 -> -0.005 | N28: =+BC!Q40 -> 0.18887425 | O28: =+BC!R40 -> 0.14206033 | P28: =+BC!S40 -> 0.16884242 | Q28: =+BC!T40 -> 0.15731268 | R28: =+BC!U40 -> 0.051585057 | S28: 0.045 | T28: 0.04 | U28: 0.035 | V28: 0.035
B30: EBIT | G30: =+Model!N24 -> 30.039 | H30: =+Model!O24 -> 16.183 | I30: =+Model!P24 -> 37.085 | J30: =+Model!Q24 -> 38.574 | K30: =+Model!R24 -> 34.524 | L30: =+Model!S24 -> 48.076 | M30: =M31*M24 -> 44.66364 | N30: =N31*N24 -> 47.70801 | O30: =O31*O24 -> 53.381465 | P30: =P31*P24 -> 55.697034 | Q30: =Q31*Q24 -> 58.114878 | R30: =R31*R24 -> 60.639594 | S30: =S31*S24 -> 63.065177 | T30: =T31*T24 -> 65.398589 | ... V30: =V31*V24 -> 69.583445
B31: % of Sales | G31: =G30/G24 -> 0.058982807 | H31: =H30/H24 -> 0.030946366 | I31: =I30/I24 -> 0.067213534 | J31: =J30/J24 -> 0.07316754 | K31: =K30/K24 -> 0.059619014 | L31: =L30/L24 -> 0.075179834 | M31: {=OFFSET(M31,$E$11,,)} -> 0.07 | N31: {=OFFSET(N31,$E$11,,)} -> 0.07 | O31: {=OFFSET(O31,$E$11,,)} -> 0.07 | P31: {=OFFSET(P31,$E$11,,)} -> 0.07 | Q31: {=OFFSET(Q31,$E$11,,)} -> 0.07 | R31: {=OFFSET(R31,$E$11,,)} -> 0.07 | S31: {=OFFSET(S31,$E$11,,)} -> 0.07 | T31: {=OFFSET(T31,$E$11,,)} -> 0.07 | ... V31: {=OFFSET(V31,$E$11,,)} -> 0.07
B32: Conservative Case | M32: =+WC!P42 -> 0.07 | N32: =+WC!Q42 -> 0.065 | O32: =+WC!R42 -> 0.06 | P32: =+WC!S42 -> 0.06 | Q32: =+WC!T42 -> 0.06 | R32: =+WC!U42 -> 0.06 | S32: 0.06 | T32: 0.06 | U32: 0.06 | V32: 0.06
B33: Base Case | M33: =+Model!T42 -> 0.07 | N33: =+Model!U42 -> 0.07 | O33: =+Model!V42 -> 0.07 | P33: =+Model!W42 -> 0.07 | Q33: =+Model!X42 -> 0.07 | R33: =+Model!Y42 -> 0.07 | S33: 0.07 | T33: 0.07 | U33: 0.07 | V33: 0.07
B34: Optimisitic Case | M34: =+BC!P42 -> 0.07 | N34: =+BC!Q42 -> 0.075 | O34: =+BC!R42 -> 0.08 | P34: =+BC!S42 -> 0.085 | Q34: =+BC!T42 -> 0.09 | R34: =+BC!U42 -> 0.09 | S34: 0.09 | T34: 0.09 | U34: 0.09 | V34: 0.09
B36: Taxes | G36: =+Model!N29 -> 9.368 | H36: =+Model!O29 -> 3.702 | I36: =+Model!P29 -> 11.604 | J36: =+Model!Q29 -> 9.525 | K36: =+Model!R29 -> 9.608 | L36: =+Model!S29 -> 13.497 | M36: =M37*M30 -> 12.505819 | N36: =N37*N30 -> 13.358243 | O36: =O37*O30 -> 14.94681 | P36: =P37*P30 -> 15.595169 | Q36: =Q37*Q30 -> 16.272166 | R36: =R37*R30 -> 16.979086 | S36: =S37*S30 -> 17.65825 | T36: =T37*T30 -> 18.311605 | ... V36: =V37*V30 -> 19.483365
B37: Tax Rate (%) | G37: =G36/G30 -> 0.31186125 | H37: =H36/H30 -> 0.22875857 | I37: =I36/I30 -> 0.31290279 | J37: =J36/J30 -> 0.24692798 | K37: =K36/K30 -> 0.27829915 | L37: =L36/L30 -> 0.28074299 | M37: 0.28 | N37: 0.28 | O37: 0.28 | P37: 0.28 | Q37: 0.28 | R37: 0.28 | S37: 0.28 | T37: 0.28 | U37: 0.28 | V37: 0.28
B39: Nopat | G39: =G30-G36 -> 20.671 | H39: =H30-H36 -> 12.481 | I39: =I30-I36 -> 25.481 | J39: =J30-J36 -> 29.049 | K39: =K30-K36 -> 24.916 | L39: =L30-L36 -> 34.579 | M39: =M30-M36 -> 32.157821 | N39: =N30-N36 -> 34.349767 | ... V39: =V30-V36 -> 50.10008
B41: D&A and other non-cash Expenses | G41: =+Model!N72 -> 16.538 | H41: =+Model!O72 -> 18.752 | I41: =+Model!P72 -> 18.495 | J41: =+Model!Q72 -> 18.446 | K41: =+Model!R72 -> 20.322 | L41: =+Model!S72 -> 20.479 | M41: =M42*M24 -> 20.417664 | N41: =N42*N24 -> 21.809376 | O41: =O42*O24 -> 24.402955 | P41: =P42*P24 -> 25.461501 | Q41: =Q42*Q24 -> 26.566801 | R41: =R42*R24 -> 27.720957 | S41: =S42*S24 -> 28.829795 | T41: =T42*T24 -> 29.896498 | ... V41: =V42*V24 -> 31.809575
B42: % of Sales | G42: =G41/G24 -> 0.032473041 | H42: =H41/H24 -> 0.035859004 | I42: =I41/I24 -> 0.033520677 | J42: =J41/J24 -> 0.034988553 | K42: =K41/K24 -> 0.035093779 | L42: =L41/L24 -> 0.032024457 | M42: 0.032 | N42: 0.032 | O42: 0.032 | P42: 0.032 | Q42: 0.032 | R42: 0.032 | S42: 0.032 | T42: 0.032 | U42: 0.032 | V42: 0.032
B44: CapEx | G44: =+Model!N91+Model!N92 -> -37.325 | H44: =+Model!O91+Model!O92 -> -24.316 | I44: =+Model!P91+Model!P92 -> -15.144 | J44: =+Model!Q91+Model!Q92 -> -15.001 | K44: =+Model!R91+Model!R92 -> -21.131 | L44: =+Model!S91+Model!S92 -> -19.557 | M44: =M45*M24 -> -21.693768 | N44: =N45*N24 -> -23.172462 | O44: =O45*O24 -> -25.92814 | P44: =P45*P24 -> -27.052845 | Q44: =Q45*Q24 -> -28.227226 | R44: =R45*R24 -> -29.453517 | S44: =S45*S24 -> -30.631658 | T44: =T45*T24 -> -31.765029 | ... V44: =V45*V24 -> -33.797673
B45: % of Sales | G45: =G44/G24 -> -0.073289167 | H45: =H44/H24 -> -0.046498909 | I45: =I44/I24 -> -0.027447263 | J45: =J44/J24 -> -0.028454043 | K45: =K44/K24 -> -0.036490829 | L45: =L44/L24 -> -0.030582661 | M45: -0.034 | N45: -0.034 | O45: -0.034 | P45: -0.034 | Q45: -0.034 | R45: -0.034 | S45: -0.034 | T45: -0.034 | U45: -0.034 | V45: -0.034
B47: Change in WC | G47: =+Model!N87 -> 18.15 | H47: =+Model!O87 -> 1.517 | I47: =+Model!P87 -> 1.073 | J47: =+Model!Q87 -> -14.116 | K47: =+Model!R87 -> -48.46 | L47: =+Model!S87 -> 46.708 | M47: =M48*M24 -> 0.638052 | N47: =N48*N24 -> 0.681543 | O47: =O48*O24 -> 0.76259236 | P47: =P48*P24 -> 0.79567191 | Q47: =Q48*Q24 -> 0.83021254 | R47: =R48*R24 -> 0.86627991 | S47: =S48*S24 -> 0.90093111 | T47: =T48*T24 -> 0.93426556 | ... V47: =V48*V24 -> 0.99404921
B48: % of Sales | G48: =G47/G24 -> 0.035638269 | H48: =H47/H24 -> 0.0029009231 | I48: =I47/I24 -> 0.0019447249 | J48: =J47/J24 -> -0.026775367 | K48: =K47/K24 -> -0.083684899 | L48: =L47/L24 -> 0.073040595 | M48: 0.001 | N48: 0.001 | O48: 0.001 | P48: 0.001 | Q48: 0.001 | R48: 0.001 | S48: 0.001 | T48: 0.001 | U48: 0.001 | V48: 0.001
B50: Unlevered Free Cashflow | G50: =G39+G41+G44+G47 -> 18.034 | H50: =H39+H41+H44+H47 -> 8.434 | I50: =I39+I41+I44+I47 -> 29.905 | J50: =J39+J41+J44+J47 -> 18.378 | K50: =K39+K41+K44+K47 -> -24.353 | L50: =L39+L41+L44+L47 -> 82.209 | M50: =M39+M41+M44+M47 -> 31.519769 | N50: =N39+N41+N44+N47 -> 33.668224 | ... V50: =V39+V41+V44+V47 -> 49.106031
B51: Present Value of unlevered FC | M51: =(M50/(1+$E$17)^M52)*M52 -> 15.164956 | N51: =N50/((1+$E$17)^N52) -> 29.997467 | O51: =O50/((1+$E$17)^O52) -> 31.078497 | P51: =P50/((1+$E$17)^P52) -> 30.024642 | Q51: =Q50/((1+$E$17)^Q52) -> 29.007436 | R51: =R50/((1+$E$17)^R52) -> 28.025575 | S51: =S50/((1+$E$17)^S52) -> 26.987591 | T51: =T50/((1+$E$17)^T52) -> 25.913085 | U51: =U50/((1+$E$17)^U52) -> 24.785386 | V51: =V50/(1+$E$17)^V52 -> 23.637914
B52: Discount Period | M52: =YEARFRAC(E3,E4) -> 0.5 | N52: =M52+1 -> 1.5 | O52: =N52+1 -> 2.5 | P52: =O52+1 -> 3.5 | Q52: =P52+1 -> 4.5 | R52: =Q52+1 -> 5.5 | S52: =R52+1 -> 6.5 | T52: =S52+1 -> 7.5 | U52: =T52+1 -> 8.5 | V52: =U52+1 -> 9.5
B53: Sum of Present Value | V53: =SUM(M51:V51) -> 264.62255
B54: Terminal Value | V54: =+(V39*(1+E18))*(1-(E18/E19))/(E17-E18) -> 688.0411 | X54: CV(t) = NOPAT(t+1)*(1-g/RONIC)/(WACC - g) => equal perpetuity formula: CV = FCF*(1+g) /(WACC-g)
B55: Present Value of TV | V55: =V54/(1+E17)^V52 -> 331.19876
B56: Enterprise Value | V56: =V53+V55 -> 595.82131
B57: (+) Cash and other non-operating assets | V57: =+Main!H5 -> 83.239
B58: (-) Debt and other non-equity claims | V58: =+Main!H6 -> 15.464
B59: Equity Value | V59: =V56+V57-V58 -> 663.59631
B60: Number of Shares | V60: =+Main!H3 -> 6.812598
B61: Share Price | V61: =V59/V60 -> 97.407232
A65: x | B65: Sensitivity Analysis
C67: TGR | N67: ROINC
B68: WACC | C68: =+J3 -> 97.407232 | D68: 0.015 | E68: 0.02 | F68: 0.025 | G68: 0.03 | H68: 0.035 | I68: 0.04 | J68: 0.045 | M68: WACC | N68: =+J3 -> 97.407232 | O68: 0.075 | P68: 0.08 | Q68: 0.085 | R68: 0.09 | S68: 0.095 | T68: 0.1 | U68: 0.105
C69: 0.065 | D69: 120.03375 | E69: 122.91626 | F69: 126.46325 | G69: 130.95949 | H69: 136.87961 | I69: 145.07793 | J69: 157.2631 | N69: 0.065 | O69: 123.0275 | P69: 126.002 | Q69: 128.62655 | R69: 130.95949 | S69: 133.04686 | T69: 134.92549 | U69: 136.6252
C70: 0.07 | D70: 110.12726 | E70: 112.01391 | F70: 114.27208 | G70: 117.04108 | H70: 120.53984 | I70: 125.13324 | J70: 131.47806 | N70: 0.07 | O70: 110.40264 | P70: 112.89205 | Q70: 115.0886 | R70: 117.04108 | S70: 118.78803 | T70: 120.36029 | U70: 121.78282
C71: 0.075 | D71: 101.86082 | E71: 103.07063 | F71: 104.48131 | G71: 106.15979 | H71: 108.20652 | I71: 110.7793 | J71: 114.14116 | N71: 0.075 | O71: 100.5146 | P71: 102.63155 | Q71: 104.49944 | R71: 106.15979 | S71: 107.64537 | T71: 108.98239 | U71: 110.19207
C72: 0.08 | D72: 94.856635 | E72: 95.597912 | F72: 96.438209 | G72: 97.407232 | H72: 98.54789 | I72: 99.924546 | J72: 101.63834 | N72: 0.08 | O72: 92.545668 | P72: 94.368755 | Q72: 95.97736 | R72: 97.407232 | S72: 98.68659 | T72: 99.838013 | U72: 100.87978
C73: 0.085 | D73: 88.844831 | E73: 89.257472 | F73: 89.707516 | G73: 90.205164 | H73: 90.764697 | I73: 91.406743 | J73: 92.162246 | N73: 0.085 | O73: 85.9753 | P73: 87.561499 | Q73: 88.961086 | R73: 90.205164 | S73: 91.318286 | T73: 92.320096 | U73: 93.226495
C74: 0.09 | D74: 83.627452 | E74: 83.80763 | F74: 83.987808 | G74: 84.167986 | H74: 84.348164 | I74: 84.528342 | J74: 84.708519 | N74: 0.09 | O74: 80.456322 | P74: 81.848196 | Q74: 83.07632 | R74: 84.167986 | S74: 85.144739 | T74: 86.023818 | U74: 86.819174
C75: 0.095 | D75: 79.056003 | E75: 79.071098 | F75: 79.063705 | G75: 79.028634 | H75: 78.958965 | I75: 78.845264 | J75: 78.674321 | N75: 0.096 | O75: 74.887909 | P75: 76.088952 | Q75: 77.148696 | R75: 78.090691 | S75: 78.933528 | T75: 79.692082 | U75: 80.378393

Sheet CoC
A1: Main
B3: Cost of Capital
A4: x | B4: Cost of Equity (CAPM)
B5: Riskfree Rate
B6: Expected Inflation | H6: =(1+Nominal Rate)/(1+Real Rate)-1
B7: Average Real Interest Rate | H7: = Average Interest Rate of the Past
B8: Riskfree Rate | F8: =F6+F7 -> 0 | H8: =Goverment Bond or Expected Inflation + Average Real Interest Rate
A10: x | B10: Adjustments for Industry/Company Risk
B11: Raw Beta | H11: =Raw beta slope of regression line aginst total market -> Ri= alpha + beta*Rm + standard error
B12: Debt to Value Ratio | H12: Value of Debt/Enterpries Value
B13: Unlevered Beta | H13: = Raw Beta* Debt-to-Equity Ratio (Book Value)
B14: Unlevered Industry Beta | H14: =Median of Peer Group
B15: Levered Industry Beta | H15: =Unlevered Industry Beta * Market Value of Debt to Market Value of Equity
A17: x | B17: Expected Equity Risk Premium
B18: Estimated Future Market Return | H18: = 1/P/E * (1.g/ROE) + g , g = real growth in GDP, P/E => P/E ratio for S&P500 or MSCI World Index, ROE = Average ROE in S&P500 or MSCI World
B19: Riskfree Rate
B20: Expected Equity Risk Premium | F20: =F18-F19 -> 0
A22: x | B22: Cost of Equity (CAPM) | F22: =F8+F15*F20 -> 0 | H22: => ER(i)=rf+beta(i)*(Er(m)-rf)
A25: x | B25: Cost of Debt
B26: Yield to Maturity on Trading Bonds | H26: => Price = Coupon/(1+YTM)+Coupon(1+YTM)^2 + … + (Face Value + Coupon)/(1+YTM)^n => solve for YTM
B27: or
B28: Riskfree Rate
B29: Credit Default Spread
B30: Country Rsik Premium
A32: x | B32: Cost of Debt | F32: =F28+F29+F30 -> 0
A34: x | B34: Capital Structure
B35: Market Value of Debt
B36: Market Value of Equity
B37: Total Enterprise Value | F37: =F35+F36 -> 0
B39: Marginal Tax Rate
A41: x | B41: WACC | F41: =(F32*(F35/F37)*(1-F39))+((F36/F38)*F22) -> #DIV/0! | H41: => WACC = (D/D+E)*kd * (1-t) + (E/D+E) * ke
I47: =SLOPE(H48:H52,K48:K52) -> #DIV/0!
H48: Change
