Workbook

Sheet Main
A1: On Holding
A2: numbers in mio CHF | G2: Price USD | H2: 30.85
G3: Price CHF | H3: =+H2*H10 -> 26.2225
B4: IR | G4: Shares | H4: 296.87335 | I4: Q226
B5: ONON | G5: MC | H5: =+H3*H4 -> 7784.7615
G6: Cash | H6: 1020.4 | I6: Q226
B7: Segments | G7: Debt | H7: =52.2+5.8 -> 58 | I7: Q226
B8: Shoes | G8: EV | H8: =+H5-H6+H7 -> 6822.3615
B9: Appereal
B10: Accessoires | G10: USD/CHF | H10: 0.85
G11: Employee Count: 3.254
B12: Notes
B13: 2024 multi-year brand partnership with Zendaya | G13: Management
B14: IPO 2021 | G14: CEO | H14: Martin Hoffman (former CFO) | K14: Marc Maurer former CEO
B15: Manufacturing: 25 Suppliers; | G15: CFO | H15: Martin Hoffman
B16: Footwear 8 Vietnam, 1 Indonesia, Appereal 13 Suppliers ->
B17: Vietnam, Portugal, Turkey, China
B18: Vietnam Tariffs: 46%

Sheet Model
A1: Main
C2: Q123 | D2: Q223 | E2: Q323 | F2: Q423 | G2: Q124 | H2: Q224 | I2: Q324 | J2: Q424 | K2: Q125 | L2: Q225 | M2: Q325 | N2: Q425 | O2: Q126 | P2: Q226 | Q2: Q326 | R2: Q426 | T2: FY19 | U2: FY20 | V2: FY21 | W2: FY22 | X2: FY23 | Y2: FY24 | Z2: FY25
B3: EMEA Revenue | C3: 118.9 | D3: 113.6 | E3: 144 | F3: =+X3-SUM(C3:E3) -> 112.2 | G3: 126.2 | H3: 138.4 | I3: 165.8 | J3: =+Y3-SUM(G3:I3) -> 147.4 | K3: 168.6 | L3: 197.8 | M3: 213.3 | N3: =+Z3-SUM(K3:M3) -> 183 | O3: 207.1 | P3: 228.2 | T3: =128.344+9.148 -> 137.492 | U3: =187.51+6.697 -> 194.207 | V3: =260.4+12 -> 272.4 | W3: 378.1 | X3: 488.7 | Y3: 577.8 | Z3: 762.7
B4: Americas Revenue | C4: 270.2 | D4: 296.6 | E4: 294.9 | F4: =+X4-SUM(C4:E4) -> 300.5 | G4: 329.6 | H4: 370 | I4: 395.5 | J4: =+Y4-SUM(G4:I4) -> 385.2 | K4: 437.4 | L4: 432.3 | M4: 436.2 | N4: =+Z4-SUM(K4:M4) -> 434.2 | O4: 450.7 | P4: 451.6 | T4: 111.761 | U4: 208.089 | V4: 409.5 | W4: 763.8 | X4: 1162.2 | Y4: 1480.3 | Z4: 1740.1
B5: Asia Pacific Revenue | C5: 31.1 | D5: 34.1 | E5: 41.6 | F5: =+X5-SUM(C5:E5) -> 34.3 | G5: 52.4 | H5: 59.2 | I5: 74.6 | J5: =+Y5-SUM(G5:I5) -> 74 | K5: 120.6 | L5: 119.2 | M5: 144.9 | N5: =+Z5-SUM(K5:M5) -> 126.4 | O5: 174 | P5: 170.5 | T5: 17.867 | U5: 22.999 | V5: =42.7 -> 42.7 | W5: 80.2 | X5: 141.1 | Y5: 260.2 | Z5: 511.1
B6: Shoes Revenue | C6: 400.5 | D6: 428.2 | E6: 456.9 | F6: =+X6-SUM(C6:E6) -> 425.8 | G6: 484.7 | H6: 542.5 | I6: 603.7 | J6: =+Y6-SUM(G6:I6) -> 568.7 | K6: 680.9 | L6: 704.9 | M6: 731.3 | N6: =+Z6-SUM(K6:M6) -> 687.3 | O6: 763.7 | P6: 781.6 | T6: 255.612 | U6: 406.39 | V6: 683.3 | W6: 1167.5 | X6: 1711.4 | Y6: 2199.6 | Z6: 2804.4
B7: Appereal Revenue | C7: 16.9 | D7: 13.4 | E7: 20.1 | F7: =+X7-SUM(C7:E7) -> 18.5 | G7: 19.7 | H7: 21.9 | I7: 26.8 | J7: =+Y7-SUM(G7:I7) -> 32.6 | K7: 38.1 | L7: 36.7 | M7: 50.1 | N7: =+Z7-SUM(K7:M7) -> 45 | O7: 55.3 | P7: 54.2 | T7: 9.57 | U7: 15.75 | V7: 36.3 | W7: 47.3 | X7: 68.9 | Y7: 101 | Z7: 169.9
B8: Accessoires Revenue | C8: 2.8 | D8: 2.7 | E8: 3.5 | F8: =+X8-SUM(C8:E8) -> 2.8 | G8: 3.8 | H8: 3.3 | I8: 5.3 | J8: =+Y8-SUM(G8:I8) -> 5.3 | K8: 7.6 | L8: 7.7 | M8: 13 | N8: =+Z8-SUM(K8:M8) -> 11.3 | O8: 12.9 | P8: 14.5 | T8: 1.938 | U8: 3.155 | V8: 5 | W8: 7.4 | X8: 11.8 | Y8: 17.7 | Z8: 39.6
B9: Wholesale Revenue | C9: 283.2 | D9: 280.8 | E9: 315.7 | F9: =+X9-SUM(C9:E9) -> 240.6 | G9: 317.7 | H9: 358.2 | I9: 389.1 | J9: =+Y9-SUM(G9:I9) -> 310.5 | K9: 449.7 | L9: 441 | M9: 479.6 | N9: =+Z9-SUM(K9:M9) -> 383.1 | O9: 509.6 | P9: 461.9 | T9: 200.716 | U9: 264.819 | V9: 448.8 | W9: 777 | X9: 1120.3 | Y9: 1375.5 | Z9: 1753.4
B10: DTC Revenue | C10: 137 | D10: 163.5 | E10: 164.7 | F10: =+X10-SUM(C10:E10) -> 206.6 | G10: 190.5 | H10: 209.4 | I10: 246.7 | J10: =+Y10-SUM(G10:I10) -> 296.2 | K10: 276.9 | L10: 308.3 | M10: 314.7 | N10: =+Z10-SUM(K10:M10) -> 360.6 | O10: 322.3 | P10: 388.4 | T10: 66.404 | U10: 160.476 | V10: 275.8 | W10: 445.1 | X10: 671.8 | Y10: 942.8 | Z10: 1260.5
B11: Revenue | C11: 420.2 | D11: 444.3 | E11: 480.5 | F11: =+X11-SUM(C11:E11) -> 447.1 | G11: 508.2 | H11: 567.7 | I11: 635.8 | J11: =+Y11-SUM(G11:I11) -> 606.6 | K11: 726.6 | L11: 749.2 | M11: 794.4 | N11: =+Z11-SUM(K11:M11) -> 743.8 | O11: 831.9 | P11: 850.3 | T11: 267.12 | U11: 425.29 | V11: 724.6 | W11: 1222.1 | X11: 1792.1 | Y11: 2318.3 | Z11: 3014
B12: COGS | C12: 175.3 | D12: 179.8 | E12: 192.8 | F12: =+X12-SUM(C12:E12) -> 176.9 | G12: 204.9 | H12: 227.4 | I12: 250.5 | J12: =+Y12-SUM(G12:I12) -> 229.8 | K12: 291.3 | L12: 288.4 | M12: 272.1 | N12: =+Z12-SUM(K12:M12) -> 268.5 | O12: 297.6 | P12: 294.6 | T12: 124.003 | U12: 194.19 | V12: 294.3 | W12: 537.2 | X12: 724.8 | Y12: 912.6 | Z12: 1120.3
B13: Gross Profit | C13: =+C11-C12 -> 244.9 | D13: =+D11-D12 -> 264.5 | E13: =+E11-E12 -> 287.7 | F13: =+F11-F12 -> 270.2 | G13: =+G11-G12 -> 303.3 | H13: =+H11-H12 -> 340.3 | I13: =+I11-I12 -> 385.3 | J13: =+J11-J12 -> 376.8 | ... P13: =+P11-P12 -> 555.7 | T13: =+T11-T12 -> 143.117 | U13: =+U11-U12 -> 231.1 | V13: =+V11-V12 -> 430.3 | W13: =+W11-W12 -> 684.9 | X13: =+X11-X12 -> 1067.3 | Y13: =+Y11-Y12 -> 1405.7 | Z13: =+Z11-Z12 -> 1893.7
B14: SGA | C14: 202.6 | D14: 225.1 | E14: 229.9 | F14: =+X14-SUM(C14:E14) -> 229.4 | G14: 264.8 | H14: 292.9 | I14: 312.7 | J14: =+Y14-SUM(G14:I14) -> 323.8 | K14: 358.2 | L14: 368 | M14: 397.5 | N14: =+Z14-SUM(K14:M14) -> 392.9 | O14: 416.9 | P14: 436.3 | T14: 137.428 | U14: 248.199 | V14: 571.4 | W14: 599.8 | X14: 887 | Y14: 1194.2 | Z14: 1516.6
B15: Operating Income | C15: =+C13-C14 -> 42.3 | D15: =+D13-D14 -> 39.4 | E15: =+E13-E14 -> 57.8 | F15: =+F13-F14 -> 40.8 | G15: =+G13-G14 -> 38.5 | H15: =+H13-H14 -> 47.4 | I15: =+I13-I14 -> 72.6 | J15: =+J13-J14 -> 53 | ... P15: =+P13-P14 -> 119.4 | T15: =+T13-T14 -> 5.689 | U15: =+U13-U14 -> -17.099 | V15: =+V13-V14 -> -141.1 | W15: =+W13-W14 -> 85.1 | X15: =+X13-X14 -> 180.3 | Y15: =+Y13-Y14 -> 211.5 | Z15: =+Z13-Z14 -> 377.1
B16: Interest Income | C16: 2.1 | D16: 4.3 | E16: 1 | F16: =+X16-SUM(C16:E16) -> 4.1 | G16: 5.4 | H16: 5.8 | I16: 6 | J16: =+Y16-SUM(G16:I16) -> 6.3 | K16: 7.3 | L16: 7.5 | M16: 8.1 | N16: =+Z16-SUM(K16:M16) -> 8 | O16: 7 | P16: 11.3 | T16: 0.047 | U16: 0.027 | V16: 0 | W16: 5.7 | X16: 11.5 | Y16: 23.5 | Z16: 30.9
B17: Interest Expenses | C17: 1.7 | D17: 1.9 | E17: 3.2 | F17: =+X17-SUM(C17:E17) -> 4.5 | G17: 4.9 | H17: 5.9 | I17: 6.5 | J17: =+Y17-SUM(G17:I17) -> 5.8 | K17: 5.9 | L17: 7.7 | M17: 8.1 | N17: =+Z17-SUM(K17:M17) -> 7.9 | O17: 8 | P17: 8.3 | T17: 0.697 | U17: 0.93 | V17: 3.6 | W17: 6.4 | X17: 11.3 | Y17: 23.1 | Z17: 29.6
B18: Loss on foreign exchanges | C18: -8.8 | D18: 48.5 | E18: -13.8 | F18: =+X18-SUM(C18:E18) -> -137.3 | G18: -76.8 | H18: 4.5 | I18: 42.6 | J18: =+Y18-SUM(G18:I18) -> 97.4 | K18: 14.5 | L18: 139.9 | M18: 6.1 | N18: =+Z18-SUM(K18:M18) -> -333.7 | O18: 0.3 | P18: 3.3 | T18: -1.893 | U18: -6.434 | V18: -14.9 | W18: -6.5 | X18: -111.4 | Y18: 67.7 | Z18: -173.2
B19: Pretax Income | C19: =+C15+C16-C17-C18 -> 51.5 | D19: =+D15+D16-D17-D18 -> -6.7 | E19: =+E15+E16-E17-E18 -> 69.4 | F19: =+F15+F16-F17-F18 -> 177.7 | G19: =+G15+G16-G17-G18 -> 115.8 | H19: =+H15+H16-H17-H18 -> 42.8 | I19: =+I15+I16-I17-I18 -> 29.5 | J19: =+J15+J16-J17-J18 -> -43.9 | ... P19: =+P15+P16-P17-P18 -> 119.1 | T19: =+T15+T16-T17+T18 -> 3.146 | U19: =+U15+U16-U17+U18 -> -24.436 | V19: =+V15+V16-V17+V18 -> -159.6 | W19: =+W15+W16-W17+W18 -> 77.9 | X19: =+X15+X16-X17+X18 -> 69.1 | Y19: =+Y15+Y16-Y17+Y18 -> 279.6 | Z19: =+Z15+Z16-Z17+Z18 -> 205.2
B20: Tax Expense | C20: 7.1 | D20: -10 | E20: 10.6 | F20: =+X20-SUM(C20:E20) -> -18.2 | G20: 24.4 | H20: 11.8 | I20: -0.9 | J20: =+Y20-SUM(G20:I20) -> 2.1 | K20: 7.2 | L20: -6.4 | M20: -0.3 | N20: =+Z20-SUM(K20:M20) -> 1 | O20: 12.8 | P20: 20.7 | T20: 4.62 | U20: 3.083 | V20: 10.6 | W20: 20.2 | X20: -10.5 | Y20: 37.4 | Z20: 1.5
B21: Net Income | C21: =+C19-C20 -> 44.4 | D21: =+D19-D20 -> 3.3 | E21: =+E19-E20 -> 58.8 | F21: =+F19-F20 -> 195.9 | G21: =+G19-G20 -> 91.4 | H21: =+H19-H20 -> 31 | I21: =+I19-I20 -> 30.4 | J21: =+Y21-SUM(G21:I21) -> 89.4 | K21: =+K19-K20 -> 56.8 | L21: =+L19-L20 -> -40.9 | M21: =+M19-M20 -> 119 | N21: =+N19-N20 -> 415.2 | O21: =+O19-O20 -> 103.3 | P21: =+P19-P20 -> 98.4 | T21: =+T19-T20 -> -1.474 | U21: =+U19-U20 -> -27.519 | V21: =+V19-V20 -> -170.2 | W21: =+W19-W20 -> 57.7 | X21: =+X19-X20 -> 79.6 | Y21: =+Y19-Y20 -> 242.2 | Z21: =+Z19-Z20 -> 203.7
B23: EPS | C23: =+C21/C24 -> 0.15660108 | D23: =+D21/D24 -> 0.011625483 | E23: =+E21/E24 -> 0.20694907 | F23: =+F21/F24 -> 0.6878935 | G23: =+G21/G24 -> 0.31774568 | H23: =+H21/H24 -> 0.10760789 | I23: =+I21/I24 -> 0.10547036 | J23: =+J21/J24 -> 0.30865931 | ... P23: =+P21/P24 -> 0.33145447 | T23: n.a. | U23: n.a. | V23: =+V21/V24 -> -0.64427914 | W23: =+W21/W24 -> 0.20446746 | X23: =+X21/X24 -> 0.2795116 | Y23: =+Y21/Y24 -> 0.83621125 | Z23: =+Z21/Z24 -> 0.68615118
B24: Shares | C24: 283.52294 | D24: 283.85917 | E24: 284.12788 | F24: =+X24 -> 284.78246 | G24: 287.65143 | H24: 288.08296 | I24: 288.23264 | J24: =+Y24 -> 289.63973 | K24: 293.33796 | L24: 293.04771 | M24: 296.4725 | N24: 296.4725 | O24: 296.87335 | P24: 296.87335 | T24: n.a. | U24: n.a. | V24: 264.17121 | W24: 282.1965 | X24: 284.78246 | Y24: 289.63973 | Z24: 296.87335
B26: Europe Growth | G26: =+G3/C3-1 -> 0.061396131 | H26: =+H3/D3-1 -> 0.21830986 | I26: =+I3/E3-1 -> 0.15138889 | J26: =+J3/F3-1 -> 0.31372549 | K26: =+K3/G3-1 -> 0.33597464 | L26: =+L3/H3-1 -> 0.42919075 | M26: =+M3/I3-1 -> 0.28648975 | N26: =+N3/J3-1 -> 0.24151967 | ... P26: =+P3/L3-1 -> 0.1536906 | T26: n.a. | U26: =+U3/T3-1 -> 0.41249673 | V26: =+V3/U3-1 -> 0.40262709 | W26: =+W3/V3-1 -> 0.38803231 | X26: =+X3/W3-1 -> 0.29251521 | Y26: =+Y3/X3-1 -> 0.18232044 | Z26: =+Z3/Y3-1 -> 0.32000692
B27: America Growth | G27: =+G4/C4-1 -> 0.21983716 | H27: =+H4/D4-1 -> 0.24747134 | I27: =+I4/E4-1 -> 0.34113259 | J27: =+J4/F4-1 -> 0.28186356 | K27: =+K4/G4-1 -> 0.32706311 | L27: =+L4/H4-1 -> 0.16837838 | M27: =+M4/I4-1 -> 0.10290771 | N27: =+N4/J4-1 -> 0.12720665 | ... P27: =+P4/L4-1 -> 0.044644923 | T27: n.a. | U27: =+U4/T4-1 -> 0.86191068 | V27: =+V4/U4-1 -> 0.96790796 | W27: =+W4/V4-1 -> 0.86520147 | X27: =+X4/W4-1 -> 0.52160251 | Y27: =+Y4/X4-1 -> 0.27370504 | Z27: =+Z4/Y4-1 -> 0.17550497
B28: Asia Pacific Growth | G28: =+G5/C5-1 -> 0.68488746 | H28: =+H5/D5-1 -> 0.73607038 | I28: =+I5/E5-1 -> 0.79326923 | J28: =+J5/F5-1 -> 1.1574344 | K28: =+K5/G5-1 -> 1.3015267 | L28: =+L5/H5-1 -> 1.0135135 | M28: =+M5/I5-1 -> 0.94235925 | N28: =+N5/J5-1 -> 0.70810811 | ... P28: =+P5/L5-1 -> 0.43036913 | T28: n.a. | U28: =+U5/T5-1 -> 0.28723345 | V28: =+V5/U5-1 -> 0.85660246 | W28: =+W5/V5-1 -> 0.87822014 | X28: =+X5/W5-1 -> 0.75935162 | Y28: =+Y5/X5-1 -> 0.84408221 | Z28: =+Z5/Y5-1 -> 0.96425826
B29: Shoes Growth | G29: =+G6/C6-1 -> 0.2102372 | H29: =+H6/D6-1 -> 0.26693134 | I29: =+I6/E6-1 -> 0.32129569 | J29: =+J6/F6-1 -> 0.33560357 | K29: =+K6/G6-1 -> 0.40478647 | L29: =+L6/H6-1 -> 0.29935484 | M29: =+M6/I6-1 -> 0.21136326 | N29: =+N6/J6-1 -> 0.20854581 | ... P29: =+P6/L6-1 -> 0.10880976 | T29: n.a. | U29: =+U6/T6-1 -> 0.58987059 | V29: =+V6/U6-1 -> 0.6813898 | W29: =+W6/V6-1 -> 0.70861993 | X29: =+X6/W6-1 -> 0.46586724 | Y29: =+Y6/X6-1 -> 0.28526353 | Z29: =+Z6/Y6-1 -> 0.27495908
B30: Appereal Growth | G30: =+G7/C7-1 -> 0.16568047 | H30: =+H7/D7-1 -> 0.63432836 | I30: =+I7/E7-1 -> 0.33333333 | J30: =+J7/F7-1 -> 0.76216216 | K30: =+K7/G7-1 -> 0.93401015 | L30: =+L7/H7-1 -> 0.67579909 | M30: =+M7/I7-1 -> 0.86940299 | N30: =+N7/J7-1 -> 0.3803681 | ... P30: =+P7/L7-1 -> 0.47683924 | T30: n.a. | U30: =+U7/T7-1 -> 0.64576803 | V30: =+V7/U7-1 -> 1.3047619 | W30: =+W7/V7-1 -> 0.3030303 | X30: =+X7/W7-1 -> 0.45665962 | Y30: =+Y7/X7-1 -> 0.4658926 | Z30: =+Z7/Y7-1 -> 0.68217822
B31: Accessoires Growth | G31: =+G8/C8-1 -> 0.35714286 | H31: =+H8/D8-1 -> 0.22222222 | I31: =+I8/E8-1 -> 0.51428571 | J31: =+J8/F8-1 -> 0.89285714 | K31: =+K8/G8-1 -> 1 | L31: =+L8/H8-1 -> 1.3333333 | M31: =+M8/I8-1 -> 1.4528302 | N31: =+N8/J8-1 -> 1.1320755 | ... P31: =+P8/L8-1 -> 0.88311688 | T31: n.a. | U31: =+U8/T8-1 -> 0.62796698 | V31: =+V8/U8-1 -> 0.58478605 | W31: =+W8/V8-1 -> 0.48 | X31: =+X8/W8-1 -> 0.59459459 | Y31: =+Y8/X8-1 -> 0.5 | Z31: =+Z8/Y8-1 -> 1.2372881
B32: Wholesale Growth | G32: =+G9/C9-1 -> 0.12182203 | H32: =+H9/D9-1 -> 0.27564103 | I32: =+I9/E9-1 -> 0.23249921 | J32: =+J9/F9-1 -> 0.29052369 | K32: =+K9/G9-1 -> 0.41548631 | L32: =+L9/H9-1 -> 0.23115578 | M32: =+M9/I9-1 -> 0.23258802 | N32: =+N9/J9-1 -> 0.23381643 | ... P32: =+P9/L9-1 -> 0.04739229 | T32: n.a. | U32: =+U9/T9-1 -> 0.31937165 | V32: =+V9/U9-1 -> 0.69474245 | W32: =+W9/V9-1 -> 0.73128342 | X32: =+X9/W9-1 -> 0.44182754 | Y32: =+Y9/X9-1 -> 0.22779613 | Z32: =+Z9/Y9-1 -> 0.27473646
B33: DTC Growth | G33: =+G10/C10-1 -> 0.39051095 | H33: =+H10/D10-1 -> 0.28073394 | I33: =+I10/E10-1 -> 0.49787492 | J33: =+J10/F10-1 -> 0.43368829 | K33: =+K10/G10-1 -> 0.45354331 | L33: =+L10/H10-1 -> 0.47230181 | M33: =+M10/I10-1 -> 0.27563843 | N33: =+N10/J10-1 -> 0.21742066 | ... P33: =+P10/L10-1 -> 0.25981187 | T33: n.a. | U33: =+U10/T10-1 -> 1.4166616 | V33: =+V10/U10-1 -> 0.71863705 | W33: =+W10/V10-1 -> 0.61385062 | X33: =+X10/W10-1 -> 0.50932375 | Y33: =+Y10/X10-1 -> 0.40339387 | Z33: =+Z10/Y10-1 -> 0.33697497
B34: Revenue Growth | G34: =+G11/C11-1 -> 0.20942408 | H34: =+H11/D11-1 -> 0.27774027 | I34: =+I11/E11-1 -> 0.32320499 | J34: =+J11/F11-1 -> 0.35674346 | K34: =+K11/G11-1 -> 0.42975207 | L34: =+L11/H11-1 -> 0.31971112 | M34: =+M11/I11-1 -> 0.24944951 | N34: =+N11/J11-1 -> 0.2261787 | ... P34: =+P11/L11-1 -> 0.13494394 | T34: n.a. | U34: =+U11/T11-1 -> 0.59213088 | V34: =+V11/U11-1 -> 0.7037786 | W34: =+W11/V11-1 -> 0.6865857 | X34: =+X11/W11-1 -> 0.46641028 | Y34: =+Y11/X11-1 -> 0.29362201 | Z34: =+Z11/Y11-1 -> 0.30009058
B35: Gross Margin | C35: =+C13/C11 -> 0.58281771 | D35: =+D13/D11 -> 0.59531848 | E35: =+E13/E11 -> 0.5987513 | F35: =+F13/F11 -> 0.60433907 | G35: =+G13/G11 -> 0.59681228 | H35: =+H13/H11 -> 0.59943632 | I35: =+I13/I11 -> 0.60600818 | J35: =+J13/J11 -> 0.62116716 | ... P35: =+P13/P11 -> 0.65353405 | T35: =+T13/T11 -> 0.53577793 | U35: =+U13/U11 -> 0.54339392 | V35: =+V13/V11 -> 0.59384488 | W35: =+W13/W11 -> 0.56042877 | X35: =+X13/X11 -> 0.59555828 | Y35: =+Y13/Y11 -> 0.60634948 | Z35: =+Z13/Z11 -> 0.62830126
B36: Operating Margin | C36: =+C15/C11 -> 0.10066635 | D36: =+D15/D11 -> 0.088678821 | E36: =+E15/E11 -> 0.12029136 | F36: =+F15/F11 -> 0.091254753 | G36: =+G15/G11 -> 0.075757576 | H36: =+H15/H11 -> 0.083494804 | I36: =+I15/I11 -> 0.11418685 | J36: =+J15/J11 -> 0.087372239 | ... P36: =+P15/P11 -> 0.14042103 | T36: =+T15/T11 -> 0.021297544 | U36: =+U15/U11 -> -0.040205507 | V36: =+V15/V11 -> -0.19472813 | W36: =+W15/W11 -> 0.069634236 | X36: =+X15/X11 -> 0.10060822 | Y36: =+Y15/Y11 -> 0.091230643 | Z36: =+Z15/Z11 -> 0.12511612
B37: Tax Rate | C37: =+C20/C19 -> 0.13786408 | D37: =+D20/D19 -> 1.4925373 | E37: =+E20/E19 -> 0.15273775 | F37: =+F20/F19 -> -0.10241981 | G37: =+G20/G19 -> 0.21070812 | H37: =+H20/H19 -> 0.27570093 | I37: =+I20/I19 -> -0.030508475 | J37: =+J20/J19 -> -0.047835991 | ... P37: =+P20/P19 -> 0.17380353 | T37: =+T20/T19 -> 1.4685315 | U37: =+U20/U19 -> -0.12616631 | V37: =+V20/V19 -> -0.06641604 | W37: =+W20/W19 -> 0.2593068 | X37: =+X20/X19 -> -0.15195369 | Y37: =+Y20/Y19 -> 0.13376252 | Z37: =+Z20/Z19 -> 0.0073099415
B39: Cash & Cash Equivalents | U39: 90.642 | V39: 653.081 | W39: 371 | X39: 494.6 | Y39: 924.3 | Z39: 1019.9
B40: Account Receivables | U40: 51.631 | V40: 99.264 | W40: 174.6 | X40: 204.8 | Y40: 246.1 | Z40: 305.4
B41: Inventories | U41: 102.878 | V41: 134.178 | W41: 395.6 | X41: 356.5 | Y41: 419.2 | Z41: 419.8
B42: Other Financial Assets | U42: 17.135 | V42: 30.054 | W42: 33.2 | X42: 34.2 | Y42: 56.4 | Z42: 59.2
B43: Other | U43: 19.979 | V43: 48.024 | W43: 77 | X43: 61.2 | Y43: 113.7 | Z43: 158.2
B44: Current Assets | T44: =+SUM(T39:T43) -> 0 | U44: =+SUM(U39:U43) -> 282.265 | V44: =+SUM(V39:V43) -> 964.601 | W44: =+SUM(W39:W43) -> 1051.4 | X44: =+SUM(X39:X43) -> 1151.3 | Y44: =+SUM(Y39:Y43) -> 1759.7 | Z44: =+SUM(Z39:Z43) -> 1962.5
B45: PP&E | U45: 17.004 | V45: 34.399 | W45: 77.2 | X45: 93.6 | Y45: 127.2 | Z45: 148.8
B46: Leases | U46: 22.719 | V46: 177.89 | W46: 151.6 | X46: 214 | Y46: 323.6 | Z46: 494.1
B47: Intangibles | U47: 54.667 | V47: 57.464 | W47: 70.3 | X47: 64.6 | Y47: 58.3 | Z47: 54.2
B48: Deferred Tax Assets | U48: 5.915 | V48: 2.171 | W48: 31.7 | X48: 69.5 | Y48: 107.8 | Z48: 175.9
B49: Non-Current Assets | T49: =+SUM(T45:T48) -> 0 | U49: =+SUM(U45:U48) -> 100.305 | V49: =+SUM(V45:V48) -> 271.924 | W49: =+SUM(W45:W48) -> 330.8 | X49: =+SUM(X45:X48) -> 441.7 | Y49: =+SUM(Y45:Y48) -> 616.9 | Z49: =+SUM(Z45:Z48) -> 873
B50: Total Assets | T50: =+T49+T44 -> 0 | U50: =+U49+U44 -> 382.57 | V50: =+V49+V44 -> 1236.525 | W50: =+W49+W44 -> 1382.2 | X50: =+X49+X44 -> 1593 | Y50: =+Y49+Y44 -> 2376.6 | Z50: =+Z49+Z44 -> 2835.5
B51: Account Payables | U51: 41.543 | V51: 45.939 | W51: 111 | X51: 65.1 | Y51: 166.5 | Z51: 154.8
B52: Current Lease Liabilties | U52: 0 | V52: 0 | W52: 0 | X52: 38.7 | Y52: 59.1 | Z52: 81.2
B53: Other Financial Liabilties | U53: 7.276 | V53: 20.097 | W53: 31 | X53: 14.8 | Y53: 51.3 | Z53: 56.7
B54: Other Operating Liabilties | U54: 36.113 | V54: 121.673 | W54: 81.7 | X54: 156.4 | Y54: 299.3 | Z54: 355.4
B55: Current Provisions | U55: 0.376 | V55: 14.902 | W55: 5 | X55: 7.1 | Y55: 21.7 | Z55: 13
B56: Income Tax Liabilities | U56: 1.054 | V56: 2.4 | W56: 13.9 | X56: 23.5 | Y56: 62.5 | Z56: 63.2
B57: Current Liabilties | T57: =+SUM(T51:T56) -> 0 | U57: =+SUM(U51:U56) -> 86.362 | V57: =+SUM(V51:V56) -> 205.011 | W57: =+SUM(W51:W56) -> 242.6 | X57: =+SUM(X51:X56) -> 305.6 | Y57: =+SUM(Y51:Y56) -> 660.4 | Z57: =+SUM(Z51:Z56) -> 724.3
B58: Employee benefits | U58: 5.63 | V58: 5.853 | W58: 6.3 | X58: 2.2 | Y58: 8.6 | Z58: 5.5
B59: Non-current Provisions | U59: 20.645 | V59: 4.442 | W59: 7.2 | X59: 10 | Y59: 14.9 | Z59: 20.7
B60: Lease liabilities | T60: 0 | U60: 0 | V60: 0 | W60: 0 | X60: 190.3 | Y60: 288.5 | Z60: 440.3
B61: Other Financial Liabilties | U61: 19.174 | V61: 167.228 | W61: 138.8 | X61: 0 | Y61: 1.7 | Z61: 2.8
B62: Deferred Tax Liabilties | U62: 5.664 | V62: 5.611 | W62: 17.9 | X62: 10.4 | Y62: 10.8 | Z62: 9.3
B63: Non-current Liabilities | T63: =+SUM(T58:T62) -> 0 | U63: =+SUM(U58:U62) -> 51.113 | V63: =+SUM(V58:V62) -> 183.134 | W63: =+SUM(W58:W62) -> 170.2 | X63: =+SUM(X58:X62) -> 212.9 | Y63: =+SUM(Y58:Y62) -> 324.5 | Z63: =+SUM(Z58:Z62) -> 478.6
B64: Total Liabilties | T64: =+T63+T57 -> 0 | U64: =+U63+U57 -> 137.475 | V64: =+V63+V57 -> 388.145 | W64: =+W63+W57 -> 412.8 | X64: =+X63+X57 -> 518.5 | Y64: =+Y63+Y57 -> 984.9 | Z64: =+Z63+Z57 -> 1202.9
B65: Equity | U65: 245.093 | V65: 838.379 | W65: 969.5 | X65: 1074.5 | Y65: 1391.8 | Z65: 1632.4
B66: Total Liabilties & Equity | T66: =+T64+T65 -> 0 | U66: =+U64+U65 -> 382.568 | V66: =+V64+V65 -> 1226.524 | W66: =+W64+W65 -> 1382.3 | X66: =+X64+X65 -> 1593 | Y66: =+Y64+Y65 -> 2376.7 | Z66: =+Z64+Z65 -> 2835.3
B68: Net Income | T68: -1.473 | U68: -27.524 | V68: -170.228 | W68: 57.7 | X68: 79.6 | Y68: 242.3 | Z68: 203.7
B69: SBCs | T69: 18.838 | U69: 48.631 | V69: 192.436 | W69: 38.3 | X69: 27.3 | Y69: 57.5 | Z69: 66.6
B70: Employee Benefits | T70: -0.143 | U70: 0.957 | V70: 1.121 | W70: 4.8 | X70: -7.5 | Y70: 5.2 | Z70: 4
B71: D&A | T71: 5.342 | U71: 12.091 | V71: 31.413 | W71: 46.4 | X71: 64.9 | Y71: 104.6 | Z71: 127.4
B72: Loss on Disposal of Assets | T72: 0 | U72: 0 | V72: 0 | W72: 0.9 | X72: 0.6 | Y72: 0.7 | Z72: 3.7
B73: Interest Income and Expenses | T73: 0.502 | U73: 0.602 | V73: 2.777 | W73: -0.8 | X73: -4.5 | Y73: -7.2 | Z73: -8.5
B74: Net Exchange Differences | T74: 1.518 | U74: 6.666 | V74: 15.183 | W74: -8.3 | X74: 102.9 | Y74: -70.9 | Z74: 165.6
B75: Income taxes | T75: 4.62 | U75: 3.083 | V75: 10.625 | W75: 20.2 | X75: -10.5 | Y75: 37.4 | Z75: 1.5
B76: Change in Receivables | T76: -21.481 | U76: -13.482 | V76: -46.993 | W76: -78.6 | X76: -46.9 | Y76: -30.1 | Z76: -96.1
B77: Change in Inventories | T77: -12.353 | U77: -61.305 | V77: -31.771 | W77: -273 | X77: -10 | Y77: -27.8 | Z77: -82.4
B78: Change in Payables | T78: 3.154 | U78: 25.564 | V78: 4.327 | W78: 65.8 | X78: -44.3 | Y78: 104 | Z78: -9.2
B79: Change in WC | T79: =+SUM(T76:T78) -> -30.68 | U79: =+SUM(U76:U78) -> -49.223 | V79: =+SUM(V76:V78) -> -74.437 | W79: =+SUM(W76:W78) -> -285.8 | X79: =+SUM(X76:X78) -> -101.2 | Y79: =+SUM(Y76:Y78) -> 46.1 | Z79: =+SUM(Z76:Z78) -> -187.7
B80: Change in other current A/L | T80: -2.677 | U80: -6.511 | V80: 8.095 | W80: -67.6 | X80: 93.4 | Y80: 95.7 | Z80: 25
B81: Change in Provisions | T81: 1.099 | U81: 1.674 | V81: 4.368 | W81: -7.4 | X81: 4.8 | Y81: 18 | Z81: -7.8
B82: Interest Received | T82: 0 | U82: 0 | V82: 0 | W82: 5.6 | X82: 11 | Y82: 22.5 | Z82: 30.1
B83: Taxes Paid | T83: -2.163 | U83: -5.174 | V83: -4.407 | W83: -31 | X83: -28.6 | Y83: -41.2 | Z83: -64
B84: CFFO | T84: =+SUM(T68:T75)+T79+SUM(T80:T83) -> -5.217 | U84: =+SUM(U68:U75)+U79+SUM(U80:U83) -> -14.728 | V84: =+SUM(V68:V75)+V79+SUM(V80:V83) -> 16.946 | W84: =+SUM(W68:W75)+W79+SUM(W80:W83) -> -227 | X84: =+SUM(X68:X75)+X79+SUM(X80:X83) -> 232.2 | Y84: =+SUM(Y68:Y75)+Y79+SUM(Y80:Y83) -> 510.7 | Z84: =+SUM(Z68:Z75)+Z79+SUM(Z80:Z83) -> 359.6
B85: CapEx | T85: -7.432 | U85: -10.986 | V85: -24.639 | W85: -60.3 | X85: -42.8 | Y85: -60.5 | Z85: -72.9
B86: Disposal of Intangibles | T86: 0 | U86: 0 | V86: 0 | W86: 0 | X86: 0 | Y86: 0.1 | Z86: 0
B87: Purchase of Intangibles | T87: =-1.785-0.321 -> -2.106 | U87: =-7.612-0.026 -> -7.638 | V87: =-11.6-0.2 -> -11.8 | W87: -22.7 | X87: -4.4 | Y87: -4.5 | Z87: -5.7
B88: CFFI | T88: =+SUM(T85:T87) -> -9.538 | U88: =+SUM(U85:U87) -> -18.624 | V88: =+SUM(V85:V87) -> -36.439 | W88: =+SUM(W85:W87) -> -83 | X88: =+SUM(X85:X87) -> -47.2 | Y88: =+SUM(Y85:Y87) -> -64.9 | Z88: =+SUM(Z85:Z87) -> -78.6
B89: Payment of Lease Liabilties | T89: =3-1.2-2 -> -0.2 | U89: =-(3+3.399) -> -6.399 | V89: -13.311 | W89: -15.4 | X89: -25.5 | Y89: -51.3 | Z89: -69.9
B90: Issuance of Stock | T90: 0 | U90: =133.266-1.476 -> 131.79 | V90: =0.071+618.191-6.836 -> 611.426 | W90: 0 | X90: 0 | Y90: 0.2 | Z90: 4.3
B91: Disposal of Treasury Shares | T91: -0.491 | U91: -0.595 | V91: =0.5-2.764 -> -2.264 | W91: 26.4 | X91: 10.1 | Y91: 10.9 | Z91: 8.6
B92: Interest Paid | T92: 0 | U92: 0 | V92: 0 | W92: -4.7 | X92: -6.5 | Y92: -15.3 | Z92: -21.5
B93: CFFF | T93: =+SUM(T89:T92) -> -0.691 | U93: =+SUM(U89:U92) -> 124.796 | V93: =+SUM(V89:V92) -> 595.851 | W93: =+SUM(W89:W92) -> 6.3 | X93: =+SUM(X89:X92) -> -21.9 | Y93: =+SUM(Y89:Y92) -> -55.5 | Z93: =+SUM(Z89:Z92) -> -78.5
B94: FX Effect | T94: -0.195 | U94: -0.969 | V94: -13.868 | W94: 21.5 | X94: -39.6 | Y94: 39.4 | Z94: -106.7
B95: Change in Cash | T95: =+SUM(T94,T93,T88,T84) -> -15.641 | U95: =+SUM(U94,U93,U88,U84) -> 90.475 | V95: =+SUM(V94,V93,V88,V84) -> 562.49 | W95: =+SUM(W94,W93,W88,W84) -> -282.2 | X95: =+SUM(X94,X93,X88,X84) -> 123.5 | Y95: =+SUM(Y94,Y93,Y88,Y84) -> 429.7 | Z95: =+SUM(Z94,Z93,Z88,Z84) -> 95.8
B96: Cash BoP | T96: =+T97-T95 -> 15.776 | U96: =+U97-U95 -> 0.135 | V96: =+V97-V95 -> 90.61 | W96: 653.1 | X96: 371 | Y96: 494.6 | Z96: 924.3
B97: Cash EoP | T97: =+U96 -> 0.135 | U97: =+V96 -> 90.61 | V97: =+W96 -> 653.1 | W97: =+X96 -> 371 | X97: =+Y96 -> 494.6 | Y97: =+Y95+Y96 -> 924.3 | Z97: 1019.9

Sheet KPIs
A1: Main
B2: Ratios | C2: 20 | D2: 21 | E2: 22 | F2: 23 | G2: 24 | H2: 25
B3: Price USD | C3: n.a. | D3: 38.68 | E3: 17.07 | F3: 26.76 | G3: 55.37 | H3: 41.05
B4: Price CHF | C4: n.a. | D4: =+D3*Main!$H$10 -> 32.878 | E4: =+E3*Main!$H$10 -> 14.5095 | F4: =+F3*Main!$H$10 -> 22.746 | G4: =+G3*Main!$H$10 -> 47.0645 | H4: =+H3*Main!$H$10 -> 34.8925
B5: Shares o/s | C5: n.a. | D5: =+Model!V24 -> 264.17121 | E5: =+Model!W24 -> 282.1965 | F5: =+Model!X24 -> 284.78246 | G5: =+Model!Y24 -> 289.63973 | H5: =+Model!Z24 -> 296.87335
B6: Market Cap | C6: n.a. | D6: =+D4*D5 -> 8685.421 | E6: =+E4*E5 -> 4094.53 | F6: =+F4*F5 -> 6477.6617 | G6: =+G4*G5 -> 13631.749 | H6: =+H4*H5 -> 10358.653
B7: Net Debt | C7: =+Model!U53-Model!U39+Model!U42 -> -66.231 | D7: =+Model!V53-Model!V39+Model!V42 -> -602.93 | E7: =+Model!W53-Model!W39+Model!W42 -> -306.8 | F7: =+Model!X53-Model!X39+Model!X42 -> -445.6 | G7: =+Model!Y53-Model!Y39+Model!Y42 -> -816.6 | H7: =+Model!Z53-Model!Z39+Model!Z42 -> -904
B8: EV | C8: n.a. | D8: =+D6+D7 -> 8082.491 | E8: =+E6+E7 -> 3787.73 | F8: =+F6+F7 -> 6032.0617 | G8: =+G6+G7 -> 12815.149 | H8: =+H6+H7 -> 9454.6535
A10: x | B10: Value Driver
B11: Capital Emloyed | C11: n.a. | D11: =+Model!V49+SUM(Model!V40,Model!V41,Model!V43)-Model!V51 -> 507.451 | E11: =+Model!W49+SUM(Model!W40,Model!W41,Model!W43)-Model!W51 -> 867 | F11: =+Model!X49+SUM(Model!X40,Model!X41,Model!X43)-Model!X51 -> 999.1 | G11: =+Model!Y49+SUM(Model!Y40,Model!Y41,Model!Y43)-Model!Y51 -> 1229.4 | H11: =+Model!Z49+SUM(Model!Z40,Model!Z41,Model!Z43)-Model!Z51 -> 1601.6 | J11: =Long Term Assets + Working Capital (Exclusive of cash)-Accounts Payables
B12: Invested Capital | C12: n.a. | D12: =+Model!V45+SUM(Model!V40:V41,Model!V43)-SUM(Model!V51:V54)+Model!V42+Model!V47 -> 215.674 | E12: =+Model!W45+SUM(Model!W40:W41,Model!W43)-SUM(Model!W51:W54)+Model!W42+Model!W47 -> 604.2 | F12: =+Model!X45+SUM(Model!X40:X41,Model!X43)-SUM(Model!X51:X54)+Model!X42+Model!X47 -> 539.9 | G12: =+Model!Y45+SUM(Model!Y40:Y41,Model!Y43)-SUM(Model!Y51:Y54)+Model!Y42+Model!Y47 -> 444.7 | H12: =+Model!Z45+SUM(Model!Z40:Z41,Model!Z43)-SUM(Model!Z51:Z54)+Model!Z42+Model!Z47 -> 497.5 | J12: =Net Working Capital + PP&E + Other Net Operating Assets (net of Liabilties) + (Intangibles)
B13: Invested Capital (exl. Intangibles) | C13: n.a. | D13: =+D12-Model!V47 -> 158.21 | E13: =+E12-Model!W47 -> 533.9 | F13: =+F12-Model!X47 -> 475.3 | G13: =+G12-Model!Y47 -> 386.4 | H13: =+H12-Model!Z47 -> 443.3
B14: Total Funds Invested | C14: n.a. | D14: =+D12+Model!V39+Model!V46 -> 1046.645 | E14: =+E12+Model!W39+Model!W46 -> 1126.8 | F14: =+F12+Model!X39+Model!X46 -> 1248.5 | G14: =+G12+Model!Y39+Model!Y46 -> 1692.6 | H14: =+H12+Model!Z39+Model!Z46 -> 2011.5 | J14: Invested Capital + Non-Operating Assets
B15: NOPAT | C15: n.a. | D15: =+Model!V15*(1-Model!V37) -> -150.4713 | E15: =+Model!W15*(1-Model!W37) -> 63.032991 | F15: =+Model!X15*(1-Model!X37) -> 207.69725 | G15: =+Model!Y15*(1-Model!Y37) -> 183.20923 | H15: =+Model!Z15*(1-Model!Z37) -> 374.34342 | J15: EBITA * (1-Marginal Tax Rate)
B16: Net Investment | C16: n.a. | D16: n.a. | E16: =+E14-D14 -> 80.155 | F16: =+F14-E14 -> 121.7 | G16: =+G14-F14 -> 444.1 | H16: =+H14-G14 -> 318.9 | J16: =Invested Capital (t+1)-Invested Capital (t)
B17: FCF | C17: n.a. | D17: n.a. | E17: =+E15-E16+SUM(Model!W69:W71) -> 72.377991 | F17: =+F15-F16+SUM(Model!X69:X71) -> 170.69725 | G17: =+G15-G16+SUM(Model!Y69:Y71) -> -93.590773 | H17: =+H15-H16+SUM(Model!Z69:Z71) -> 253.44342 | J17: =NOPAT + non-cash Expenses - Investments in Invested Capital
B18: Investment Rate | C18: n.a. | D18: n.a. | E18: =+E16/E15 -> 1.2716357 | F18: =+F16/F15 -> 0.58594902 | G18: =+G16/G15 -> 2.4240045 | H18: =+H16/H15 -> 0.85189156 | J18: =Net Investment/NOPAT
B19: Economic Profit | C19: n.a. | J19: =Invested Capital *(ROIC-WACC)
A21: x | B21: Efficency-Ratios
B22: Capital Turnover | C22: n.a. | D22: =+Model!V11/Model!V65 -> 0.86428692 | E22: =+Model!W11/Model!W65 -> 1.2605467 | F22: =+Model!X11/Model!X65 -> 1.6678455 | G22: =+Model!Y11/Model!Y65 -> 1.6656847 | H22: =+Model!Z11/Model!Z65 -> 1.8463612 | J22: =Revenue/Equity
B23: Return on Equity (ROE) | C23: n.a. | D23: =+Model!V21/Model!V65 -> -0.20301081 | E23: =+Model!W21/Model!W65 -> 0.059515214 | F23: =+Model!X21/Model!X65 -> 0.074080968 | G23: =+Model!Y21/Model!Y65 -> 0.17401926 | H23: =+Model!Z21/Model!Z65 -> 0.12478559 | J23: =Net Income/Book Value of Equity
B24: Return on Capital Employed (ROCE) | C24: n.a. | D24: =+Model!V15/KPIs!D11 -> -0.2780564 | E24: =+Model!W15/KPIs!E11 -> 0.098154556 | F24: =+Model!X15/KPIs!F11 -> 0.18046242 | G24: =+Model!Y15/KPIs!G11 -> 0.17203514 | H24: =+Model!Z15/KPIs!H11 -> 0.23545205 | J24: =EBIT/Capital Employed
B25: Return on Capital Invested (ROIC) | C25: n.a. | D25: =+D15/D12 -> -0.69767938 | E25: =+E15/E12 -> 0.10432471 | F25: =+F15/F12 -> 0.38469578 | G25: =+G15/G12 -> 0.41198387 | H25: =+H15/H12 -> 0.75244909 | J25: =NOPAT/Invested Capital
B26: ROIC without Intangibles | C26: n.a. | D26: =+D15/D13 -> -0.95108592 | E26: =+E15/E13 -> 0.11806142 | F26: =+F15/F13 -> 0.43698138 | G26: =+G15/G13 -> 0.47414396 | H26: =+H15/H13 -> 0.84444715 | J26: =NOPAT/(Invested Capital exclusive of Intangibles)
B27: Decomposed ROIC | C27: n.a. | J27: = ROIC = (1-operating cash tax)* (EBITA/Revenues) * (Revenue/Invested Capital)
B29: Retention Rate | C29: n.a. | D29: =1-(0/Model!V21)% -> 1 | E29: =1-(0/Model!W21)% -> 1 | F29: =1-(0/Model!X21)% -> 1 | G29: =1-(0/Model!Y21)% -> 1 | H29: =1-(0/Model!Z21)% -> 1 | J29: =1 - Dividends/Net Income
B30: Reinvestment Rate | C30: n.a. | D30: =-(Model!V85+Model!V79)/KPIs!D15 -> -0.65843784 | E30: =-(Model!W85+Model!W79)/KPIs!E15 -> 5.4907755 | F30: =-(Model!X85+Model!X79)/KPIs!F15 -> 0.69331683 | G30: =-(Model!Y85+Model!Y79)/KPIs!G15 -> 0.078598661 | H30: =-(Model!Z85+Model!Z79)/KPIs!H15 -> 0.69615221 | J30: =Net CapEx + Change in WC / EBIT * (1-t)
B31: Epected Growth in Net Income | C31: n.a. | D31: =+D29*D23 -> -0.20301081 | E31: =+E29*E23 -> 0.059515214 | F31: =+F29*F23 -> 0.074080968 | G31: =+G29*G23 -> 0.17401926 | H31: =+H29*H23 -> 0.12478559 | J31: =ROE * Retention Rate
B32: Expected Growth in NOPAT | C32: n.a. | D32: =+D30*D26 -> 0.62623096 | E32: =+E30*E26 -> 0.64824874 | F32: =+F30*F26 -> 0.30296655 | G32: =+G30*G26 -> 0.037267081 | H32: =+H30*H26 -> 0.58786375 | J32: =ROIC * Reinvestment Rate
A34: x | B34: Finacial Stability Ratios
B35: Equity/Debt Ratio | C35: n.a. | J35: =Book Value of Equtiy/Book Value of Debt
B36: Gearing | C36: n.a. | J36: =(Debt - Cash (Net Debt))/Book Value of Equity
B37: Interest Coverage Ratio | C37: n.a. | J37: =EBIT/Interest Expenses
B38: Net Debt / EBITDA | C38: n.a. | J38: =Net Debt/EBITDA
B39: Cash Burn Rate | C39: n.a. | J39: =Book Value of Equity/Absolute value of Loss
A41: x | B41: WC-Managment Ratios
B42: Debitor-Duration | C42: n.a. | D42: =+Model!V40/Model!V11*360 -> 49.31692 | E42: =+Model!W40/Model!W11*360 -> 51.43278 | F42: =+Model!X40/Model!X11*360 -> 41.140561 | G42: =+Model!Y40/Model!Y11*360 -> 38.215934 | H42: =+Model!Z40/Model!Z11*360 -> 36.47777 | J42: =Accounts Receivables/Revenue*360
B43: Creditor-Duration | C43: n.a. | D43: =+Model!V51/Model!V11*360 -> 22.823682 | E43: =+Model!W51/Model!W11*360 -> 32.697815 | F43: =+Model!X51/Model!X11*360 -> 13.077395 | G43: =+Model!Y51/Model!Y11*360 -> 25.855152 | H43: =+Model!Z51/Model!Z11*360 -> 18.489715 | J43: =Accounts Payable/Revenue*360
B44: Inventory Intensity | C44: n.a. | D44: =+Model!V41/Model!V50 -> 0.10851216 | E44: =+Model!W41/Model!W50 -> 0.28621039 | F44: =+Model!X41/Model!X50 -> 0.22379159 | G44: =+Model!Y41/Model!Y50 -> 0.17638643 | H44: =+Model!Z41/Model!Z50 -> 0.14805149 | J44: =Inventory/Balance Sheet Total
B45: Invetory Turnover | C45: n.a. | D45: =+Model!V12/Model!V41 -> 2.1933551 | E45: =+Model!W12/Model!W41 -> 1.3579373 | F45: =+Model!X12/Model!X41 -> 2.0330996 | G45: =+Model!Y12/Model!Y41 -> 2.1770038 | H45: =+Model!Z12/Model!Z41 -> 2.6686517 | J45: =Cogs/Inventory
B46: Storage-Duration | C46: n.a. | D46: =360/D45 -> 164.13211 | E46: =360/E45 -> 265.10797 | F46: =360/F45 -> 177.06954 | G46: =360/G45 -> 165.36489 | H46: =360/H45 -> 134.89958 | J46: =360/Inventory Turnover
B47: Cash Conversion Cycle | C47: n.a. | D47: =+D42+D46-D43 -> 190.62535 | E47: =+E42+E46-E43 -> 283.84293 | F47: =+F42+F46-F43 -> 205.1327 | G47: =+G42+G46-G43 -> 177.72567 | H47: =+H42+H46-H43 -> 152.88764 | J47: =Debitor Duration + Storage Duration - Creditor Duration
A49: x | B49: Multipliers
B50: Equitymultiples
B51: P/E Ratio | C51: n.a. | D51: =+D6/Model!V21 -> -51.030676 | E51: =+E6/Model!W21 -> 70.962392 | F51: =+F6/Model!X21 -> 81.37766 | G51: =+G6/Model!Y21 -> 56.283027 | H51: =+H6/Model!Z21 -> 50.852496 | J51: =Share Price/EPS
B52: PEG Ratio | C52: n.a. | D52: n.a. | E52: =+E51/((Model!W21/Model!V21-1)*100) -> -0.52996047 | F52: =+F51/((Model!X21/Model!W21-1)*100) -> 2.1440598 | G52: =+G51/((Model!Y21/Model!X21-1)*100) -> 0.27553068 | H52: =+H51/((Model!Z21/Model!Y21-1)*100) -> -3.1990843 | J52: =P/E Ratio / Growth
B53: P/B Ratio | C53: n.a. | D53: =+KPIs!D6/Model!V50 -> 7.0240561 | E53: =+KPIs!E6/Model!W50 -> 2.9623282 | F53: =+KPIs!F6/Model!X50 -> 4.0663288 | G53: =+KPIs!G6/Model!Y50 -> 5.7358197 | H53: =+KPIs!H6/Model!Z50 -> 3.6532017 | J53: =Market Cap/Book Vakue of Equity
B54: P/Cf Ratio | C54: n.a. | D54: =+D6/Model!V84 -> 512.53517 | E54: =+E6/Model!W84 -> -18.037577 | F54: =+F6/Model!X84 -> 27.896907 | G54: =+G6/Model!Y84 -> 26.692283 | H54: =+H6/Model!Z84 -> 28.806044 | J54: =Share Price/Cashflow per share
B55: P/R Ratio | C55: n.a. | D55: =+D6/Model!V11 -> 11.986504 | E55: =+E6/Model!W11 -> 3.3504051 | F55: =+F6/Model!X11 -> 3.6145649 | G55: =+G6/Model!Y11 -> 5.8800626 | H55: =+H6/Model!Z11 -> 3.4368459 | J55: =Share Price/Revenue per Share
B56: Entitymultiples
B57: EV/EBITDA | C57: n.a. | D57: =+D8/(Model!V15+Model!V71) -> -73.686863 | E57: =+E8/(Model!W15+Model!W71) -> 28.804031 | F57: =+F8/(Model!X15+Model!X71) -> 24.600578 | G57: =+G8/(Model!Y15+Model!Y71) -> 40.54144 | H57: =+H8/(Model!Z15+Model!Z71) -> 18.740641 | J57: =EV/EBITDA
B58: EV/EBIT | C58: n.a. | D58: =+D8/Model!V15 -> -57.282006 | E58: =+E8/Model!W15 -> 44.509166 | F58: =+F8/Model!X15 -> 33.455695 | G58: =+G8/Model!Y15 -> 60.591721 | H58: =+H8/Model!Z15 -> 25.072006 | J58: =EV/EBIT
B59: EV/FCF | C59: n.a. | D59: n.a. | E59: =+E8/E17 -> 52.332622 | F59: =+F8/F17 -> 35.337779 | G59: =+G8/G17 -> -136.92748 | H59: =+H8/H17 -> 37.304789 | J59: =EV/FCF
B60: EV/Sales | C60: n.a. | D60: =+D8/Model!V11 -> 11.154418 | E60: =+E8/Model!W11 -> 3.0993618 | F60: =+F8/Model!X11 -> 3.3659181 | G60: =+G8/Model!Y11 -> 5.5278217 | H60: =+H8/Model!Z11 -> 3.1369122 | J60: =EV/Revenue

Sheet CoC
A1: Main
B3: Cost of Capital
A4: x | B4: Cost of Equity (CAPM)
B5: Riskfree Rate
B6: Expected Inflation | H6: =(1+Nominal Rate)/(1+Real Rate)-1
B7: Average Real Interest Rate | H7: = Average Interest Rate of the Past
B8: Riskfree Rate | F8: =F6+F7 -> 0 | H8: =Goverment Bond or Expected Inflation + Average Real Interest Rate
A10: x | B10: Adjustments for Industry/Company Risk
B11: Raw Beta | H11: =Raw beta slope of regression line aginst total market -> Ri= alpha + beta*Rm + standard error
B12: Debt to Value Ratio | H12: Value of Debt/Enterpries Value
B13: Unlevered Beta | H13: = Raw Beta* Debt-to-Equity Ratio (Book Value)
B14: Unlevered Industry Beta | H14: =Median of Peer Group
B15: Levered Industry Beta | H15: =Unlevered Industry Beta * Market Value of Debt to Market Value of Equity
A17: x | B17: Expected Equity Risk Premium
B18: Estimated Future Market Return | H18: = 1/P/E * (1.g/ROE) + g , g = real growth in GDP, P/E => P/E ratio for S&P500 or MSCI World Index, ROE = Average ROE in S&P500 or MSCI World
B19: Riskfree Rate
B20: Expected Equity Risk Premium | F20: =F18-F19 -> 0
A22: x | B22: Cost of Equity (CAPM) | F22: =F8+F15*F20 -> 0 | H22: => ER(i)=rf+beta(i)*(Er(m)-rf)
A25: x | B25: Cost of Debt
B26: Yield to Maturity on Trading Bonds | H26: => Price = Coupon/(1+YTM)+Coupon(1+YTM)^2 + … + (Face Value + Coupon)/(1+YTM)^n => solve for YTM
B27: or
B28: Riskfree Rate
B29: Credit Default Spread
B30: Country Rsik Premium
A32: x | B32: Cost of Debt | F32: =F28+F29+F30 -> 0
A34: x | B34: Capital Structure
B35: Market Value of Debt
B36: Market Value of Equity
B37: Total Enterprise Value | F37: =F35+F36 -> 0
B39: Marginal Tax Rate
A41: x | B41: WACC | F41: =(F32*(F35/F37)*(1-F39))+((F36/F38)*F22) -> #DIV/0! | H41: => WACC = (D/D+E)*kd * (1-t) + (E/D+E) * ke
I47: =SLOPE(H48:H52,K48:K52) -> #DIV/0!
H48: Change

Sheet DCF
A1: Main | B1: ON DCF
B3: Ticker | E3: ONON | G3: Share Price | J3: =+Main!H3 -> 26.2225 | L3: Share Price | O3: =+J3 -> 26.2225
B4: Date | E4: =+TODAY() -> 46245 | G4: Fair Share Price | J4: =V62 -> 100.63137 | L4: Scneario DCF Price | O4: =+J15+O15+T15 -> 0
B5: End of FY | E5: 46022 | G5: Implied Upside | J5: =J4/J3-1 -> 2.8375964 | L5: Implied Upside | O5: =O4/O3-1 -> -1
A7: x | B7: Assumptions
B9: Switches | G9: Conservative Case | L9: Base Case | Q9: Optimistic Case
B10: Assuptions | G10: Assuptions | I10: Year | J10: Metic | L10: Assuptions | N10: Year | O10: Metic | Q10: Assuptions | S10: Year | T10: Metic
B11: Revenue | E11: 2 | G11: Revenue | L11: Revenue | O11: -0.02 | Q11: Revenue
B12: EBIT | E12: 2 | G12: EBIT | L12: EBIT | O12: 0.1 | Q12: EBIT
B13: WACC | E13: 2 | G13: Implied Share Price | L13: Implied Share Price | Q13: Implied Share Price
B14: TGR | E14: 2 | G14: Probability | L14: Probability | Q14: Probability
B15: ROIC | E15: 2 | G15: Implied Share Price * p | L15: Implied Share Price * p | Q15: Implied Share Price * p
B17: Valuation
B18: WACC | E18: =CHOOSE(E13,J18,O18,T18) -> 0.1 | G18: WACC | L18: WACC | O18: 0.1 | Q18: WACC
B19: TGR | E19: =CHOOSE(E14,J19,O19,T19) -> 0.03 | G19: TGR | L19: TGR | O19: 0.03 | Q19: TGR
B20: RONIC | E20: =CHOOSE(E15,J20,O20,T20) -> 0.15 | G20: RONIC | L20: RONIC | O20: 0.15 | Q20: RONIC
A24: x | B24: Model | G24: 19 | H24: =G24+1 -> 20 | I24: =H24+1 -> 21 | J24: =I24+1 -> 22 | K24: =J24+1 -> 23 | L24: =K24+1 -> 24 | M24: =L24+1 -> 25 | N24: =M24+1 -> 26 | O24: =N24+1 -> 27 | ... V24: =U24+1 -> 34
B25: Revenue | G25: n.a. | H25: =+Model!U11 -> 425.29 | I25: =+Model!V11 -> 724.6 | J25: =+Model!W11 -> 1222.1 | K25: =+Model!X11 -> 1792.1 | L25: =+Model!Y11 -> 2318.3 | M25: =L25*(1+M26) -> 2619.679 | N25: =M25*(1+N26) -> 3274.5988 | O25: =N25*(1+O26) -> 4076.8754 | P25: =O25*(1+P26) -> 5055.7332 | Q25: =P25*(1+Q26) -> 6245.3372 | R25: =Q25*(1+R26) -> 7685.4622 | S25: =R25*(1+S26) -> 8838.2815 | T25: =S25*(1+T26) -> 10164.024 | ... V25: =U25*(1+V26) -> 11739.447
B26: Growth (%) | G26: n.a. | H26: n.a. | I26: =I25/H25-1 -> 0.7037786 | J26: =J25/I25-1 -> 0.6865857 | K26: =K25/J25-1 -> 0.46641028 | L26: =L25/K25-1 -> 0.29362201 | M26: {=OFFSET(M26,$E$11,,)} -> 0.13 | N26: {=OFFSET(N26,$E$11,,)} -> 0.25 | O26: {=OFFSET(O26,$E$11,,)} -> 0.245 | P26: {=OFFSET(P26,$E$11,,)} -> 0.2401 | Q26: {=OFFSET(Q26,$E$11,,)} -> 0.235298 | R26: {=OFFSET(R26,$E$11,,)} -> 0.23059204 | S26: {=OFFSET(S26,$E$11,,)} -> 0.15 | T26: {=OFFSET(T26,$E$11,,)} -> 0.15 | ... V26: {=OFFSET(V26,$E$11,,)} -> 0.05
B27: Conservative Case
B28: Base Case | M28: 0.13 | N28: 0.25 | O28: =+N28*(1+$O$11) -> 0.245 | P28: =+O28*(1+$O$11) -> 0.2401 | Q28: =+P28*(1+$O$11) -> 0.235298 | R28: =+Q28*(1+$O$11) -> 0.23059204 | S28: 0.15 | T28: 0.15 | U28: 0.1 | V28: 0.05
B29: Optimisitic Case
B31: EBIT | G31: n.a. | H31: =+Model!U15 -> -17.099 | I31: =+Model!V15 -> -141.1 | J31: =+Model!W15 -> 85.1 | K31: =+Model!X15 -> 180.3 | L31: =+Model!Y15 -> 211.5 | M31: =M32*M25 -> 261.9679 | N31: =N32*N25 -> 491.18981 | O31: =O32*O25 -> 611.53132 | P31: =P32*P25 -> 1011.1466 | Q31: =Q32*Q25 -> 1561.3343 | R31: =R32*R25 -> 2305.6387 | S31: =S32*S25 -> 3093.3985 | T31: =T32*T25 -> 4065.6095 | ... V31: =V32*V25 -> 4695.779
B32: % of Sales | G32: n.a. | H32: =H31/H25 -> -0.040205507 | I32: =I31/I25 -> -0.19472813 | J32: =J31/J25 -> 0.069634236 | K32: =K31/K25 -> 0.10060822 | L32: =L31/L25 -> 0.091230643 | M32: {=OFFSET(M32,$E$12,,)} -> 0.1 | N32: {=OFFSET(N32,$E$12,,)} -> 0.15 | O32: {=OFFSET(O32,$E$12,,)} -> 0.15 | P32: {=OFFSET(P32,$E$12,,)} -> 0.2 | Q32: {=OFFSET(Q32,$E$12,,)} -> 0.25 | R32: {=OFFSET(R32,$E$12,,)} -> 0.3 | S32: {=OFFSET(S32,$E$12,,)} -> 0.35 | T32: {=OFFSET(T32,$E$12,,)} -> 0.4 | ... V32: {=OFFSET(V32,$E$12,,)} -> 0.4
B33: Conservative Case
B34: Base Case | M34: 0.1 | N34: 0.15 | O34: 0.15 | P34: 0.2 | Q34: 0.25 | R34: 0.3 | S34: 0.35 | T34: 0.4 | U34: 0.4 | V34: 0.4
B35: Optimisitic Case
B37: Taxes | G37: n.a. | H37: =+Model!U20 -> 3.083 | I37: =+Model!V20 -> 10.6 | J37: =+Model!W20 -> 20.2 | K37: =+Model!X20 -> -10.5 | L37: =+Model!Y20 -> 37.4 | M37: =M38*M31 -> 23.577111 | N37: =N38*N31 -> 44.207083 | O37: =O38*O31 -> 55.037818 | P37: =P38*P31 -> 91.003198 | Q37: =Q38*Q31 -> 140.52009 | R37: =R38*R31 -> 207.50748 | S37: =S38*S31 -> 278.40587 | T37: =T38*T31 -> 365.90485 | ... V37: =V38*V31 -> 422.62011
B38: Tax Rate (%) | G38: n.a. | H38: =H37/H31 -> -0.18030294 | I38: =I37/I31 -> -0.075124026 | J38: =J37/J31 -> 0.2373678 | K38: =K37/K31 -> -0.058236273 | L38: =L37/L31 -> 0.17683215 | M38: 0.09 | N38: 0.09 | O38: 0.09 | P38: 0.09 | Q38: 0.09 | R38: 0.09 | S38: 0.09 | T38: 0.09 | U38: 0.09 | V38: 0.09
B40: Nopat | G40: n.a. | H40: =H31-H37 -> -20.182 | I40: =I31-I37 -> -151.7 | J40: =J31-J37 -> 64.9 | K40: =K31-K37 -> 190.8 | L40: =L31-L37 -> 174.1 | M40: =M31-M37 -> 238.39079 | N40: =N31-N37 -> 446.98273 | O40: =O31-O37 -> 556.4935 | ... V40: =V31-V37 -> 4273.1589
B42: D&A and other non-cash Expenses | G42: n.a. | H42: =+Model!U71 -> 12.091 | I42: =+Model!V71 -> 31.413 | J42: =+Model!W71 -> 46.4 | K42: =+Model!X71 -> 64.9 | L42: =+Model!Y71 -> 104.6 | M42: =M43*M25 -> 104.78716 | N42: =N43*N25 -> 130.98395 | O42: =O43*O25 -> 163.07502 | P42: =P43*P25 -> 202.22933 | Q42: =Q43*Q25 -> 249.81349 | R42: =R43*R25 -> 307.41849 | S42: =S43*S25 -> 353.53126 | T42: =T43*T25 -> 406.56095 | ... V42: =V43*V25 -> 469.5779
B43: % of Sales | G43: n.a. | H43: =H42/H25 -> 0.028430012 | I43: =I42/I25 -> 0.043352194 | J43: =J42/J25 -> 0.037967433 | K43: =K42/K25 -> 0.036214497 | L43: =L42/L25 -> 0.045119268 | M43: 0.04 | N43: 0.04 | O43: 0.04 | P43: 0.04 | Q43: 0.04 | R43: 0.04 | S43: 0.04 | T43: 0.04 | U43: 0.04 | V43: 0.04
B45: CapEx | G45: n.a. | H45: =+SUM(Model!U85:U86) -> -10.986 | I45: =+SUM(Model!V85:V86) -> -24.639 | J45: =+SUM(Model!W85:W86) -> -60.3 | K45: =+SUM(Model!X85:X86) -> -42.8 | L45: =+SUM(Model!Y85:Y86) -> -60.4 | M45: =M46*M25 -> -91.688765 | N45: =N46*N25 -> -114.61096 | O45: =O46*O25 -> -142.69064 | P45: =P46*P25 -> -176.95066 | Q45: =Q46*Q25 -> -218.5868 | R45: =R46*R25 -> -268.99118 | S45: =S46*S25 -> -309.33985 | T45: =T46*T25 -> -355.74083 | ... V45: =V46*V25 -> -410.88066
B46: % of Sales | G46: n.a. | H46: =H45/H25 -> -0.025831785 | I46: =I45/I25 -> -0.034003588 | J46: =J45/J25 -> -0.049341298 | K46: =K45/K25 -> -0.023882596 | L46: =L45/L25 -> -0.026053574 | M46: -0.035 | N46: -0.035 | O46: -0.035 | P46: -0.035 | Q46: -0.035 | R46: -0.035 | S46: -0.035 | T46: -0.035 | U46: -0.035 | V46: -0.035
B48: Change in WC | G48: n.a. | H48: =+Model!U79 -> -49.223 | I48: =+Model!V79 -> -74.437 | J48: =+Model!W79 -> -285.8 | K48: =+Model!X79 -> -101.2 | L48: =+Model!Y79 -> 46.1 | M48: =M49*M25 -> -130.98395 | N48: =N49*N25 -> -163.72994 | O48: =O49*O25 -> -203.84377 | P48: =P49*P25 -> -252.78666 | Q48: =Q49*Q25 -> -312.26686 | R48: =R49*R25 -> -384.27311 | S48: =S49*S25 -> -441.91408 | T48: =T49*T25 -> -508.20119 | ... V48: =V49*V25 -> -586.97237
B49: % of Sales | G49: n.a. | H49: =H48/H25 -> -0.11573985 | I49: =I48/I25 -> -0.1027284 | J49: =J48/J25 -> -0.23385975 | K49: =K48/K25 -> -0.056470063 | L49: =L48/L25 -> 0.019885261 | M49: -0.05 | N49: -0.05 | O49: -0.05 | P49: -0.05 | Q49: -0.05 | R49: -0.05 | S49: -0.05 | T49: -0.05 | U49: -0.05 | V49: -0.05
B51: Unlevered Free Cashflow | G51: n.a. | H51: =H40+H42+H45+H48 -> -68.3 | I51: =I40+I42+I45+I48 -> -219.363 | J51: =J40+J42+J45+J48 -> -234.8 | K51: =K40+K42+K45+K48 -> 111.7 | L51: =L40+L42+L45+L48 -> 264.4 | M51: =M40+M42+M45+M48 -> 120.50523 | N51: =N40+N42+N45+N48 -> 299.62579 | O51: =O40+O42+O45+O48 -> 373.0341 | ... V51: =V40+V42+V45+V48 -> 3744.8837
B52: Present Value of unlevered FC | M52: =(M51/(1+$E$18)^M53)*M53 -> 69.772643 | N52: =N51/(1+$E$18)^N53 -> 256.90703 | O52: =O51/(1+$E$18)^O53 -> 290.77205 | P52: =P51/(1+$E$18)^P53 -> 490.81311 | Q52: =Q51/(1+$E$18)^Q53 -> 734.2391 | R52: =R51/(1+$E$18)^R53 -> 1026.1974 | S52: =S51/(1+$E$18)^S53 -> 1286.9407 | T52: =T51/(1+$E$18)^T53 -> 1569.2677 | U52: =U51/(1+$E$18)^U53 -> 1569.2677 | V52: =V51/(1+$E$18)^V53 -> 1497.9374
B53: Discount Period | M53: =YEARFRAC(E4,E5) -> 0.61388889 | N53: =M53+1 -> 1.6138889 | O53: =N53+1 -> 2.6138889 | P53: =O53+1 -> 3.6138889 | Q53: =P53+1 -> 4.6138889 | R53: =Q53+1 -> 5.6138889 | S53: =R53+1 -> 6.6138889 | T53: =S53+1 -> 7.6138889 | U53: =T53+1 -> 8.6138889 | V53: =U53+1 -> 9.6138889
B54: Sum of Present Value | V54: =SUM(M52:V52) -> 8792.1149
B55: Terminal Value | V55: =+(V40*(1+E19))*(1-(E19/E20))/(E18-E19) -> 50301.184 | X55: => CV(t) = NOPAT(t+1)*(1-g/RONIC)/(WACC - g) => equal pertuity formula: CV = FCF*(1+g) /(WACC-g)
B56: Present Value of TV | V56: =V55/(1+E18)^V53 -> 20120.258
B57: Enterprise Value | V57: =V54+V56 -> 28912.372
B58: (+) Cash and other non-operating assets | V58: =+Main!H6 -> 1020.4
B59: (-) Debt and other non-equity claims | V59: =+Main!H7 -> 58
B60: Equity Value | V60: =V57+V58-V59 -> 29874.772
B61: Number of Shares | V61: =+Main!H4 -> 296.87335
B62: Share Price | V62: =V60/V61 -> 100.63137
A66: x | B66: Sensitivity Analysis
C68: TGR | N68: ROINC
B69: WACC | C69: =+J4 -> 100.63137 | M69: WACC | N69: =+J4 -> 100.63137
